Workbook
Name _75: OFFSET('Buy List'!$V$3,'Buy List'!$Q$4*'Buy List'!$Q$27,,COUNT('Buy List'!$V$3:$V$502),)
Name _80: OFFSET('Buy List'!$W$3,'Buy List'!$Q$4*'Buy List'!$Q$27,,COUNT('Buy List'!$W$3:$W$502),)
Name _85: OFFSET('Buy List'!$X$3,'Buy List'!$Q$4*'Buy List'!$Q$27,,COUNT('Buy List'!$X$3:$X$502),)
Name _90: OFFSET('Buy List'!$Y$3,'Buy List'!$Q$4*'Buy List'!$Q$27,,COUNT('Buy List'!$Y$3:$Y$502),)
Name KeepList: Table1[]
Name Prob: OFFSET('Buy List'!$U$3,'Buy List'!$Q$4*'Buy List'!$Q$27,,COUNT('Buy List'!$U$3:$U$502),)
Name Spectrum: OFFSET('Buy List'!$T$3,'Buy List'!$Q$4*'Buy List'!$Q$27,,COUNT('Buy List'!$T$3:$T$502),)

Sheet Purchase Log
P1: Shipping | Q1: Price | R1: Tax
P2: =SUM(G:G) -> 197.81 | Q2: =SUM(F:F) -> 1327.41 | R2: =SUM(H:H) -> 149.485
B3: Status | C3: Seller | D3: Date Purchased | E3: Show# | F3: Price | G3: Shipping | H3: Tax | I3: Player | J3: ID | K3: Item # | L3: Link | M3: TEXT | N3: CONCAT | O3: WhatNot Total | P3: Adjusted Shipping | Q3: Adjusted Price/Shipping | R3: Adjusted Tax | S3: Adjusted Total | T3: Value | U3: Variance | V3: Count | W3: Set | X3: Description | Y3: Notes | AB3: Row Labels | AC3: Sum of Variance
B4: R | C4: Hoot2000 | D4: 46145 | E4: 33 | F4: 7 | G4: 4.11 | H4: 1.14 | I4: Wembanyama | J4: 6059255 | K4: 108 | L4: https://www.whatnot.com/order/Hqs3wb8GAkuyHj9LA3xEdv | M4: whatnot.com/order/Hqs3wb8GAkuyHj9LA3xEdv $7.00 + $1.14 (Shared Shipping) + $0.83 Tax = Total of $8.97 | N4: =IFERROR(_xlfn.TEXTAFTER(L4,"https://www."),"")&CHAR(10)&_xlfn.CONCAT(TEXT(F4,"$0.00")," + ",TEXT(P4,"$0.00")," (Shared Shipping) + ",TEXT(R4,"$0.00")," Tax = Total of ",TEXT(S4,"$0.00")) -> whatnot.com/order/Hqs3wb8GAkuyHj9LA3xEdv $7.00 + $1.14 (Shared Shipping) + $0.83 Tax = Total of $8.97 | O4: =SUM(F4:H4) -> 12.25 | P4: =SUMIFS(G:G,C:C,C4,D:D,D4)/COUNTIFS(C:C,C4,D:D,D4) -> 1.1375 | Q4: =+F4+P4 -> 8.1375 | R4: =IF(H4=0,0,Q4*0.1025) -> 0.83409375 | S4: =+Q4+R4 -> 8.9715937 | T4: =IFERROR(_xlfn.XLOOKUP(J4,Collection!A:A,Collection!D:D,0)/100/_xlfn.XLOOKUP(J4,Collection!A:A,Collection!J:J,0),_xlfn.XLOOKUP(J4,Sold!A:A,Sold!D:D,0)/100/_xlfn.XLOOKUP(J4,Sold!A:A,Sold!J:J,0)) -> 6.47 | U4: =IFERROR(T4-S4,0) -> -2.5015937 | V4: =COUNTIF(Collection!A:A,J4)+COUNTIF(Sold!A:A,J4) -> 1 | W4: =IFERROR(_xlfn.TEXTAFTER(_xlfn.XLOOKUP(J4,Collection!A:A,Collection!C:C,),"Cards "),_xlfn.TEXTAFTER(_xlfn.XLOOKUP(J4,Sold!A:A,Sold!C:C,),"Cards ")) -> 2023 Panini Hoops | X4: =IFERROR(_xlfn.XLOOKUP(J4,Collection!A:A,Collection!B:B,),_xlfn.XLOOKUP(J4,Sold!A:A,Sold!B:B,)) -> Victor Wembanyama #298 | Y4: . | AB4: jaytheselller | AC4: 30.518475
B5: R | C5: Hoot2000 | D5: 46145 | E5: 35 | F5: 8 | G5: 0.44 | H5: 0.87 | I5: Wembanyama | J5: 12415755 | K5: 90 | L5: https://www.whatnot.com/order/ATFJnWBvkv75frTYPbgk5o | M5: whatnot.com/order/ATFJnWBvkv75frTYPbgk5o $8.00 + $1.14 (Shared Shipping) + $0.94 Tax = Total of $10.07 | N5: =IFERROR(_xlfn.TEXTAFTER(L5,"https://www."),"")&CHAR(10)&_xlfn.CONCAT(TEXT(F5,"$0.00")," + ",TEXT(P5,"$0.00")," (Shared Shipping) + ",TEXT(R5,"$0.00")," Tax = Total of ",TEXT(S5,"$0.00")) -> whatnot.com/order/ATFJnWBvkv75frTYPbgk5o $8.00 + $1.14 (Shared Shipping) + $0.94 Tax = Total of $10.07 | O5: =SUM(F5:H5) -> 9.31 | P5: =SUMIFS(G:G,C:C,C5,D:D,D5)/COUNTIFS(C:C,C5,D:D,D5) -> 1.1375 | Q5: =+F5+P5 -> 9.1375 | R5: =IF(H5=0,0,Q5*0.1025) -> 0.93659375 | S5: =+Q5+R5 -> 10.074094 | T5: =IFERROR(_xlfn.XLOOKUP(J5,Collection!A:A,Collection!D:D,0)/100/_xlfn.XLOOKUP(J5,Collection!A:A,Collection!J:J,0),_xlfn.XLOOKUP(J5,Sold!A:A,Sold!D:D,0)/100/_xlfn.XLOOKUP(J5,Sold!A:A,Sold!J:J,0)) -> 9.49 | U5: =IFERROR(T5-S5,0) -> -0.58409375 | V5: =COUNTIF(Collection!A:A,J5)+COUNTIF(Sold!A:A,J5) -> 1 | W5: =IFERROR(_xlfn.TEXTAFTER(_xlfn.XLOOKUP(J5,Collection!A:A,Collection!C:C,),"Cards "),_xlfn.TEXTAFTER(_xlfn.XLOOKUP(J5,Sold!A:A,Sold!C:C,),"Cards ")) -> 2026 Topps Collectors Kit | X5: =IFERROR(_xlfn.XLOOKUP(J5,Collection!A:A,Collection!B:B,),_xlfn.XLOOKUP(J5,Sold!A:A,Sold!B:B,)) -> Victor Wembanyama [Wave] #NBA-7 | Y5: . | AB5: jayspopup | AC5: 25.520133
B6: R | C6: Hoot2000 | D6: 46145 | E6: 44 | F6: 3 | G6: 0 | H6: 0.31 | I6: James | J6: 10826665 | K6: 55 | L6: https://www.whatnot.com/order/R4eDqBQtSQwNRiU33sZje5 | M6: whatnot.com/order/R4eDqBQtSQwNRiU33sZje5 $3.00 + $1.14 (Shared Shipping) + $0.42 Tax = Total of $4.56 | N6: =IFERROR(_xlfn.TEXTAFTER(L6,"https://www."),"")&CHAR(10)&_xlfn.CONCAT(TEXT(F6,"$0.00")," + ",TEXT(P6,"$0.00")," (Shared Shipping) + ",TEXT(R6,"$0.00")," Tax = Total of ",TEXT(S6,"$0.00")) -> whatnot.com/order/R4eDqBQtSQwNRiU33sZje5 $3.00 + $1.14 (Shared Shipping) + $0.42 Tax = Total of $4.56 | O6: =SUM(F6:H6) -> 3.31 | P6: =SUMIFS(G:G,C:C,C6,D:D,D6)/COUNTIFS(C:C,C6,D:D,D6) -> 1.1375 | Q6: =+F6+P6 -> 4.1375 | R6: =IF(H6=0,0,Q6*0.1025) -> 0.42409375 | S6: =+Q6+R6 -> 4.5615938 | T6: =IFERROR(_xlfn.XLOOKUP(J6,Collection!A:A,Collection!D:D,0)/100/_xlfn.XLOOKUP(J6,Collection!A:A,Collection!J:J,0),_xlfn.XLOOKUP(J6,Sold!A:A,Sold!D:D,0)/100/_xlfn.XLOOKUP(J6,Sold!A:A,Sold!J:J,0)) -> 3.25 | U6: =IFERROR(T6-S6,0) -> -1.3115938 | V6: =COUNTIF(Collection!A:A,J6)+COUNTIF(Sold!A:A,J6) -> 1 | W6: =IFERROR(_xlfn.TEXTAFTER(_xlfn.XLOOKUP(J6,Collection!A:A,Collection!C:C,),"Cards "),_xlfn.TEXTAFTER(_xlfn.XLOOKUP(J6,Sold!A:A,Sold!C:C,),"Cards ")) -> 2025 Topps | X6: =IFERROR(_xlfn.XLOOKUP(J6,Collection!A:A,Collection!B:B,),_xlfn.XLOOKUP(J6,Sold!A:A,Sold!B:B,)) -> LeBron James [Holo Foil] #150 | Y6: . | AB6: everydaysingles | AC6: 6.498275
B7: R | C7: Hoot2000 | D7: 46145 | E7: Givvy | F7: 0 | G7: 0 | H7: 0 | I7: Edgecombe | J7: 10895833 | K7: 478 | L7: https://www.whatnot.com/order/6QdgQ3vUdPh6pHE5WaqAmr | M7: whatnot.com/order/6QdgQ3vUdPh6pHE5WaqAmr $0.00 + $1.14 (Shared Shipping) + $0.12 Tax = Total of $1.25 | N7: =IFERROR(_xlfn.TEXTAFTER(L7,"https://www."),"")&CHAR(10)&_xlfn.CONCAT(TEXT(F7,"$0.00")," + ",TEXT(P7,"$0.00")," (Shared Shipping) + ",TEXT(R7,"$0.00")," Tax = Total of ",TEXT(S7,"$0.00")) -> whatnot.com/order/6QdgQ3vUdPh6pHE5WaqAmr $0.00 + $1.14 (Shared Shipping) + $0.00 Tax = Total of $1.14 | O7: =SUM(F7:H7) -> 0 | P7: =SUMIFS(G:G,C:C,C7,D:D,D7)/COUNTIFS(C:C,C7,D:D,D7) -> 1.1375 | Q7: =+F7+P7 -> 1.1375 | R7: =IF(H7=0,0,Q7*0.1025) -> 0 | S7: =+Q7+R7 -> 1.1375 | T7: =IFERROR(_xlfn.XLOOKUP(J7,Collection!A:A,Collection!D:D,0)/100/_xlfn.XLOOKUP(J7,Collection!A:A,Collection!J:J,0),_xlfn.XLOOKUP(J7,Sold!A:A,Sold!D:D,0)/100/_xlfn.XLOOKUP(J7,Sold!A:A,Sold!J:J,0)) -> 1.44 | U7: =IFERROR(T7-S7,0) -> 0.3025 | V7: =COUNTIF(Collection!A:A,J7)+COUNTIF(Sold!A:A,J7) -> 1 | W7: =IFERROR(_xlfn.TEXTAFTER(_xlfn.XLOOKUP(J7,Collection!A:A,Collection!C:C,),"Cards "),_xlfn.TEXTAFTER(_xlfn.XLOOKUP(J7,Sold!A:A,Sold!C:C,),"Cards ")) -> 2025 Topps Holiday | X7: =IFERROR(_xlfn.XLOOKUP(J7,Collection!A:A,Collection!B:B,),_xlfn.XLOOKUP(J7,Sold!A:A,Sold!B:B,)) -> VJ Edgecombe #H163 | Y7: . | AB7: plymouthsportscards | AC7: 5.2
B8: R | C8: kenjay_cards | D8: 46146 | E8: 144 | F8: 3 | G8: 1.09 | H8: 0.42 | I8: Chet | J8: 5475661 | K8: 451 | L8: https://www.whatnot.com/order/7TdKSNvxiGa3Bt8dCiKKbe | M8: whatnot.com/order/7TdKSNvxiGa3Bt8dCiKKbe $3.00 + $0.45 (Shared Shipping) + $0.35 Tax = Total of $3.81 | N8: =IFERROR(_xlfn.TEXTAFTER(L8,"https://www."),"")&CHAR(10)&_xlfn.CONCAT(TEXT(F8,"$0.00")," + ",TEXT(P8,"$0.00")," (Shared Shipping) + ",TEXT(R8,"$0.00")," Tax = Total of ",TEXT(S8,"$0.00")) -> whatnot.com/order/7TdKSNvxiGa3Bt8dCiKKbe $3.00 + $0.45 (Shared Shipping) + $0.35 Tax = Total of $3.81 | O8: =SUM(F8:H8) -> 4.51 | P8: =SUMIFS(G:G,C:C,C8,D:D,D8)/COUNTIFS(C:C,C8,D:D,D8) -> 0.45454545 | Q8: =+F8+P8 -> 3.4545455 | R8: =IF(H8=0,0,Q8*0.1025) -> 0.35409091 | S8: =+Q8+R8 -> 3.8086364 | T8: =IFERROR(_xlfn.XLOOKUP(J8,Collection!A:A,Collection!D:D,0)/100/_xlfn.XLOOKUP(J8,Collection!A:A,Collection!J:J,0),_xlfn.XLOOKUP(J8,Sold!A:A,Sold!D:D,0)/100/_xlfn.XLOOKUP(J8,Sold!A:A,Sold!J:J,0)) -> 1.42 | U8: =IFERROR(T8-S8,0) -> -2.3886364 | V8: =COUNTIF(Collection!A:A,J8)+COUNTIF(Sold!A:A,J8) -> 1 | W8: =IFERROR(_xlfn.TEXTAFTER(_xlfn.XLOOKUP(J8,Collection!A:A,Collection!C:C,),"Cards "),_xlfn.TEXTAFTER(_xlfn.XLOOKUP(J8,Sold!A:A,Sold!C:C,),"Cards ")) -> 2022 Panini Select Rookie Revolution | X8: =IFERROR(_xlfn.XLOOKUP(J8,Collection!A:A,Collection!B:B,),_xlfn.XLOOKUP(J8,Sold!A:A,Sold!B:B,)) -> Chet Holmgren #18 | Y8: . | AB8: freddievar84 | AC8: 3.476125
B9: R | C9: kenjay_cards | D9: 46146 | E9: 159 | F9: 4 | G9: 0.3 | H9: 0.45 | I9: Luka | J9: 4235113 | K9: 411 | L9: https://www.whatnot.com/order/A2VyUVWvtd6f5zu7wQpMgK | M9: whatnot.com/order/A2VyUVWvtd6f5zu7wQpMgK $4.00 + $0.45 (Shared Shipping) + $0.46 Tax = Total of $4.91 | N9: =IFERROR(_xlfn.TEXTAFTER(L9,"https://www."),"")&CHAR(10)&_xlfn.CONCAT(TEXT(F9,"$0.00")," + ",TEXT(P9,"$0.00")," (Shared Shipping) + ",TEXT(R9,"$0.00")," Tax = Total of ",TEXT(S9,"$0.00")) -> whatnot.com/order/A2VyUVWvtd6f5zu7wQpMgK $4.00 + $0.45 (Shared Shipping) + $0.46 Tax = Total of $4.91 | O9: =SUM(F9:H9) -> 4.75 | P9: =SUMIFS(G:G,C:C,C9,D:D,D9)/COUNTIFS(C:C,C9,D:D,D9) -> 0.45454545 | Q9: =+F9+P9 -> 4.4545455 | R9: =IF(H9=0,0,Q9*0.1025) -> 0.45659091 | S9: =+Q9+R9 -> 4.9111364 | T9: =IFERROR(_xlfn.XLOOKUP(J9,Collection!A:A,Collection!D:D,0)/100/_xlfn.XLOOKUP(J9,Collection!A:A,Collection!J:J,0),_xlfn.XLOOKUP(J9,Sold!A:A,Sold!D:D,0)/100/_xlfn.XLOOKUP(J9,Sold!A:A,Sold!J:J,0)) -> 1.27 | U9: =IFERROR(T9-S9,0) -> -3.6411364 | V9: =COUNTIF(Collection!A:A,J9)+COUNTIF(Sold!A:A,J9) -> 1 | W9: =IFERROR(_xlfn.TEXTAFTER(_xlfn.XLOOKUP(J9,Collection!A:A,Collection!C:C,),"Cards "),_xlfn.TEXTAFTER(_xlfn.XLOOKUP(J9,Sold!A:A,Sold!C:C,),"Cards ")) -> 2021 Panini Select | X9: =IFERROR(_xlfn.XLOOKUP(J9,Collection!A:A,Collection!B:B,),_xlfn.XLOOKUP(J9,Sold!A:A,Sold!B:B,)) -> Luka Doncic [Blue Prizm] #12 | Y9: . | AB9: cardboardbeast | AC9: 2.565
B10: R | C10: kenjay_cards | D10: 46146 | E10: 223 | F10: 4 | G10: 2.96 | H10: 0.71 | I10: Luka | J10: 4116797 | K10: 397 | L10: https://www.whatnot.com/order/UfG2uFVzbc3XCQZDoAnZnQ | M10: whatnot.com/order/UfG2uFVzbc3XCQZDoAnZnQ $4.00 + $0.45 (Shared Shipping) + $0.46 Tax = Total of $4.91 | N10: =IFERROR(_xlfn.TEXTAFTER(L10,"https://www."),"")&CHAR(10)&_xlfn.CONCAT(TEXT(F10,"$0.00")," + ",TEXT(P10,"$0.00")," (Shared Shipping) + ",TEXT(R10,"$0.00")," Tax = Total of ",TEXT(S10,"$0.00")) -> whatnot.com/order/UfG2uFVzbc3XCQZDoAnZnQ $4.00 + $0.45 (Shared Shipping) + $0.46 Tax = Total of $4.91 | O10: =SUM(F10:H10) -> 7.67 | P10: =SUMIFS(G:G,C:C,C10,D:D,D10)/COUNTIFS(C:C,C10,D:D,D10) -> 0.45454545 | Q10: =+F10+P10 -> 4.4545455 | R10: =IF(H10=0,0,Q10*0.1025) -> 0.45659091 | S10: =+Q10+R10 -> 4.9111364 | T10: =IFERROR(_xlfn.XLOOKUP(J10,Collection!A:A,Collection!D:D,0)/100/_xlfn.XLOOKUP(J10,Collection!A:A,Collection!J:J,0),_xlfn.XLOOKUP(J10,Sold!A:A,Sold!D:D,0)/100/_xlfn.XLOOKUP(J10,Sold!A:A,Sold!J:J,0)) -> 1.55 | U10: =IFERROR(T10-S10,0) -> -3.3611364 | V10: =COUNTIF(Collection!A:A,J10)+COUNTIF(Sold!A:A,J10) -> 1 | W10: =IFERROR(_xlfn.TEXTAFTER(_xlfn.XLOOKUP(J10,Collection!A:A,Collection!C:C,),"Cards "),_xlfn.TEXTAFTER(_xlfn.XLOOKUP(J10,Sold!A:A,Sold!C:C,),"Cards ")) -> 2021 Panini Donruss Optic Splash | X10: =IFERROR(_xlfn.XLOOKUP(J10,Collection!A:A,Collection!B:B,),_xlfn.XLOOKUP(J10,Sold!A:A,Sold!B:B,)) -> Luka Doncic #4 | Y10: . | AB10: hotmamajamacards | AC10: 1.88
B11: R | C11: kenjay_cards | D11: 46146 | E11: 233 | F11: 3 | G11: 0.45 | H11: 0.36 | I11: Cade | J11: 3782640 | K11: 328 | L11: https://www.whatnot.com/order/JieocTtxhoCCzfkGLnBz49 | M11: whatnot.com/order/JieocTtxhoCCzfkGLnBz49 $3.00 + $0.45 (Shared Shipping) + $0.35 Tax = Total of $3.81 | N11: =IFERROR(_xlfn.TEXTAFTER(L11,"https://www."),"")&CHAR(10)&_xlfn.CONCAT(TEXT(F11,"$0.00")," + ",TEXT(P11,"$0.00")," (Shared Shipping) + ",TEXT(R11,"$0.00")," Tax = Total of ",TEXT(S11,"$0.00")) -> whatnot.com/order/JieocTtxhoCCzfkGLnBz49 $3.00 + $0.45 (Shared Shipping) + $0.35 Tax = Total of $3.81 | O11: =SUM(F11:H11) -> 3.81 | P11: =SUMIFS(G:G,C:C,C11,D:D,D11)/COUNTIFS(C:C,C11,D:D,D11) -> 0.45454545 | Q11: =+F11+P11 -> 3.4545455 | R11: =IF(H11=0,0,Q11*0.1025) -> 0.35409091 | S11: =+Q11+R11 -> 3.8086364 | T11: =IFERROR(_xlfn.XLOOKUP(J11,Collection!A:A,Collection!D:D,0)/100/_xlfn.XLOOKUP(J11,Collection!A:A,Collection!J:J,0),_xlfn.XLOOKUP(J11,Sold!A:A,Sold!D:D,0)/100/_xlfn.XLOOKUP(J11,Sold!A:A,Sold!J:J,0)) -> 1.46 | U11: =IFERROR(T11-S11,0) -> -2.3486364 | V11: =COUNTIF(Collection!A:A,J11)+COUNTIF(Sold!A:A,J11) -> 1 | W11: =IFERROR(_xlfn.TEXTAFTER(_xlfn.XLOOKUP(J11,Collection!A:A,Collection!C:C,),"Cards "),_xlfn.TEXTAFTER(_xlfn.XLOOKUP(J11,Sold!A:A,Sold!C:C,),"Cards ")) -> 2021 Panini Prizm Emergent | X11: =IFERROR(_xlfn.XLOOKUP(J11,Collection!A:A,Collection!B:B,),_xlfn.XLOOKUP(J11,Sold!A:A,Sold!B:B,)) -> Cade Cunningham #22 | Y11: . | AB11: noketownstar32 | AC11: 1.583275
B12: R | C12: kenjay_cards | D12: 46146 | E12: 234 | F12: 3 | G12: 0 | H12: 0.31 | I12: Luka | J12: 5289892 | K12: 311 | L12: https://www.whatnot.com/order/YdoZr7RTzDToYz6PByf22R | M12: whatnot.com/order/YdoZr7RTzDToYz6PByf22R $3.00 + $0.45 (Shared Shipping) + $0.35 Tax = Total of $3.81 | N12: =IFERROR(_xlfn.TEXTAFTER(L12,"https://www."),"")&CHAR(10)&_xlfn.CONCAT(TEXT(F12,"$0.00")," + ",TEXT(P12,"$0.00")," (Shared Shipping) + ",TEXT(R12,"$0.00")," Tax = Total of ",TEXT(S12,"$0.00")) -> whatnot.com/order/YdoZr7RTzDToYz6PByf22R $3.00 + $0.45 (Shared Shipping) + $0.35 Tax = Total of $3.81 | O12: =SUM(F12:H12) -> 3.31 | P12: =SUMIFS(G:G,C:C,C12,D:D,D12)/COUNTIFS(C:C,C12,D:D,D12) -> 0.45454545 | Q12: =+F12+P12 -> 3.4545455 | R12: =IF(H12=0,0,Q12*0.1025) -> 0.35409091 | S12: =+Q12+R12 -> 3.8086364 | T12: =IFERROR(_xlfn.XLOOKUP(J12,Collection!A:A,Collection!D:D,0)/100/_xlfn.XLOOKUP(J12,Collection!A:A,Collection!J:J,0),_xlfn.XLOOKUP(J12,Sold!A:A,Sold!D:D,0)/100/_xlfn.XLOOKUP(J12,Sold!A:A,Sold!J:J,0)) -> 1.86 | U12: =IFERROR(T12-S12,0) -> -1.9486364 | V12: =COUNTIF(Collection!A:A,J12)+COUNTIF(Sold!A:A,J12) -> 1 | W12: =IFERROR(_xlfn.TEXTAFTER(_xlfn.XLOOKUP(J12,Collection!A:A,Collection!C:C,),"Cards "),_xlfn.TEXTAFTER(_xlfn.XLOOKUP(J12,Sold!A:A,Sold!C:C,),"Cards ")) -> 2022 Panini Donruss Optic T Minus 3 2 1 | X12: =IFERROR(_xlfn.XLOOKUP(J12,Collection!A:A,Collection!B:B,),_xlfn.XLOOKUP(J12,Sold!A:A,Sold!B:B,)) -> Luka Doncic [Purple] #7 | Y12: . | AB12: card_fire | AC12: 1
B13: R | C13: kenjay_cards | D13: 46146 | E13: 242 | F13: 1 | G13: 0 | H13: 0.11 | I13: Gafford | J13: 11473930 | K13: 134 | L13: https://www.whatnot.com/order/fsZrqS9c5o3n2dqHjHqttF | M13: whatnot.com/order/fsZrqS9c5o3n2dqHjHqttF $1.00 + $0.45 (Shared Shipping) + $0.15 Tax = Total of $1.60 | N13: =IFERROR(_xlfn.TEXTAFTER(L13,"https://www."),"")&CHAR(10)&_xlfn.CONCAT(TEXT(F13,"$0.00")," + ",TEXT(P13,"$0.00")," (Shared Shipping) + ",TEXT(R13,"$0.00")," Tax = Total of ",TEXT(S13,"$0.00")) -> whatnot.com/order/fsZrqS9c5o3n2dqHjHqttF $1.00 + $0.45 (Shared Shipping) + $0.15 Tax = Total of $1.60 | O13: =SUM(F13:H13) -> 1.11 | P13: =SUMIFS(G:G,C:C,C13,D:D,D13)/COUNTIFS(C:C,C13,D:D,D13) -> 0.45454545 | Q13: =+F13+P13 -> 1.4545455 | R13: =IF(H13=0,0,Q13*0.1025) -> 0.14909091 | S13: =+Q13+R13 -> 1.6036364 | T13: =IFERROR(_xlfn.XLOOKUP(J13,Collection!A:A,Collection!D:D,0)/100/_xlfn.XLOOKUP(J13,Collection!A:A,Collection!J:J,0),_xlfn.XLOOKUP(J13,Sold!A:A,Sold!D:D,0)/100/_xlfn.XLOOKUP(J13,Sold!A:A,Sold!J:J,0)) -> 4.01 | U13: =IFERROR(T13-S13,0) -> 2.4063636 | V13: =COUNTIF(Collection!A:A,J13)+COUNTIF(Sold!A:A,J13) -> 1 | W13: =IFERROR(_xlfn.TEXTAFTER(_xlfn.XLOOKUP(J13,Collection!A:A,Collection!C:C,),"Cards "),_xlfn.TEXTAFTER(_xlfn.XLOOKUP(J13,Sold!A:A,Sold!C:C,),"Cards ")) -> 2025 Topps Chrome | X13: =IFERROR(_xlfn.XLOOKUP(J13,Collection!A:A,Collection!B:B,),_xlfn.XLOOKUP(J13,Sold!A:A,Sold!B:B,)) -> Daniel Gafford [Purple Refractor] #78 | Y13: . | AB13: blakewaldron4 | AC13: 1
B14: R | C14: kenjay_cards | D14: 46146 | E14: 276 | F14: 1 | G14: 0.2 | H14: 0.12 | I14: Murray | J14: 5178537 | K14: 394 | L14: https://www.whatnot.com/order/XWP5KdeeCdt8TKjdVmH5ek | M14: whatnot.com/order/XWP5KdeeCdt8TKjdVmH5ek $1.00 + $0.45 (Shared Shipping) + $0.15 Tax = Total of $1.60 | N14: =IFERROR(_xlfn.TEXTAFTER(L14,"https://www."),"")&CHAR(10)&_xlfn.CONCAT(TEXT(F14,"$0.00")," + ",TEXT(P14,"$0.00")," (Shared Shipping) + ",TEXT(R14,"$0.00")," Tax = Total of ",TEXT(S14,"$0.00")) -> whatnot.com/order/XWP5KdeeCdt8TKjdVmH5ek $1.00 + $0.45 (Shared Shipping) + $0.15 Tax = Total of $1.60 | O14: =SUM(F14:H14) -> 1.32 | P14: =SUMIFS(G:G,C:C,C14,D:D,D14)/COUNTIFS(C:C,C14,D:D,D14) -> 0.45454545 | Q14: =+F14+P14 -> 1.4545455 | R14: =IF(H14=0,0,Q14*0.1025) -> 0.14909091 | S14: =+Q14+R14 -> 1.6036364 | T14: =IFERROR(_xlfn.XLOOKUP(J14,Collection!A:A,Collection!D:D,0)/100/_xlfn.XLOOKUP(J14,Collection!A:A,Collection!J:J,0),_xlfn.XLOOKUP(J14,Sold!A:A,Sold!D:D,0)/100/_xlfn.XLOOKUP(J14,Sold!A:A,Sold!J:J,0)) -> 1.55 | U14: =IFERROR(T14-S14,0) -> -0.053636364 | V14: =COUNTIF(Collection!A:A,J14)+COUNTIF(Sold!A:A,J14) -> 1 | W14: =IFERROR(_xlfn.TEXTAFTER(_xlfn.XLOOKUP(J14,Collection!A:A,Collection!C:C,),"Cards "),_xlfn.TEXTAFTER(_xlfn.XLOOKUP(J14,Sold!A:A,Sold!C:C,),"Cards ")) -> 2022 Panini Contenders Suite Shots | X14: =IFERROR(_xlfn.XLOOKUP(J14,Collection!A:A,Collection!B:B,),_xlfn.XLOOKUP(J14,Sold!A:A,Sold!B:B,)) -> Jamal Murray #9 | Y14: . | AB14: peba_66 | AC14: 0.68345
B15: R | C15: kenjay_cards | D15: 46146 | E15: 289 | F15: 4 | G15: 0 | H15: 0.41 | I15: Luka | J15: 5463744 | K15: 584 | L15: https://www.whatnot.com/order/hQVu9JLwFefwSJcu3QwY6E | M15: whatnot.com/order/hQVu9JLwFefwSJcu3QwY6E $4.00 + $0.45 (Shared Shipping) + $0.46 Tax = Total of $4.91 | N15: =IFERROR(_xlfn.TEXTAFTER(L15,"https://www."),"")&CHAR(10)&_xlfn.CONCAT(TEXT(F15,"$0.00")," + ",TEXT(P15,"$0.00")," (Shared Shipping) + ",TEXT(R15,"$0.00")," Tax = Total of ",TEXT(S15,"$0.00")) -> whatnot.com/order/hQVu9JLwFefwSJcu3QwY6E $4.00 + $0.45 (Shared Shipping) + $0.46 Tax = Total of $4.91 | O15: =SUM(F15:H15) -> 4.41 | P15: =SUMIFS(G:G,C:C,C15,D:D,D15)/COUNTIFS(C:C,C15,D:D,D15) -> 0.45454545 | Q15: =+F15+P15 -> 4.4545455 | R15: =IF(H15=0,0,Q15*0.1025) -> 0.45659091 | S15: =+Q15+R15 -> 4.9111364 | T15: =IFERROR(_xlfn.XLOOKUP(J15,Collection!A:A,Collection!D:D,0)/100/_xlfn.XLOOKUP(J15,Collection!A:A,Collection!J:J,0),_xlfn.XLOOKUP(J15,Sold!A:A,Sold!D:D,0)/100/_xlfn.XLOOKUP(J15,Sold!A:A,Sold!J:J,0)) -> 0.62 | U15: =IFERROR(T15-S15,0) -> -4.2911364 | V15: =COUNTIF(Collection!A:A,J15)+COUNTIF(Sold!A:A,J15) -> 1 | W15: =IFERROR(_xlfn.TEXTAFTER(_xlfn.XLOOKUP(J15,Collection!A:A,Collection!C:C,),"Cards "),_xlfn.TEXTAFTER(_xlfn.XLOOKUP(J15,Sold!A:A,Sold!C:C,),"Cards ")) -> 2022 Panini Select | X15: =IFERROR(_xlfn.XLOOKUP(J15,Collection!A:A,Collection!B:B,),_xlfn.XLOOKUP(J15,Sold!A:A,Sold!B:B,)) -> Luka Doncic #151 | Y15: . | AB15: kassab_cards | AC15: 0.442525
B16: R | C16: kenjay_cards | D16: 46146 | E16: 293 | F16: 2 | G16: 0 | H16: 0.21 | I16: Jokic | J16: 10190248 | K16: 443 | L16: https://www.whatnot.com/order/HWhpJLX6J4h4DZZVCaeVYr | M16: whatnot.com/order/HWhpJLX6J4h4DZZVCaeVYr $2.00 + $0.45 (Shared Shipping) + $0.25 Tax = Total of $2.71 | N16: =IFERROR(_xlfn.TEXTAFTER(L16,"https://www."),"")&CHAR(10)&_xlfn.CONCAT(TEXT(F16,"$0.00")," + ",TEXT(P16,"$0.00")," (Shared Shipping) + ",TEXT(R16,"$0.00")," Tax = Total of ",TEXT(S16,"$0.00")) -> whatnot.com/order/HWhpJLX6J4h4DZZVCaeVYr $2.00 + $0.45 (Shared Shipping) + $0.25 Tax = Total of $2.71 | O16: =SUM(F16:H16) -> 2.21 | P16: =SUMIFS(G:G,C:C,C16,D:D,D16)/COUNTIFS(C:C,C16,D:D,D16) -> 0.45454545 | Q16: =+F16+P16 -> 2.4545455 | R16: =IF(H16=0,0,Q16*0.1025) -> 0.25159091 | S16: =+Q16+R16 -> 2.7061364 | T16: =IFERROR(_xlfn.XLOOKUP(J16,Collection!A:A,Collection!D:D,0)/100/_xlfn.XLOOKUP(J16,Collection!A:A,Collection!J:J,0),_xlfn.XLOOKUP(J16,Sold!A:A,Sold!D:D,0)/100/_xlfn.XLOOKUP(J16,Sold!A:A,Sold!J:J,0)) -> 1.47 | U16: =IFERROR(T16-S16,0) -> -1.2361364 | V16: =COUNTIF(Collection!A:A,J16)+COUNTIF(Sold!A:A,J16) -> 1 | W16: =IFERROR(_xlfn.TEXTAFTER(_xlfn.XLOOKUP(J16,Collection!A:A,Collection!C:C,),"Cards "),_xlfn.TEXTAFTER(_xlfn.XLOOKUP(J16,Sold!A:A,Sold!C:C,),"Cards ")) -> 2024 Panini Donruss Optic | X16: =IFERROR(_xlfn.XLOOKUP(J16,Collection!A:A,Collection!B:B,),_xlfn.XLOOKUP(J16,Sold!A:A,Sold!B:B,)) -> Nikola Jokic [Hyper Pink] #100 | Y16: . | AB16: sbgcards | AC16: 0.410775
B17: R | C17: kenjay_cards | D17: 46146 | E17: 302 | F17: 5 | G17: 0 | H17: 0.52 | I17: Reaves | J17: 3727445 | K17: 274 | L17: https://www.whatnot.com/order/o3mHoMSnpC2X8C3j6r4tiK | M17: whatnot.com/order/o3mHoMSnpC2X8C3j6r4tiK $5.00 + $0.45 (Shared Shipping) + $0.56 Tax = Total of $6.01 | N17: =IFERROR(_xlfn.TEXTAFTER(L17,"https://www."),"")&CHAR(10)&_xlfn.CONCAT(TEXT(F17,"$0.00")," + ",TEXT(P17,"$0.00")," (Shared Shipping) + ",TEXT(R17,"$0.00")," Tax = Total of ",TEXT(S17,"$0.00")) -> whatnot.com/order/o3mHoMSnpC2X8C3j6r4tiK $5.00 + $0.45 (Shared Shipping) + $0.56 Tax = Total of $6.01 | O17: =SUM(F17:H17) -> 5.52 | P17: =SUMIFS(G:G,C:C,C17,D:D,D17)/COUNTIFS(C:C,C17,D:D,D17) -> 0.45454545 | Q17: =+F17+P17 -> 5.4545455 | R17: =IF(H17=0,0,Q17*0.1025) -> 0.55909091 | S17: =+Q17+R17 -> 6.0136364 | T17: =IFERROR(_xlfn.XLOOKUP(J17,Collection!A:A,Collection!D:D,0)/100/_xlfn.XLOOKUP(J17,Collection!A:A,Collection!J:J,0),_xlfn.XLOOKUP(J17,Sold!A:A,Sold!D:D,0)/100/_xlfn.XLOOKUP(J17,Sold!A:A,Sold!J:J,0)) -> 2.37 | U17: =IFERROR(T17-S17,0) -> -3.6436364 | V17: =COUNTIF(Collection!A:A,J17)+COUNTIF(Sold!A:A,J17) -> 1 | W17: =IFERROR(_xlfn.TEXTAFTER(_xlfn.XLOOKUP(J17,Collection!A:A,Collection!C:C,),"Cards "),_xlfn.TEXTAFTER(_xlfn.XLOOKUP(J17,Sold!A:A,Sold!C:C,),"Cards ")) -> 2021 Panini Prizm | X17: =IFERROR(_xlfn.XLOOKUP(J17,Collection!A:A,Collection!B:B,),_xlfn.XLOOKUP(J17,Sold!A:A,Sold!B:B,)) -> Austin Reaves #165 | Y17: . | AB17: demarco210 | AC17: 0.28755
B18: R | C18: kenjay_cards | D18: 46146 | E18: 352 | F18: 5 | G18: 0 | H18: 0.52 | I18: Ant | J18: 3401118 | K18: 290 | L18: https://www.whatnot.com/order/3bymbw4YA5kuEYFfvvyWw2 | M18: whatnot.com/order/3bymbw4YA5kuEYFfvvyWw2 $5.00 + $0.45 (Shared Shipping) + $0.56 Tax = Total of $6.01 | N18: =IFERROR(_xlfn.TEXTAFTER(L18,"https://www."),"")&CHAR(10)&_xlfn.CONCAT(TEXT(F18,"$0.00")," + ",TEXT(P18,"$0.00")," (Shared Shipping) + ",TEXT(R18,"$0.00")," Tax = Total of ",TEXT(S18,"$0.00")) -> whatnot.com/order/3bymbw4YA5kuEYFfvvyWw2 $5.00 + $0.45 (Shared Shipping) + $0.56 Tax = Total of $6.01 | O18: =SUM(F18:H18) -> 5.52 | P18: =SUMIFS(G:G,C:C,C18,D:D,D18)/COUNTIFS(C:C,C18,D:D,D18) -> 0.45454545 | Q18: =+F18+P18 -> 5.4545455 | R18: =IF(H18=0,0,Q18*0.1025) -> 0.55909091 | S18: =+Q18+R18 -> 6.0136364 | T18: =IFERROR(_xlfn.XLOOKUP(J18,Collection!A:A,Collection!D:D,0)/100/_xlfn.XLOOKUP(J18,Collection!A:A,Collection!J:J,0),_xlfn.XLOOKUP(J18,Sold!A:A,Sold!D:D,0)/100/_xlfn.XLOOKUP(J18,Sold!A:A,Sold!J:J,0)) -> 1.7 | U18: =IFERROR(T18-S18,0) -> -4.3136364 | V18: =COUNTIF(Collection!A:A,J18)+COUNTIF(Sold!A:A,J18) -> 1 | W18: =IFERROR(_xlfn.TEXTAFTER(_xlfn.XLOOKUP(J18,Collection!A:A,Collection!C:C,),"Cards "),_xlfn.TEXTAFTER(_xlfn.XLOOKUP(J18,Sold!A:A,Sold!C:C,),"Cards ")) -> 2020 Panini Prizm Emergent | X18: =IFERROR(_xlfn.XLOOKUP(J18,Collection!A:A,Collection!B:B,),_xlfn.XLOOKUP(J18,Sold!A:A,Sold!B:B,)) -> Anthony Edwards #3 | Y18: . | AB18: kidds_cards | AC18: 0.15862353
B19: R | C19: Tanner346 | D19: 46145 | E19: 44 | F19: 3 | G19: 0.78 | H19: 0.39 | I19: Luka | J19: 4166936 | K19: 474 | L19: https://www.whatnot.com/order/gS3Pko5Lnk9cRAzYzXbJeF | M19: whatnot.com/order/gS3Pko5Lnk9cRAzYzXbJeF $3.00 + $0.36 (Shared Shipping) + $0.34 Tax = Total of $3.71 | N19: =IFERROR(_xlfn.TEXTAFTER(L19,"https://www."),"")&CHAR(10)&_xlfn.CONCAT(TEXT(F19,"$0.00")," + ",TEXT(P19,"$0.00")," (Shared Shipping) + ",TEXT(R19,"$0.00")," Tax = Total of ",TEXT(S19,"$0.00")) -> whatnot.com/order/gS3Pko5Lnk9cRAzYzXbJeF $3.00 + $0.36 (Shared Shipping) + $0.34 Tax = Total of $3.71 | O19: =SUM(F19:H19) -> 4.17 | P19: =SUMIFS(G:G,C:C,C19,D:D,D19)/COUNTIFS(C:C,C19,D:D,D19) -> 0.36333333 | Q19: =+F19+P19 -> 3.3633333 | R19: =IF(H19=0,0,Q19*0.1025) -> 0.34474167 | S19: =+Q19+R19 -> 3.708075 | T19: =IFERROR(_xlfn.XLOOKUP(J19,Collection!A:A,Collection!D:D,0)/100/_xlfn.XLOOKUP(J19,Collection!A:A,Collection!J:J,0),_xlfn.XLOOKUP(J19,Sold!A:A,Sold!D:D,0)/100/_xlfn.XLOOKUP(J19,Sold!A:A,Sold!J:J,0)) -> 1.3 | U19: =IFERROR(T19-S19,0) -> -2.408075 | V19: =COUNTIF(Collection!A:A,J19)+COUNTIF(Sold!A:A,J19) -> 1 | W19: =IFERROR(_xlfn.TEXTAFTER(_xlfn.XLOOKUP(J19,Collection!A:A,Collection!C:C,),"Cards "),_xlfn.TEXTAFTER(_xlfn.XLOOKUP(J19,Sold!A:A,Sold!C:C,),"Cards ")) -> 2021 Panini Chronicles | X19: =IFERROR(_xlfn.XLOOKUP(J19,Collection!A:A,Collection!B:B,),_xlfn.XLOOKUP(J19,Sold!A:A,Sold!B:B,)) -> Luka Doncic #304 | Y19: . | AB19: pbdreamlove | AC19: 0.1434125
... B28: R | C28: Tasrelics | D28: 46147 | E28: 10 | F28: 3 | G28: 0.4 | H28: 0.36 | I28: Embiid | J28: 131835 | K28: 125 | L28: https://www.whatnot.com/order/jhwwvPX5xZkZWVs8CGhFXe | M28: whatnot.com/order/jhwwvPX5xZkZWVs8CGhFXe $3.00 + $2.48 (Shared Shipping) + $0.56 Tax = Total of $6.04 | N28: =IFERROR(_xlfn.TEXTAFTER(L28,"https://www."),"")&CHAR(10)&_xlfn.CONCAT(TEXT(F28,"$0.00")," + ",TEXT(P28,"$0.00")," (Shared Shipping) + ",TEXT(R28,"$0.00")," Tax = Total of ",TEXT(S28,"$0.00")) -> whatnot.com/order/jhwwvPX5xZkZWVs8CGhFXe $3.00 + $2.48 (Shared Shipping) + $0.56 Tax = Total of $6.04 | O28: =SUM(F28:H28) -> 3.76 | P28: =SUMIFS(G:G,C:C,C28,D:D,D28)/COUNTIFS(C:C,C28,D:D,D28) -> 2.475 | Q28: =+F28+P28 -> 5.475 | R28: =IF(H28=0,0,Q28*0.1025) -> 0.5611875 | S28: =+Q28+R28 -> 6.0361875 | T28: =IFERROR(_xlfn.XLOOKUP(J28,Collection!A:A,Collection!D:D,0)/100/_xlfn.XLOOKUP(J28,Collection!A:A,Collection!J:J,0),_xlfn.XLOOKUP(J28,Sold!A:A,Sold!D:D,0)/100/_xlfn.XLOOKUP(J28,Sold!A:A,Sold!J:J,0)) -> 5.56 | U28: =IFERROR(T28-S28,0) -> -0.4761875 | V28: =COUNTIF(Collection!A:A,J28)+COUNTIF(Sold!A:A,J28) -> 1 | W28: =IFERROR(_xlfn.TEXTAFTER(_xlfn.XLOOKUP(J28,Collection!A:A,Collection!C:C,),"Cards "),_xlfn.TEXTAFTER(_xlfn.XLOOKUP(J28,Sold!A:A,Sold!C:C,),"Cards ")) -> 2014 Panini Hoops | X28: =IFERROR(_xlfn.XLOOKUP(J28,Collection!A:A,Collection!B:B,),_xlfn.XLOOKUP(J28,Sold!A:A,Sold!B:B,)) -> Joel Embiid #263 | Y28: . | AB28: dcollectorsclub | AC28: -1.17745
B29: R | C29: djbsports | D29: 46148 | E29: 93 | F29: 1 | G29: 1.09 | H29: 0.22 | I29: Wade | L29: https://www.whatnot.com/order/ZQa92YACdaqMGpqFzdMcVG | M29: whatnot.com/order/ZQa92YACdaqMGpqFzdMcVG $1.00 + $1.09 (Shared Shipping) + $0.21 Tax = Total of $2.30 | N29: =IFERROR(_xlfn.TEXTAFTER(L29,"https://www."),"")&CHAR(10)&_xlfn.CONCAT(TEXT(F29,"$0.00")," + ",TEXT(P29,"$0.00")," (Shared Shipping) + ",TEXT(R29,"$0.00")," Tax = Total of ",TEXT(S29,"$0.00")) -> whatnot.com/order/ZQa92YACdaqMGpqFzdMcVG $1.00 + $1.09 (Shared Shipping) + $0.21 Tax = Total of $2.30 | O29: =SUM(F29:H29) -> 2.31 | P29: =SUMIFS(G:G,C:C,C29,D:D,D29)/COUNTIFS(C:C,C29,D:D,D29) -> 1.09 | Q29: =+F29+P29 -> 2.09 | R29: =IF(H29=0,0,Q29*0.1025) -> 0.214225 | S29: =+Q29+R29 -> 2.304225 | T29: =IFERROR(_xlfn.XLOOKUP(J29,Collection!A:A,Collection!D:D,0)/100/_xlfn.XLOOKUP(J29,Collection!A:A,Collection!J:J,0),_xlfn.XLOOKUP(J29,Sold!A:A,Sold!D:D,0)/100/_xlfn.XLOOKUP(J29,Sold!A:A,Sold!J:J,0)) -> #DIV/0! | U29: =IFERROR(T29-S29,0) -> 0 | V29: =COUNTIF(Collection!A:A,J29)+COUNTIF(Sold!A:A,J29) -> 0 | W29: =IFERROR(_xlfn.TEXTAFTER(_xlfn.XLOOKUP(J29,Collection!A:A,Collection!C:C,),"Cards "),_xlfn.TEXTAFTER(_xlfn.XLOOKUP(J29,Sold!A:A,Sold!C:C,),"Cards ")) -> #N/A | X29: =IFERROR(_xlfn.XLOOKUP(J29,Collection!A:A,Collection!B:B,),_xlfn.XLOOKUP(J29,Sold!A:A,Sold!B:B,)) -> 0 | Y29: Not Listed | AB29: cardyoinkers | AC29: -1.56495
B30: R | C30: iceball | D30: 46148 | E30: 45 | F30: 5 | G30: 4.35 | H30: 0.97 | I30: Reaves | J30: 8776006 | K30: 253 | L30: https://www.whatnot.com/order/9ki7HURGVDFpQYLubozunU | M30: whatnot.com/order/9ki7HURGVDFpQYLubozunU $5.00 + $0.21 (Shared Shipping) + $0.53 Tax = Total of $5.74 | N30: =IFERROR(_xlfn.TEXTAFTER(L30,"https://www."),"")&CHAR(10)&_xlfn.CONCAT(TEXT(F30,"$0.00")," + ",TEXT(P30,"$0.00")," (Shared Shipping) + ",TEXT(R30,"$0.00")," Tax = Total of ",TEXT(S30,"$0.00")) -> whatnot.com/order/9ki7HURGVDFpQYLubozunU $5.00 + $0.21 (Shared Shipping) + $0.53 Tax = Total of $5.74 | O30: =SUM(F30:H30) -> 10.32 | P30: =SUMIFS(G:G,C:C,C30,D:D,D30)/COUNTIFS(C:C,C30,D:D,D30) -> 0.20714286 | Q30: =+F30+P30 -> 5.2071429 | R30: =IF(H30=0,0,Q30*0.1025) -> 0.53373214 | S30: =+Q30+R30 -> 5.740875 | T30: =IFERROR(_xlfn.XLOOKUP(J30,Collection!A:A,Collection!D:D,0)/100/_xlfn.XLOOKUP(J30,Collection!A:A,Collection!J:J,0),_xlfn.XLOOKUP(J30,Sold!A:A,Sold!D:D,0)/100/_xlfn.XLOOKUP(J30,Sold!A:A,Sold!J:J,0)) -> 2.13 | U30: =IFERROR(T30-S30,0) -> -3.610875 | V30: =COUNTIF(Collection!A:A,J30)+COUNTIF(Sold!A:A,J30) -> 1 | W30: =IFERROR(_xlfn.TEXTAFTER(_xlfn.XLOOKUP(J30,Collection!A:A,Collection!C:C,),"Cards "),_xlfn.TEXTAFTER(_xlfn.XLOOKUP(J30,Sold!A:A,Sold!C:C,),"Cards ")) -> 2024 Panini Donruss | X30: =IFERROR(_xlfn.XLOOKUP(J30,Collection!A:A,Collection!B:B,),_xlfn.XLOOKUP(J30,Sold!A:A,Sold!B:B,)) -> Austin Reaves [Storm] #163 | Y30: . | AB30: iceball | AC30: -2.2392542
B31: R | C31: iceball | D31: 46148 | E31: 109 | F31: 15 | G31: 0 | H31: 1.54 | I31: Jokic | J31: 95721 | K31: 51082129 | L31: https://www.whatnot.com/order/27RrZ5UcQbAp2yynBpazpE | M31: whatnot.com/order/27RrZ5UcQbAp2yynBpazpE $15.00 + $0.21 (Shared Shipping) + $1.56 Tax = Total of $16.77 | N31: =IFERROR(_xlfn.TEXTAFTER(L31,"https://www."),"")&CHAR(10)&_xlfn.CONCAT(TEXT(F31,"$0.00")," + ",TEXT(P31,"$0.00")," (Shared Shipping) + ",TEXT(R31,"$0.00")," Tax = Total of ",TEXT(S31,"$0.00")) -> whatnot.com/order/27RrZ5UcQbAp2yynBpazpE $15.00 + $0.21 (Shared Shipping) + $1.56 Tax = Total of $16.77 | O31: =SUM(F31:H31) -> 16.54 | P31: =SUMIFS(G:G,C:C,C31,D:D,D31)/COUNTIFS(C:C,C31,D:D,D31) -> 0.20714286 | Q31: =+F31+P31 -> 15.207143 | R31: =IF(H31=0,0,Q31*0.1025) -> 1.5587321 | S31: =+Q31+R31 -> 16.765875 | T31: =IFERROR(_xlfn.XLOOKUP(J31,Collection!A:A,Collection!D:D,0)/100/_xlfn.XLOOKUP(J31,Collection!A:A,Collection!J:J,0),_xlfn.XLOOKUP(J31,Sold!A:A,Sold!D:D,0)/100/_xlfn.XLOOKUP(J31,Sold!A:A,Sold!J:J,0)) -> 19.52 | U31: =IFERROR(T31-S31,0) -> 2.754125 | V31: =COUNTIF(Collection!A:A,J31)+COUNTIF(Sold!A:A,J31) -> 1 | W31: =IFERROR(_xlfn.TEXTAFTER(_xlfn.XLOOKUP(J31,Collection!A:A,Collection!C:C,),"Cards "),_xlfn.TEXTAFTER(_xlfn.XLOOKUP(J31,Sold!A:A,Sold!C:C,),"Cards ")) -> 2019 Panini Prizm | X31: =IFERROR(_xlfn.XLOOKUP(J31,Collection!A:A,Collection!B:B,),_xlfn.XLOOKUP(J31,Sold!A:A,Sold!B:B,)) -> Nikola Jokic [Ruby Wave Prizm] #84 | Y31: . | AB31: Tanner346 | AC31: -2.434225
B32: R | C32: iceball | D32: 46148 | E32: Givvy 4 | F32: 0 | G32: 0 | H32: 0 | I32: James | J32: 9781694 | K32: 335 | L32: https://www.whatnot.com/order/9Nw32iaBQX4B786bgpSBCs | M32: whatnot.com/order/9Nw32iaBQX4B786bgpSBCs $0.00 + $0.21 (Shared Shipping) + $0.02 Tax = Total of $0.23 | N32: =IFERROR(_xlfn.TEXTAFTER(L32,"https://www."),"")&CHAR(10)&_xlfn.CONCAT(TEXT(F32,"$0.00")," + ",TEXT(P32,"$0.00")," (Shared Shipping) + ",TEXT(R32,"$0.00")," Tax = Total of ",TEXT(S32,"$0.00")) -> whatnot.com/order/9Nw32iaBQX4B786bgpSBCs $0.00 + $0.21 (Shared Shipping) + $0.00 Tax = Total of $0.21 | O32: =SUM(F32:H32) -> 0 | P32: =SUMIFS(G:G,C:C,C32,D:D,D32)/COUNTIFS(C:C,C32,D:D,D32) -> 0.20714286 | Q32: =+F32+P32 -> 0.20714286 | R32: =IF(H32=0,0,Q32*0.1025) -> 0 | S32: =+Q32+R32 -> 0.20714286 | T32: =IFERROR(_xlfn.XLOOKUP(J32,Collection!A:A,Collection!D:D,0)/100/_xlfn.XLOOKUP(J32,Collection!A:A,Collection!J:J,0),_xlfn.XLOOKUP(J32,Sold!A:A,Sold!D:D,0)/100/_xlfn.XLOOKUP(J32,Sold!A:A,Sold!J:J,0)) -> 1.68 | U32: =IFERROR(T32-S32,0) -> 1.4728571 | V32: =COUNTIF(Collection!A:A,J32)+COUNTIF(Sold!A:A,J32) -> 1 | W32: =IFERROR(_xlfn.TEXTAFTER(_xlfn.XLOOKUP(J32,Collection!A:A,Collection!C:C,),"Cards "),_xlfn.TEXTAFTER(_xlfn.XLOOKUP(J32,Sold!A:A,Sold!C:C,),"Cards ")) -> 2024 Panini Select | X32: =IFERROR(_xlfn.XLOOKUP(J32,Collection!A:A,Collection!B:B,),_xlfn.XLOOKUP(J32,Sold!A:A,Sold!B:B,)) -> LeBron James [Blue Prizm] #54 | Y32: Verify Parallel - LeBron James [Blue Prizm] #54 - 2024 Panini Select | AB32: sycotik | AC32: -2.5945
B33: R | C33: iceball | D33: 46148 | E33: Givvy 4 | F33: 0 | G33: 0 | H33: 0 | I33: Brown | J33: 10198347 | K33: 537 | L33: https://www.whatnot.com/order/9Nw32iaBQX4B786bgpSBCs | M33: whatnot.com/order/9Nw32iaBQX4B786bgpSBCs $0.00 + $0.21 (Shared Shipping) + $0.02 Tax = Total of $0.23 | N33: =IFERROR(_xlfn.TEXTAFTER(L33,"https://www."),"")&CHAR(10)&_xlfn.CONCAT(TEXT(F33,"$0.00")," + ",TEXT(P33,"$0.00")," (Shared Shipping) + ",TEXT(R33,"$0.00")," Tax = Total of ",TEXT(S33,"$0.00")) -> whatnot.com/order/9Nw32iaBQX4B786bgpSBCs $0.00 + $0.21 (Shared Shipping) + $0.00 Tax = Total of $0.21 | O33: =SUM(F33:H33) -> 0 | P33: =SUMIFS(G:G,C:C,C33,D:D,D33)/COUNTIFS(C:C,C33,D:D,D33) -> 0.20714286 | Q33: =+F33+P33 -> 0.20714286 | R33: =IF(H33=0,0,Q33*0.1025) -> 0 | S33: =+Q33+R33 -> 0.20714286 | T33: =IFERROR(_xlfn.XLOOKUP(J33,Collection!A:A,Collection!D:D,0)/100/_xlfn.XLOOKUP(J33,Collection!A:A,Collection!J:J,0),_xlfn.XLOOKUP(J33,Sold!A:A,Sold!D:D,0)/100/_xlfn.XLOOKUP(J33,Sold!A:A,Sold!J:J,0)) -> 1 | U33: =IFERROR(T33-S33,0) -> 0.79285714 | V33: =COUNTIF(Collection!A:A,J33)+COUNTIF(Sold!A:A,J33) -> 1 | W33: =IFERROR(_xlfn.TEXTAFTER(_xlfn.XLOOKUP(J33,Collection!A:A,Collection!C:C,),"Cards "),_xlfn.TEXTAFTER(_xlfn.XLOOKUP(J33,Sold!A:A,Sold!C:C,),"Cards ")) -> 2024 Panini Donruss Optic | X33: =IFERROR(_xlfn.XLOOKUP(J33,Collection!A:A,Collection!B:B,),_xlfn.XLOOKUP(J33,Sold!A:A,Sold!B:B,)) -> Jaylen Brown [Purple] #206 | Y33: . | AB33: ronnierippzcards | AC33: -2.66745
B34: R | C34: iceball | D34: 46148 | E34: Givvy 4 | F34: 0 | G34: 0 | H34: 0 | I34: Sheppard | J34: 9782911 | K34: 298 | L34: https://www.whatnot.com/order/9Nw32iaBQX4B786bgpSBCs | M34: whatnot.com/order/9Nw32iaBQX4B786bgpSBCs $0.00 + $0.21 (Shared Shipping) + $0.02 Tax = Total of $0.23 | N34: =IFERROR(_xlfn.TEXTAFTER(L34,"https://www."),"")&CHAR(10)&_xlfn.CONCAT(TEXT(F34,"$0.00")," + ",TEXT(P34,"$0.00")," (Shared Shipping) + ",TEXT(R34,"$0.00")," Tax = Total of ",TEXT(S34,"$0.00")) -> whatnot.com/order/9Nw32iaBQX4B786bgpSBCs $0.00 + $0.21 (Shared Shipping) + $0.00 Tax = Total of $0.21 | O34: =SUM(F34:H34) -> 0 | P34: =SUMIFS(G:G,C:C,C34,D:D,D34)/COUNTIFS(C:C,C34,D:D,D34) -> 0.20714286 | Q34: =+F34+P34 -> 0.20714286 | R34: =IF(H34=0,0,Q34*0.1025) -> 0 | S34: =+Q34+R34 -> 0.20714286 | T34: =IFERROR(_xlfn.XLOOKUP(J34,Collection!A:A,Collection!D:D,0)/100/_xlfn.XLOOKUP(J34,Collection!A:A,Collection!J:J,0),_xlfn.XLOOKUP(J34,Sold!A:A,Sold!D:D,0)/100/_xlfn.XLOOKUP(J34,Sold!A:A,Sold!J:J,0)) -> 1.82 | U34: =IFERROR(T34-S34,0) -> 1.6128571 | V34: =COUNTIF(Collection!A:A,J34)+COUNTIF(Sold!A:A,J34) -> 1 | W34: =IFERROR(_xlfn.TEXTAFTER(_xlfn.XLOOKUP(J34,Collection!A:A,Collection!C:C,),"Cards "),_xlfn.TEXTAFTER(_xlfn.XLOOKUP(J34,Sold!A:A,Sold!C:C,),"Cards ")) -> 2024 Panini Select | X34: =IFERROR(_xlfn.XLOOKUP(J34,Collection!A:A,Collection!B:B,),_xlfn.XLOOKUP(J34,Sold!A:A,Sold!B:B,)) -> Reed Sheppard [Blue Cracked Ice Prizm] #68 | Y34: . | AB34: cardseal | AC34: -2.8825
B35: R | C35: iceball | D35: 46148 | E35: Givvy 4 | F35: 0 | G35: 0 | H35: 0 | I35: Curry | J35: 9265999 | K35: 377 | L35: https://www.whatnot.com/order/9Nw32iaBQX4B786bgpSBCs | M35: whatnot.com/order/9Nw32iaBQX4B786bgpSBCs $0.00 + $0.21 (Shared Shipping) + $0.02 Tax = Total of $0.23 | N35: =IFERROR(_xlfn.TEXTAFTER(L35,"https://www."),"")&CHAR(10)&_xlfn.CONCAT(TEXT(F35,"$0.00")," + ",TEXT(P35,"$0.00")," (Shared Shipping) + ",TEXT(R35,"$0.00")," Tax = Total of ",TEXT(S35,"$0.00")) -> whatnot.com/order/9Nw32iaBQX4B786bgpSBCs $0.00 + $0.21 (Shared Shipping) + $0.00 Tax = Total of $0.21 | O35: =SUM(F35:H35) -> 0 | P35: =SUMIFS(G:G,C:C,C35,D:D,D35)/COUNTIFS(C:C,C35,D:D,D35) -> 0.20714286 | Q35: =+F35+P35 -> 0.20714286 | R35: =IF(H35=0,0,Q35*0.1025) -> 0 | S35: =+Q35+R35 -> 0.20714286 | T35: =IFERROR(_xlfn.XLOOKUP(J35,Collection!A:A,Collection!D:D,0)/100/_xlfn.XLOOKUP(J35,Collection!A:A,Collection!J:J,0),_xlfn.XLOOKUP(J35,Sold!A:A,Sold!D:D,0)/100/_xlfn.XLOOKUP(J35,Sold!A:A,Sold!J:J,0)) -> 1.71 | U35: =IFERROR(T35-S35,0) -> 1.5028571 | V35: =COUNTIF(Collection!A:A,J35)+COUNTIF(Sold!A:A,J35) -> 1 | W35: =IFERROR(_xlfn.TEXTAFTER(_xlfn.XLOOKUP(J35,Collection!A:A,Collection!C:C,),"Cards "),_xlfn.TEXTAFTER(_xlfn.XLOOKUP(J35,Sold!A:A,Sold!C:C,),"Cards ")) -> 2024 Panini Revolution Hardwood Legacy | X35: =IFERROR(_xlfn.XLOOKUP(J35,Collection!A:A,Collection!B:B,),_xlfn.XLOOKUP(J35,Sold!A:A,Sold!B:B,)) -> Stephen Curry #3 | Y35: Verify Parallel - Stephen Curry #3 - 2024 Panini Revolution Hardwood Legac | AB35: kadenjc1 | AC35: -3.511375
B36: R | C36: iceball | D36: 46148 | E36: 125 | F36: 2.36 | G36: 0 | H36: 0.24 | I36: Luka | J36: 8406896 | K36: 515 | L36: https://www.whatnot.com/order/N3ommW2GZtgbdFUhrqPhaC | M36: whatnot.com/order/N3ommW2GZtgbdFUhrqPhaC $2.36 + $0.21 (Shared Shipping) + $0.26 Tax = Total of $2.83 | N36: =IFERROR(_xlfn.TEXTAFTER(L36,"https://www."),"")&CHAR(10)&_xlfn.CONCAT(TEXT(F36,"$0.00")," + ",TEXT(P36,"$0.00")," (Shared Shipping) + ",TEXT(R36,"$0.00")," Tax = Total of ",TEXT(S36,"$0.00")) -> whatnot.com/order/N3ommW2GZtgbdFUhrqPhaC $2.36 + $0.21 (Shared Shipping) + $0.26 Tax = Total of $2.83 | O36: =SUM(F36:H36) -> 2.6 | P36: =SUMIFS(G:G,C:C,C36,D:D,D36)/COUNTIFS(C:C,C36,D:D,D36) -> 0.20714286 | Q36: =+F36+P36 -> 2.5671429 | R36: =IF(H36=0,0,Q36*0.1025) -> 0.26313214 | S36: =+Q36+R36 -> 2.830275 | T36: =IFERROR(_xlfn.XLOOKUP(J36,Collection!A:A,Collection!D:D,0)/100/_xlfn.XLOOKUP(J36,Collection!A:A,Collection!J:J,0),_xlfn.XLOOKUP(J36,Sold!A:A,Sold!D:D,0)/100/_xlfn.XLOOKUP(J36,Sold!A:A,Sold!J:J,0)) -> 1.02 | U36: =IFERROR(T36-S36,0) -> -1.810275 | V36: =COUNTIF(Collection!A:A,J36)+COUNTIF(Sold!A:A,J36) -> 1 | W36: =IFERROR(_xlfn.TEXTAFTER(_xlfn.XLOOKUP(J36,Collection!A:A,Collection!C:C,),"Cards "),_xlfn.TEXTAFTER(_xlfn.XLOOKUP(J36,Sold!A:A,Sold!C:C,),"Cards ")) -> 2024 Panini NBA Hoops Frequent Flyers | X36: =IFERROR(_xlfn.XLOOKUP(J36,Collection!A:A,Collection!B:B,),_xlfn.XLOOKUP(J36,Sold!A:A,Sold!B:B,)) -> Luka Doncic #3 | Y36: . | AB36: millenniumcards | AC36: -3.654725
B37: R | C37: iceball | D37: 46148 | E37: 125 | F37: 2.33 | G37: 0 | H37: 0.24 | I37: Luka | J37: 8537640 | K37: 361 | L37: https://www.whatnot.com/order/N3ommW2GZtgbdFUhrqPhaC | M37: whatnot.com/order/N3ommW2GZtgbdFUhrqPhaC $2.33 + $0.21 (Shared Shipping) + $0.26 Tax = Total of $2.80 | N37: =IFERROR(_xlfn.TEXTAFTER(L37,"https://www."),"")&CHAR(10)&_xlfn.CONCAT(TEXT(F37,"$0.00")," + ",TEXT(P37,"$0.00")," (Shared Shipping) + ",TEXT(R37,"$0.00")," Tax = Total of ",TEXT(S37,"$0.00")) -> whatnot.com/order/N3ommW2GZtgbdFUhrqPhaC $2.33 + $0.21 (Shared Shipping) + $0.26 Tax = Total of $2.80 | O37: =SUM(F37:H37) -> 2.57 | P37: =SUMIFS(G:G,C:C,C37,D:D,D37)/COUNTIFS(C:C,C37,D:D,D37) -> 0.20714286 | Q37: =+F37+P37 -> 2.5371429 | R37: =IF(H37=0,0,Q37*0.1025) -> 0.26005714 | S37: =+Q37+R37 -> 2.7972 | T37: =IFERROR(_xlfn.XLOOKUP(J37,Collection!A:A,Collection!D:D,0)/100/_xlfn.XLOOKUP(J37,Collection!A:A,Collection!J:J,0),_xlfn.XLOOKUP(J37,Sold!A:A,Sold!D:D,0)/100/_xlfn.XLOOKUP(J37,Sold!A:A,Sold!J:J,0)) -> 1.71 | U37: =IFERROR(T37-S37,0) -> -1.0872 | V37: =COUNTIF(Collection!A:A,J37)+COUNTIF(Sold!A:A,J37) -> 1 | W37: =IFERROR(_xlfn.TEXTAFTER(_xlfn.XLOOKUP(J37,Collection!A:A,Collection!C:C,),"Cards "),_xlfn.TEXTAFTER(_xlfn.XLOOKUP(J37,Sold!A:A,Sold!C:C,),"Cards ")) -> 2024 Panini Prizm | X37: =IFERROR(_xlfn.XLOOKUP(J37,Collection!A:A,Collection!B:B,),_xlfn.XLOOKUP(J37,Sold!A:A,Sold!B:B,)) -> Luka Doncic #89 | Y37: . | AB37: Hoot2000 | AC37: -4.0947812
B38: R | C38: iceball | D38: 46148 | E38: 125 | F38: 2.33 | G38: 0 | H38: 0.24 | I38: Luka | J38: 2948779 | K38: 365 | L38: https://www.whatnot.com/order/N3ommW2GZtgbdFUhrqPhaC | M38: whatnot.com/order/N3ommW2GZtgbdFUhrqPhaC $2.33 + $0.21 (Shared Shipping) + $0.26 Tax = Total of $2.80 | N38: =IFERROR(_xlfn.TEXTAFTER(L38,"https://www."),"")&CHAR(10)&_xlfn.CONCAT(TEXT(F38,"$0.00")," + ",TEXT(P38,"$0.00")," (Shared Shipping) + ",TEXT(R38,"$0.00")," Tax = Total of ",TEXT(S38,"$0.00")) -> whatnot.com/order/N3ommW2GZtgbdFUhrqPhaC $2.33 + $0.21 (Shared Shipping) + $0.26 Tax = Total of $2.80 | O38: =SUM(F38:H38) -> 2.57 | P38: =SUMIFS(G:G,C:C,C38,D:D,D38)/COUNTIFS(C:C,C38,D:D,D38) -> 0.20714286 | Q38: =+F38+P38 -> 2.5371429 | R38: =IF(H38=0,0,Q38*0.1025) -> 0.26005714 | S38: =+Q38+R38 -> 2.7972 | T38: =IFERROR(_xlfn.XLOOKUP(J38,Collection!A:A,Collection!D:D,0)/100/_xlfn.XLOOKUP(J38,Collection!A:A,Collection!J:J,0),_xlfn.XLOOKUP(J38,Sold!A:A,Sold!D:D,0)/100/_xlfn.XLOOKUP(J38,Sold!A:A,Sold!J:J,0)) -> 1.74 | U38: =IFERROR(T38-S38,0) -> -1.0572 | V38: =COUNTIF(Collection!A:A,J38)+COUNTIF(Sold!A:A,J38) -> 1 | W38: =IFERROR(_xlfn.TEXTAFTER(_xlfn.XLOOKUP(J38,Collection!A:A,Collection!C:C,),"Cards "),_xlfn.TEXTAFTER(_xlfn.XLOOKUP(J38,Sold!A:A,Sold!C:C,),"Cards ")) -> 2020 Panini Chronicles | X38: =IFERROR(_xlfn.XLOOKUP(J38,Collection!A:A,Collection!B:B,),_xlfn.XLOOKUP(J38,Sold!A:A,Sold!B:B,)) -> Luka Doncic [Pink] #228 | Y38: . | AB38: brash1986 | AC38: -4.41835
B39: R | C39: iceball | D39: 46148 | E39: 125 | F39: 2.33 | G39: 0 | H39: 0.24 | I39: Luka | J39: 6834778 | K39: 312 | L39: https://www.whatnot.com/order/N3ommW2GZtgbdFUhrqPhaC | M39: whatnot.com/order/N3ommW2GZtgbdFUhrqPhaC $2.33 + $0.21 (Shared Shipping) + $0.26 Tax = Total of $2.80 | N39: =IFERROR(_xlfn.TEXTAFTER(L39,"https://www."),"")&CHAR(10)&_xlfn.CONCAT(TEXT(F39,"$0.00")," + ",TEXT(P39,"$0.00")," (Shared Shipping) + ",TEXT(R39,"$0.00")," Tax = Total of ",TEXT(S39,"$0.00")) -> whatnot.com/order/N3ommW2GZtgbdFUhrqPhaC $2.33 + $0.21 (Shared Shipping) + $0.26 Tax = Total of $2.80 | O39: =SUM(F39:H39) -> 2.57 | P39: =SUMIFS(G:G,C:C,C39,D:D,D39)/COUNTIFS(C:C,C39,D:D,D39) -> 0.20714286 | Q39: =+F39+P39 -> 2.5371429 | R39: =IF(H39=0,0,Q39*0.1025) -> 0.26005714 | S39: =+Q39+R39 -> 2.7972 | T39: =IFERROR(_xlfn.XLOOKUP(J39,Collection!A:A,Collection!D:D,0)/100/_xlfn.XLOOKUP(J39,Collection!A:A,Collection!J:J,0),_xlfn.XLOOKUP(J39,Sold!A:A,Sold!D:D,0)/100/_xlfn.XLOOKUP(J39,Sold!A:A,Sold!J:J,0)) -> 2.05 | U39: =IFERROR(T39-S39,0) -> -0.7472 | V39: =COUNTIF(Collection!A:A,J39)+COUNTIF(Sold!A:A,J39) -> 1 | W39: =IFERROR(_xlfn.TEXTAFTER(_xlfn.XLOOKUP(J39,Collection!A:A,Collection!C:C,),"Cards "),_xlfn.TEXTAFTER(_xlfn.XLOOKUP(J39,Sold!A:A,Sold!C:C,),"Cards ")) -> 2023 Donruss Optic Express Lane | X39: =IFERROR(_xlfn.XLOOKUP(J39,Collection!A:A,Collection!B:B,),_xlfn.XLOOKUP(J39,Sold!A:A,Sold!B:B,)) -> Luka Doncic [Purple] #13 | Y39: Verify Parallel | AB39: wadek2332 | AC39: -4.420875
B40: R | C40: iceball | D40: 46148 | E40: 125 | F40: 2.33 | G40: 0 | H40: 0.24 | I40: Luka | J40: 2946119 | K40: 281 | L40: https://www.whatnot.com/order/N3ommW2GZtgbdFUhrqPhaC | M40: whatnot.com/order/N3ommW2GZtgbdFUhrqPhaC $2.33 + $0.21 (Shared Shipping) + $0.26 Tax = Total of $2.80 | N40: =IFERROR(_xlfn.TEXTAFTER(L40,"https://www."),"")&CHAR(10)&_xlfn.CONCAT(TEXT(F40,"$0.00")," + ",TEXT(P40,"$0.00")," (Shared Shipping) + ",TEXT(R40,"$0.00")," Tax = Total of ",TEXT(S40,"$0.00")) -> whatnot.com/order/N3ommW2GZtgbdFUhrqPhaC $2.33 + $0.21 (Shared Shipping) + $0.26 Tax = Total of $2.80 | O40: =SUM(F40:H40) -> 2.57 | P40: =SUMIFS(G:G,C:C,C40,D:D,D40)/COUNTIFS(C:C,C40,D:D,D40) -> 0.20714286 | Q40: =+F40+P40 -> 2.5371429 | R40: =IF(H40=0,0,Q40*0.1025) -> 0.26005714 | S40: =+Q40+R40 -> 2.7972 | T40: =IFERROR(_xlfn.XLOOKUP(J40,Collection!A:A,Collection!D:D,0)/100/_xlfn.XLOOKUP(J40,Collection!A:A,Collection!J:J,0),_xlfn.XLOOKUP(J40,Sold!A:A,Sold!D:D,0)/100/_xlfn.XLOOKUP(J40,Sold!A:A,Sold!J:J,0)) -> 1.99 | U40: =IFERROR(T40-S40,0) -> -0.8072 | V40: =COUNTIF(Collection!A:A,J40)+COUNTIF(Sold!A:A,J40) -> 1 | W40: =IFERROR(_xlfn.TEXTAFTER(_xlfn.XLOOKUP(J40,Collection!A:A,Collection!C:C,),"Cards "),_xlfn.TEXTAFTER(_xlfn.XLOOKUP(J40,Sold!A:A,Sold!C:C,),"Cards ")) -> 2020 Panini Chronicles | X40: =IFERROR(_xlfn.XLOOKUP(J40,Collection!A:A,Collection!B:B,),_xlfn.XLOOKUP(J40,Sold!A:A,Sold!B:B,)) -> Luka Doncic #519 | Y40: . | AB40: jjcards23 | AC40: -4.47065
B41: R | C41: iceball | D41: 46148 | E41: 125 | F41: 2.33 | G41: 0 | H41: 0.24 | I41: Luka | J41: 11360390 | K41: 599 | L41: https://www.whatnot.com/order/N3ommW2GZtgbdFUhrqPhaC | M41: whatnot.com/order/N3ommW2GZtgbdFUhrqPhaC $2.33 + $0.21 (Shared Shipping) + $0.26 Tax = Total of $2.80 | N41: =IFERROR(_xlfn.TEXTAFTER(L41,"https://www."),"")&CHAR(10)&_xlfn.CONCAT(TEXT(F41,"$0.00")," + ",TEXT(P41,"$0.00")," (Shared Shipping) + ",TEXT(R41,"$0.00")," Tax = Total of ",TEXT(S41,"$0.00")) -> whatnot.com/order/N3ommW2GZtgbdFUhrqPhaC $2.33 + $0.21 (Shared Shipping) + $0.26 Tax = Total of $2.80 | O41: =SUM(F41:H41) -> 2.57 | P41: =SUMIFS(G:G,C:C,C41,D:D,D41)/COUNTIFS(C:C,C41,D:D,D41) -> 0.20714286 | Q41: =+F41+P41 -> 2.5371429 | R41: =IF(H41=0,0,Q41*0.1025) -> 0.26005714 | S41: =+Q41+R41 -> 2.7972 | T41: =IFERROR(_xlfn.XLOOKUP(J41,Collection!A:A,Collection!D:D,0)/100/_xlfn.XLOOKUP(J41,Collection!A:A,Collection!J:J,0),_xlfn.XLOOKUP(J41,Sold!A:A,Sold!D:D,0)/100/_xlfn.XLOOKUP(J41,Sold!A:A,Sold!J:J,0)) -> 0 | U41: =IFERROR(T41-S41,0) -> -2.7972 | V41: =COUNTIF(Collection!A:A,J41)+COUNTIF(Sold!A:A,J41) -> 1 | W41: =IFERROR(_xlfn.TEXTAFTER(_xlfn.XLOOKUP(J41,Collection!A:A,Collection!C:C,),"Cards "),_xlfn.TEXTAFTER(_xlfn.XLOOKUP(J41,Sold!A:A,Sold!C:C,),"Cards ")) -> 2020 Panini Chronicles Hometown Heroes Rookie Autographs | X41: =IFERROR(_xlfn.XLOOKUP(J41,Collection!A:A,Collection!B:B,),_xlfn.XLOOKUP(J41,Sold!A:A,Sold!B:B,)) -> Luka Doncic #554 | Y41: . | AB41: grazicards | AC41: -4.683875
B42: R | C42: iceball | D42: 46148 | E42: 125 | F42: 2.33 | G42: 0 | H42: 0.24 | I42: Luka | J42: 5001342 | K42: 362 | L42: https://www.whatnot.com/order/N3ommW2GZtgbdFUhrqPhaC | M42: whatnot.com/order/N3ommW2GZtgbdFUhrqPhaC $2.33 + $0.21 (Shared Shipping) + $0.26 Tax = Total of $2.80 | N42: =IFERROR(_xlfn.TEXTAFTER(L42,"https://www."),"")&CHAR(10)&_xlfn.CONCAT(TEXT(F42,"$0.00")," + ",TEXT(P42,"$0.00")," (Shared Shipping) + ",TEXT(R42,"$0.00")," Tax = Total of ",TEXT(S42,"$0.00")) -> whatnot.com/order/N3ommW2GZtgbdFUhrqPhaC $2.33 + $0.21 (Shared Shipping) + $0.26 Tax = Total of $2.80 | O42: =SUM(F42:H42) -> 2.57 | P42: =SUMIFS(G:G,C:C,C42,D:D,D42)/COUNTIFS(C:C,C42,D:D,D42) -> 0.20714286 | Q42: =+F42+P42 -> 2.5371429 | R42: =IF(H42=0,0,Q42*0.1025) -> 0.26005714 | S42: =+Q42+R42 -> 2.7972 | T42: =IFERROR(_xlfn.XLOOKUP(J42,Collection!A:A,Collection!D:D,0)/100/_xlfn.XLOOKUP(J42,Collection!A:A,Collection!J:J,0),_xlfn.XLOOKUP(J42,Sold!A:A,Sold!D:D,0)/100/_xlfn.XLOOKUP(J42,Sold!A:A,Sold!J:J,0)) -> 1.67 | U42: =IFERROR(T42-S42,0) -> -1.1272 | V42: =COUNTIF(Collection!A:A,J42)+COUNTIF(Sold!A:A,J42) -> 1 | W42: =IFERROR(_xlfn.TEXTAFTER(_xlfn.XLOOKUP(J42,Collection!A:A,Collection!C:C,),"Cards "),_xlfn.TEXTAFTER(_xlfn.XLOOKUP(J42,Sold!A:A,Sold!C:C,),"Cards ")) -> 2022 Panini Donruss Magicians | X42: =IFERROR(_xlfn.XLOOKUP(J42,Collection!A:A,Collection!B:B,),_xlfn.XLOOKUP(J42,Sold!A:A,Sold!B:B,)) -> Luka Doncic #2 | Y42: . | AB42: ritchievault | AC42: -5.0730417
B43: R | C43: iceball | D43: 46148 | E43: 125 | F43: 2.33 | G43: 0 | H43: 0.24 | I43: Luka | J43: N/A | L43: https://www.whatnot.com/order/N3ommW2GZtgbdFUhrqPhaC | M43: whatnot.com/order/N3ommW2GZtgbdFUhrqPhaC $2.33 + $0.21 (Shared Shipping) + $0.26 Tax = Total of $2.80 | N43: =IFERROR(_xlfn.TEXTAFTER(L43,"https://www."),"")&CHAR(10)&_xlfn.CONCAT(TEXT(F43,"$0.00")," + ",TEXT(P43,"$0.00")," (Shared Shipping) + ",TEXT(R43,"$0.00")," Tax = Total of ",TEXT(S43,"$0.00")) -> whatnot.com/order/N3ommW2GZtgbdFUhrqPhaC $2.33 + $0.21 (Shared Shipping) + $0.26 Tax = Total of $2.80 | O43: =SUM(F43:H43) -> 2.57 | P43: =SUMIFS(G:G,C:C,C43,D:D,D43)/COUNTIFS(C:C,C43,D:D,D43) -> 0.20714286 | Q43: =+F43+P43 -> 2.5371429 | R43: =IF(H43=0,0,Q43*0.1025) -> 0.26005714 | S43: =+Q43+R43 -> 2.7972 | T43: =IFERROR(_xlfn.XLOOKUP(J43,Collection!A:A,Collection!D:D,0)/100/_xlfn.XLOOKUP(J43,Collection!A:A,Collection!J:J,0),_xlfn.XLOOKUP(J43,Sold!A:A,Sold!D:D,0)/100/_xlfn.XLOOKUP(J43,Sold!A:A,Sold!J:J,0)) -> #DIV/0! | U43: =IFERROR(T43-S43,0) -> 0 | V43: =COUNTIF(Collection!A:A,J43)+COUNTIF(Sold!A:A,J43) -> 0 | W43: =IFERROR(_xlfn.TEXTAFTER(_xlfn.XLOOKUP(J43,Collection!A:A,Collection!C:C,),"Cards "),_xlfn.TEXTAFTER(_xlfn.XLOOKUP(J43,Sold!A:A,Sold!C:C,),"Cards ")) -> #N/A | X43: =IFERROR(_xlfn.XLOOKUP(J43,Collection!A:A,Collection!B:B,),_xlfn.XLOOKUP(J43,Sold!A:A,Sold!B:B,)) -> #N/A | Y43: Not listed | AB43: Tasrelics | AC43: -5.512375
B44: R | C44: iceball | D44: 46148 | E44: 125 | F44: 2.33 | G44: 0 | H44: 0.24 | I44: Luka | J44: 6284400 | K44: 436 | L44: https://www.whatnot.com/order/N3ommW2GZtgbdFUhrqPhaC | M44: whatnot.com/order/N3ommW2GZtgbdFUhrqPhaC $2.33 + $0.21 (Shared Shipping) + $0.26 Tax = Total of $2.80 | N44: =IFERROR(_xlfn.TEXTAFTER(L44,"https://www."),"")&CHAR(10)&_xlfn.CONCAT(TEXT(F44,"$0.00")," + ",TEXT(P44,"$0.00")," (Shared Shipping) + ",TEXT(R44,"$0.00")," Tax = Total of ",TEXT(S44,"$0.00")) -> whatnot.com/order/N3ommW2GZtgbdFUhrqPhaC $2.33 + $0.21 (Shared Shipping) + $0.26 Tax = Total of $2.80 | O44: =SUM(F44:H44) -> 2.57 | P44: =SUMIFS(G:G,C:C,C44,D:D,D44)/COUNTIFS(C:C,C44,D:D,D44) -> 0.20714286 | Q44: =+F44+P44 -> 2.5371429 | R44: =IF(H44=0,0,Q44*0.1025) -> 0.26005714 | S44: =+Q44+R44 -> 2.7972 | T44: =IFERROR(_xlfn.XLOOKUP(J44,Collection!A:A,Collection!D:D,0)/100/_xlfn.XLOOKUP(J44,Collection!A:A,Collection!J:J,0),_xlfn.XLOOKUP(J44,Sold!A:A,Sold!D:D,0)/100/_xlfn.XLOOKUP(J44,Sold!A:A,Sold!J:J,0)) -> 1.21 | U44: =IFERROR(T44-S44,0) -> -1.5872 | V44: =COUNTIF(Collection!A:A,J44)+COUNTIF(Sold!A:A,J44) -> 1 | W44: =IFERROR(_xlfn.TEXTAFTER(_xlfn.XLOOKUP(J44,Collection!A:A,Collection!C:C,),"Cards "),_xlfn.TEXTAFTER(_xlfn.XLOOKUP(J44,Sold!A:A,Sold!C:C,),"Cards ")) -> 2023 Panini Donruss | X44: =IFERROR(_xlfn.XLOOKUP(J44,Collection!A:A,Collection!B:B,),_xlfn.XLOOKUP(J44,Sold!A:A,Sold!B:B,)) -> Luka Doncic #141 | Y44: . | AB44: jurcar | AC44: -6.0411591
B45: R | C45: iceball | D45: 46148 | E45: 126 | F45: 2.5 | G45: 0 | H45: 0.26 | I45: Luka | J45: 6422084 | K45: 387 | L45: https://www.whatnot.com/order/8DwoNWn73teh8obUuAY5eP | M45: whatnot.com/order/8DwoNWn73teh8obUuAY5eP $2.50 + $0.21 (Shared Shipping) + $0.28 Tax = Total of $2.98 | N45: =IFERROR(_xlfn.TEXTAFTER(L45,"https://www."),"")&CHAR(10)&_xlfn.CONCAT(TEXT(F45,"$0.00")," + ",TEXT(P45,"$0.00")," (Shared Shipping) + ",TEXT(R45,"$0.00")," Tax = Total of ",TEXT(S45,"$0.00")) -> whatnot.com/order/8DwoNWn73teh8obUuAY5eP $2.50 + $0.21 (Shared Shipping) + $0.28 Tax = Total of $2.98 | O45: =SUM(F45:H45) -> 2.76 | P45: =SUMIFS(G:G,C:C,C45,D:D,D45)/COUNTIFS(C:C,C45,D:D,D45) -> 0.20714286 | Q45: =+F45+P45 -> 2.7071429 | R45: =IF(H45=0,0,Q45*0.1025) -> 0.27748214 | S45: =+Q45+R45 -> 2.984625 | T45: =IFERROR(_xlfn.XLOOKUP(J45,Collection!A:A,Collection!D:D,0)/100/_xlfn.XLOOKUP(J45,Collection!A:A,Collection!J:J,0),_xlfn.XLOOKUP(J45,Sold!A:A,Sold!D:D,0)/100/_xlfn.XLOOKUP(J45,Sold!A:A,Sold!J:J,0)) -> 1.58 | U45: =IFERROR(T45-S45,0) -> -1.404625 | V45: =COUNTIF(Collection!A:A,J45)+COUNTIF(Sold!A:A,J45) -> 1 | W45: =IFERROR(_xlfn.TEXTAFTER(_xlfn.XLOOKUP(J45,Collection!A:A,Collection!C:C,),"Cards "),_xlfn.TEXTAFTER(_xlfn.XLOOKUP(J45,Sold!A:A,Sold!C:C,),"Cards ")) -> 2023 Panini Prizm Global Reach | X45: =IFERROR(_xlfn.XLOOKUP(J45,Collection!A:A,Collection!B:B,),_xlfn.XLOOKUP(J45,Sold!A:A,Sold!B:B,)) -> Luka Doncic #1 | Y45: . | AB45: gogreen_sportscards | AC45: -6.8176
B46: R | C46: iceball | D46: 46148 | E46: 126 | F46: 2.5 | G46: 0 | H46: 0.26 | I46: Luka | J46: 9265985 | K46: 378 | L46: https://www.whatnot.com/order/8DwoNWn73teh8obUuAY5eP | M46: whatnot.com/order/8DwoNWn73teh8obUuAY5eP $2.50 + $0.21 (Shared Shipping) + $0.28 Tax = Total of $2.98 | N46: =IFERROR(_xlfn.TEXTAFTER(L46,"https://www."),"")&CHAR(10)&_xlfn.CONCAT(TEXT(F46,"$0.00")," + ",TEXT(P46,"$0.00")," (Shared Shipping) + ",TEXT(R46,"$0.00")," Tax = Total of ",TEXT(S46,"$0.00")) -> whatnot.com/order/8DwoNWn73teh8obUuAY5eP $2.50 + $0.21 (Shared Shipping) + $0.28 Tax = Total of $2.98 | O46: =SUM(F46:H46) -> 2.76 | P46: =SUMIFS(G:G,C:C,C46,D:D,D46)/COUNTIFS(C:C,C46,D:D,D46) -> 0.20714286 | Q46: =+F46+P46 -> 2.7071429 | R46: =IF(H46=0,0,Q46*0.1025) -> 0.27748214 | S46: =+Q46+R46 -> 2.984625 | T46: =IFERROR(_xlfn.XLOOKUP(J46,Collection!A:A,Collection!D:D,0)/100/_xlfn.XLOOKUP(J46,Collection!A:A,Collection!J:J,0),_xlfn.XLOOKUP(J46,Sold!A:A,Sold!D:D,0)/100/_xlfn.XLOOKUP(J46,Sold!A:A,Sold!J:J,0)) -> 1.69 | U46: =IFERROR(T46-S46,0) -> -1.294625 | V46: =COUNTIF(Collection!A:A,J46)+COUNTIF(Sold!A:A,J46) -> 1 | W46: =IFERROR(_xlfn.TEXTAFTER(_xlfn.XLOOKUP(J46,Collection!A:A,Collection!C:C,),"Cards "),_xlfn.TEXTAFTER(_xlfn.XLOOKUP(J46,Sold!A:A,Sold!C:C,),"Cards ")) -> 2024 Panini Revolution Hardwood Legacy | X46: =IFERROR(_xlfn.XLOOKUP(J46,Collection!A:A,Collection!B:B,),_xlfn.XLOOKUP(J46,Sold!A:A,Sold!B:B,)) -> Luka Doncic #1 | Y46: . | AB46: jrtcardsandcollectibles | AC46: -7.011425
B47: R | C47: iceball | D47: 46148 | E47: 126 | F47: 2.5 | G47: 0 | H47: 0.26 | I47: Luka | J47: 10339925 | K47: 216 | L47: https://www.whatnot.com/order/8DwoNWn73teh8obUuAY5eP | M47: whatnot.com/order/8DwoNWn73teh8obUuAY5eP $2.50 + $0.21 (Shared Shipping) + $0.28 Tax = Total of $2.98 | N47: =IFERROR(_xlfn.TEXTAFTER(L47,"https://www."),"")&CHAR(10)&_xlfn.CONCAT(TEXT(F47,"$0.00")," + ",TEXT(P47,"$0.00")," (Shared Shipping) + ",TEXT(R47,"$0.00")," Tax = Total of ",TEXT(S47,"$0.00")) -> whatnot.com/order/8DwoNWn73teh8obUuAY5eP $2.50 + $0.21 (Shared Shipping) + $0.28 Tax = Total of $2.98 | O47: =SUM(F47:H47) -> 2.76 | P47: =SUMIFS(G:G,C:C,C47,D:D,D47)/COUNTIFS(C:C,C47,D:D,D47) -> 0.20714286 | Q47: =+F47+P47 -> 2.7071429 | R47: =IF(H47=0,0,Q47*0.1025) -> 0.27748214 | S47: =+Q47+R47 -> 2.984625 | T47: =IFERROR(_xlfn.XLOOKUP(J47,Collection!A:A,Collection!D:D,0)/100/_xlfn.XLOOKUP(J47,Collection!A:A,Collection!J:J,0),_xlfn.XLOOKUP(J47,Sold!A:A,Sold!D:D,0)/100/_xlfn.XLOOKUP(J47,Sold!A:A,Sold!J:J,0)) -> 2.32 | U47: =IFERROR(T47-S47,0) -> -0.664625 | V47: =COUNTIF(Collection!A:A,J47)+COUNTIF(Sold!A:A,J47) -> 1 | W47: =IFERROR(_xlfn.TEXTAFTER(_xlfn.XLOOKUP(J47,Collection!A:A,Collection!C:C,),"Cards "),_xlfn.TEXTAFTER(_xlfn.XLOOKUP(J47,Sold!A:A,Sold!C:C,),"Cards ")) -> 2024 Panini Mosaic Elevate | X47: =IFERROR(_xlfn.XLOOKUP(J47,Collection!A:A,Collection!B:B,),_xlfn.XLOOKUP(J47,Sold!A:A,Sold!B:B,)) -> Luka Doncic [Mosaic] #16 | Y47: 9959212 or 10339925 whats the difference | AB47: gerberlifebb | AC47: -9.218275
B48: R | C48: iceball | D48: 46148 | E48: 126 | F48: 2.5 | G48: 0 | H48: 0.26 | I48: Luka | J48: 6713723 | K48: 323 | L48: https://www.whatnot.com/order/8DwoNWn73teh8obUuAY5eP | M48: whatnot.com/order/8DwoNWn73teh8obUuAY5eP $2.50 + $0.21 (Shared Shipping) + $0.28 Tax = Total of $2.98 | N48: =IFERROR(_xlfn.TEXTAFTER(L48,"https://www."),"")&CHAR(10)&_xlfn.CONCAT(TEXT(F48,"$0.00")," + ",TEXT(P48,"$0.00")," (Shared Shipping) + ",TEXT(R48,"$0.00")," Tax = Total of ",TEXT(S48,"$0.00")) -> whatnot.com/order/8DwoNWn73teh8obUuAY5eP $2.50 + $0.21 (Shared Shipping) + $0.28 Tax = Total of $2.98 | O48: =SUM(F48:H48) -> 2.76 | P48: =SUMIFS(G:G,C:C,C48,D:D,D48)/COUNTIFS(C:C,C48,D:D,D48) -> 0.20714286 | Q48: =+F48+P48 -> 2.7071429 | R48: =IF(H48=0,0,Q48*0.1025) -> 0.27748214 | S48: =+Q48+R48 -> 2.984625 | T48: =IFERROR(_xlfn.XLOOKUP(J48,Collection!A:A,Collection!D:D,0)/100/_xlfn.XLOOKUP(J48,Collection!A:A,Collection!J:J,0),_xlfn.XLOOKUP(J48,Sold!A:A,Sold!D:D,0)/100/_xlfn.XLOOKUP(J48,Sold!A:A,Sold!J:J,0)) -> 1.35 | U48: =IFERROR(T48-S48,0) -> -1.634625 | V48: =COUNTIF(Collection!A:A,J48)+COUNTIF(Sold!A:A,J48) -> 1 | W48: =IFERROR(_xlfn.TEXTAFTER(_xlfn.XLOOKUP(J48,Collection!A:A,Collection!C:C,),"Cards "),_xlfn.TEXTAFTER(_xlfn.XLOOKUP(J48,Sold!A:A,Sold!C:C,),"Cards ")) -> 2023 Panini Select Thunder Lane | X48: =IFERROR(_xlfn.XLOOKUP(J48,Collection!A:A,Collection!B:B,),_xlfn.XLOOKUP(J48,Sold!A:A,Sold!B:B,)) -> Luka Doncic #3 | Y48: . | AB48: stealsndealscollectibles | AC48: -13.002475
B49: R | C49: iceball | D49: 46148 | E49: 126 | F49: 2.5 | G49: 0 | H49: 0.25 | I49: Luka | J49: 8560255 | K49: 393 | L49: https://www.whatnot.com/order/8DwoNWn73teh8obUuAY5eP | M49: whatnot.com/order/8DwoNWn73teh8obUuAY5eP $2.50 + $0.21 (Shared Shipping) + $0.28 Tax = Total of $2.98 | N49: =IFERROR(_xlfn.TEXTAFTER(L49,"https://www."),"")&CHAR(10)&_xlfn.CONCAT(TEXT(F49,"$0.00")," + ",TEXT(P49,"$0.00")," (Shared Shipping) + ",TEXT(R49,"$0.00")," Tax = Total of ",TEXT(S49,"$0.00")) -> whatnot.com/order/8DwoNWn73teh8obUuAY5eP $2.50 + $0.21 (Shared Shipping) + $0.28 Tax = Total of $2.98 | O49: =SUM(F49:H49) -> 2.75 | P49: =SUMIFS(G:G,C:C,C49,D:D,D49)/COUNTIFS(C:C,C49,D:D,D49) -> 0.20714286 | Q49: =+F49+P49 -> 2.7071429 | R49: =IF(H49=0,0,Q49*0.1025) -> 0.27748214 | S49: =+Q49+R49 -> 2.984625 | T49: =IFERROR(_xlfn.XLOOKUP(J49,Collection!A:A,Collection!D:D,0)/100/_xlfn.XLOOKUP(J49,Collection!A:A,Collection!J:J,0),_xlfn.XLOOKUP(J49,Sold!A:A,Sold!D:D,0)/100/_xlfn.XLOOKUP(J49,Sold!A:A,Sold!J:J,0)) -> 1.44 | U49: =IFERROR(T49-S49,0) -> -1.544625 | V49: =COUNTIF(Collection!A:A,J49)+COUNTIF(Sold!A:A,J49) -> 1 | W49: =IFERROR(_xlfn.TEXTAFTER(_xlfn.XLOOKUP(J49,Collection!A:A,Collection!C:C,),"Cards "),_xlfn.TEXTAFTER(_xlfn.XLOOKUP(J49,Sold!A:A,Sold!C:C,),"Cards ")) -> 2024 Panini Prizm Deep Space | X49: =IFERROR(_xlfn.XLOOKUP(J49,Collection!A:A,Collection!B:B,),_xlfn.XLOOKUP(J49,Sold!A:A,Sold!B:B,)) -> Luka Doncic #4 | Y49: . | AB49: Capital_Sports | AC49: -17.032375
B50: R | C50: iceball | D50: 46148 | E50: 126 | F50: 2.5 | G50: 0 | H50: 0.25 | I50: Luka | J50: 3727503 | K50: 396 | L50: https://www.whatnot.com/order/8DwoNWn73teh8obUuAY5eP | M50: whatnot.com/order/8DwoNWn73teh8obUuAY5eP $2.50 + $0.21 (Shared Shipping) + $0.28 Tax = Total of $2.98 | N50: =IFERROR(_xlfn.TEXTAFTER(L50,"https://www."),"")&CHAR(10)&_xlfn.CONCAT(TEXT(F50,"$0.00")," + ",TEXT(P50,"$0.00")," (Shared Shipping) + ",TEXT(R50,"$0.00")," Tax = Total of ",TEXT(S50,"$0.00")) -> whatnot.com/order/8DwoNWn73teh8obUuAY5eP $2.50 + $0.21 (Shared Shipping) + $0.28 Tax = Total of $2.98 | O50: =SUM(F50:H50) -> 2.75 | P50: =SUMIFS(G:G,C:C,C50,D:D,D50)/COUNTIFS(C:C,C50,D:D,D50) -> 0.20714286 | Q50: =+F50+P50 -> 2.7071429 | R50: =IF(H50=0,0,Q50*0.1025) -> 0.27748214 | S50: =+Q50+R50 -> 2.984625 | T50: =IFERROR(_xlfn.XLOOKUP(J50,Collection!A:A,Collection!D:D,0)/100/_xlfn.XLOOKUP(J50,Collection!A:A,Collection!J:J,0),_xlfn.XLOOKUP(J50,Sold!A:A,Sold!D:D,0)/100/_xlfn.XLOOKUP(J50,Sold!A:A,Sold!J:J,0)) -> 1.47 | U50: =IFERROR(T50-S50,0) -> -1.514625 | V50: =COUNTIF(Collection!A:A,J50)+COUNTIF(Sold!A:A,J50) -> 1 | W50: =IFERROR(_xlfn.TEXTAFTER(_xlfn.XLOOKUP(J50,Collection!A:A,Collection!C:C,),"Cards "),_xlfn.TEXTAFTER(_xlfn.XLOOKUP(J50,Sold!A:A,Sold!C:C,),"Cards ")) -> 2021 Panini Prizm | X50: =IFERROR(_xlfn.XLOOKUP(J50,Collection!A:A,Collection!B:B,),_xlfn.XLOOKUP(J50,Sold!A:A,Sold!B:B,)) -> Luka Doncic #223 | Y50: . | AB50: colexcardco | AC50: -18.72875
B51: R | C51: jrtcardsandcollectibles | D51: 46149 | E51: Givvy 2 | F51: 0 | G51: 0 | H51: 0 | I51: McMahon | J51: 12627605 | K51: 426 | L51: https://www.whatnot.com/order/ezSKfFW6zDG5UWaRKJYAXA | M51: whatnot.com/order/ezSKfFW6zDG5UWaRKJYAXA $0.00 + $0.00 (Shared Shipping) + $0.00 Tax = Total of $0.00 | N51: =IFERROR(_xlfn.TEXTAFTER(L51,"https://www."),"")&CHAR(10)&_xlfn.CONCAT(TEXT(F51,"$0.00")," + ",TEXT(P51,"$0.00")," (Shared Shipping) + ",TEXT(R51,"$0.00")," Tax = Total of ",TEXT(S51,"$0.00")) -> whatnot.com/order/ezSKfFW6zDG5UWaRKJYAXA $0.00 + $0.00 (Shared Shipping) + $0.00 Tax = Total of $0.00 | O51: =SUM(F51:H51) -> 0 | P51: =SUMIFS(G:G,C:C,C51,D:D,D51)/COUNTIFS(C:C,C51,D:D,D51) -> 0 | Q51: =+F51+P51 -> 0 | R51: =IF(H51=0,0,Q51*0.1025) -> 0 | S51: =+Q51+R51 -> 0 | T51: =IFERROR(_xlfn.XLOOKUP(J51,Collection!A:A,Collection!D:D,0)/100/_xlfn.XLOOKUP(J51,Collection!A:A,Collection!J:J,0),_xlfn.XLOOKUP(J51,Sold!A:A,Sold!D:D,0)/100/_xlfn.XLOOKUP(J51,Sold!A:A,Sold!J:J,0)) -> 1.5 | U51: =IFERROR(T51-S51,0) -> 1.5 | V51: =COUNTIF(Collection!A:A,J51)+COUNTIF(Sold!A:A,J51) -> 1 | W51: =IFERROR(_xlfn.TEXTAFTER(_xlfn.XLOOKUP(J51,Collection!A:A,Collection!C:C,),"Cards "),_xlfn.TEXTAFTER(_xlfn.XLOOKUP(J51,Sold!A:A,Sold!C:C,),"Cards ")) -> 2025 Bowman Prospects | X51: =IFERROR(_xlfn.XLOOKUP(J51,Collection!A:A,Collection!B:B,),_xlfn.XLOOKUP(J51,Sold!A:A,Sold!B:B,)) -> Cotie McMahon #BPP-30 | Y51: . | AB51: msuburress | AC51: -19.7215
B52: R | C52: jrtcardsandcollectibles | D52: 46149 | E52: Givvy 10 | F52: 0 | G52: 0 | H52: 0 | I52: Salaun | J52: 10818673 | K52: 567 | L52: https://www.whatnot.com/order/Xz3tx8zp8BHqHykj7qkN3x | M52: whatnot.com/order/Xz3tx8zp8BHqHykj7qkN3x $0.00 + $0.00 (Shared Shipping) + $0.00 Tax = Total of $0.00 | N52: =IFERROR(_xlfn.TEXTAFTER(L52,"https://www."),"")&CHAR(10)&_xlfn.CONCAT(TEXT(F52,"$0.00")," + ",TEXT(P52,"$0.00")," (Shared Shipping) + ",TEXT(R52,"$0.00")," Tax = Total of ",TEXT(S52,"$0.00")) -> whatnot.com/order/Xz3tx8zp8BHqHykj7qkN3x $0.00 + $0.00 (Shared Shipping) + $0.00 Tax = Total of $0.00 | O52: =SUM(F52:H52) -> 0 | P52: =SUMIFS(G:G,C:C,C52,D:D,D52)/COUNTIFS(C:C,C52,D:D,D52) -> 0 | Q52: =+F52+P52 -> 0 | R52: =IF(H52=0,0,Q52*0.1025) -> 0 | S52: =+Q52+R52 -> 0 | T52: =IFERROR(_xlfn.XLOOKUP(J52,Collection!A:A,Collection!D:D,0)/100/_xlfn.XLOOKUP(J52,Collection!A:A,Collection!J:J,0),_xlfn.XLOOKUP(J52,Sold!A:A,Sold!D:D,0)/100/_xlfn.XLOOKUP(J52,Sold!A:A,Sold!J:J,0)) -> 0.99 | U52: =IFERROR(T52-S52,0) -> 0.99 | V52: =COUNTIF(Collection!A:A,J52)+COUNTIF(Sold!A:A,J52) -> 1 | W52: =IFERROR(_xlfn.TEXTAFTER(_xlfn.XLOOKUP(J52,Collection!A:A,Collection!C:C,),"Cards "),_xlfn.TEXTAFTER(_xlfn.XLOOKUP(J52,Sold!A:A,Sold!C:C,),"Cards ")) -> 2025 Topps | X52: =IFERROR(_xlfn.XLOOKUP(J52,Collection!A:A,Collection!B:B,),_xlfn.XLOOKUP(J52,Sold!A:A,Sold!B:B,)) -> Tidjane Salaun #71 | Y52: . | AB52: mc_sportscards | AC52: -21.84
B53: R | C53: cardboardbeast | D53: 46150 | E53: 6 | F53: 1 | G53: 1.39 | H53: 0.25 | I53: Luka | J53: 2857292 | K53: 110 | L53: https://www.whatnot.com/order/THjJHwGpnJ2cNFaSnvcckW | M53: whatnot.com/order/THjJHwGpnJ2cNFaSnvcckW $1.00 + $1.00 (Shared Shipping) + $0.21 Tax = Total of $2.21 | N53: =IFERROR(_xlfn.TEXTAFTER(L53,"https://www."),"")&CHAR(10)&_xlfn.CONCAT(TEXT(F53,"$0.00")," + ",TEXT(P53,"$0.00")," (Shared Shipping) + ",TEXT(R53,"$0.00")," Tax = Total of ",TEXT(S53,"$0.00")) -> whatnot.com/order/THjJHwGpnJ2cNFaSnvcckW $1.00 + $1.00 (Shared Shipping) + $0.21 Tax = Total of $2.21 | O53: =SUM(F53:H53) -> 2.64 | P53: =SUMIFS(G:G,C:C,C53,D:D,D53)/COUNTIFS(C:C,C53,D:D,D53) -> 1 | Q53: =+F53+P53 -> 2 | R53: =IF(H53=0,0,Q53*0.1025) -> 0.205 | S53: =+Q53+R53 -> 2.205 | T53: =IFERROR(_xlfn.XLOOKUP(J53,Collection!A:A,Collection!D:D,0)/100/_xlfn.XLOOKUP(J53,Collection!A:A,Collection!J:J,0),_xlfn.XLOOKUP(J53,Sold!A:A,Sold!D:D,0)/100/_xlfn.XLOOKUP(J53,Sold!A:A,Sold!J:J,0)) -> 5.87 | U53: =IFERROR(T53-S53,0) -> 3.665 | V53: =COUNTIF(Collection!A:A,J53)+COUNTIF(Sold!A:A,J53) -> 1 | W53: =IFERROR(_xlfn.TEXTAFTER(_xlfn.XLOOKUP(J53,Collection!A:A,Collection!C:C,),"Cards "),_xlfn.TEXTAFTER(_xlfn.XLOOKUP(J53,Sold!A:A,Sold!C:C,),"Cards ")) -> 2019 Panini Chronicles | X53: =IFERROR(_xlfn.XLOOKUP(J53,Collection!A:A,Collection!B:B,),_xlfn.XLOOKUP(J53,Sold!A:A,Sold!B:B,)) -> Luka Doncic [Teal] #15 | Y53: . | AB53: kenjay_cards | AC53: -27.750875
B54: R | C54: cardboardbeast | D54: 46150 | E54: 7 | F54: 1 | G54: 3.36 | H54: 0.46 | I54: Jordan | J54: N/A | L54: https://www.whatnot.com/order/EifBu6qeaD4paxGVjbK2N2 | M54: whatnot.com/order/EifBu6qeaD4paxGVjbK2N2 $1.00 + $1.00 (Shared Shipping) + $0.21 Tax = Total of $2.21 | N54: =IFERROR(_xlfn.TEXTAFTER(L54,"https://www."),"")&CHAR(10)&_xlfn.CONCAT(TEXT(F54,"$0.00")," + ",TEXT(P54,"$0.00")," (Shared Shipping) + ",TEXT(R54,"$0.00")," Tax = Total of ",TEXT(S54,"$0.00")) -> whatnot.com/order/EifBu6qeaD4paxGVjbK2N2 $1.00 + $1.00 (Shared Shipping) + $0.21 Tax = Total of $2.21 | O54: =SUM(F54:H54) -> 4.82 | P54: =SUMIFS(G:G,C:C,C54,D:D,D54)/COUNTIFS(C:C,C54,D:D,D54) -> 1 | Q54: =+F54+P54 -> 2 | R54: =IF(H54=0,0,Q54*0.1025) -> 0.205 | S54: =+Q54+R54 -> 2.205 | T54: =IFERROR(_xlfn.XLOOKUP(J54,Collection!A:A,Collection!D:D,0)/100/_xlfn.XLOOKUP(J54,Collection!A:A,Collection!J:J,0),_xlfn.XLOOKUP(J54,Sold!A:A,Sold!D:D,0)/100/_xlfn.XLOOKUP(J54,Sold!A:A,Sold!J:J,0)) -> #DIV/0! | U54: =IFERROR(T54-S54,0) -> 0 | V54: =COUNTIF(Collection!A:A,J54)+COUNTIF(Sold!A:A,J54) -> 0 | W54: =IFERROR(_xlfn.TEXTAFTER(_xlfn.XLOOKUP(J54,Collection!A:A,Collection!C:C,),"Cards "),_xlfn.TEXTAFTER(_xlfn.XLOOKUP(J54,Sold!A:A,Sold!C:C,),"Cards ")) -> #N/A | X54: =IFERROR(_xlfn.XLOOKUP(J54,Collection!A:A,Collection!B:B,),_xlfn.XLOOKUP(J54,Sold!A:A,Sold!B:B,)) -> #N/A | Y54: Not listed | AB54: NorCal_Collector | AC54: -28.6975
B55: R | C55: cardboardbeast | D55: 46150 | E55: 9 | F55: 2 | G55: 0.25 | H55: 0.24 | I55: Flagg | J55: 12613839 | K55: 79 | L55: https://www.whatnot.com/order/jUyUBmgt9rDM2xSirWQMVK | M55: whatnot.com/order/jUyUBmgt9rDM2xSirWQMVK $2.00 + $1.00 (Shared Shipping) + $0.31 Tax = Total of $3.31 | N55: =IFERROR(_xlfn.TEXTAFTER(L55,"https://www."),"")&CHAR(10)&_xlfn.CONCAT(TEXT(F55,"$0.00")," + ",TEXT(P55,"$0.00")," (Shared Shipping) + ",TEXT(R55,"$0.00")," Tax = Total of ",TEXT(S55,"$0.00")) -> whatnot.com/order/jUyUBmgt9rDM2xSirWQMVK $2.00 + $1.00 (Shared Shipping) + $0.31 Tax = Total of $3.31 | O55: =SUM(F55:H55) -> 2.49 | P55: =SUMIFS(G:G,C:C,C55,D:D,D55)/COUNTIFS(C:C,C55,D:D,D55) -> 1 | Q55: =+F55+P55 -> 3 | R55: =IF(H55=0,0,Q55*0.1025) -> 0.3075 | S55: =+Q55+R55 -> 3.3075 | T55: =IFERROR(_xlfn.XLOOKUP(J55,Collection!A:A,Collection!D:D,0)/100/_xlfn.XLOOKUP(J55,Collection!A:A,Collection!J:J,0),_xlfn.XLOOKUP(J55,Sold!A:A,Sold!D:D,0)/100/_xlfn.XLOOKUP(J55,Sold!A:A,Sold!J:J,0)) -> 3.71 | U55: =IFERROR(T55-S55,0) -> 0.4025 | V55: =COUNTIF(Collection!A:A,J55)+COUNTIF(Sold!A:A,J55) -> 2 | W55: =IFERROR(_xlfn.TEXTAFTER(_xlfn.XLOOKUP(J55,Collection!A:A,Collection!C:C,),"Cards "),_xlfn.TEXTAFTER(_xlfn.XLOOKUP(J55,Sold!A:A,Sold!C:C,),"Cards ")) -> 2025 Bowman | X55: =IFERROR(_xlfn.XLOOKUP(J55,Collection!A:A,Collection!B:B,),_xlfn.XLOOKUP(J55,Sold!A:A,Sold!B:B,)) -> Cooper Flagg #1 | Y55: . | AB55: Grand Total | AC55: -152.85727
B56: R | C56: cardboardbeast | D56: 46150 | E56: 10 | F56: 1 | G56: 0 | H56: 0.11 | I56: Morant | J56: 156688 | K56: 209 | L56: https://www.whatnot.com/order/o8pD2uRJ2uJBZu72TvBaqn | M56: whatnot.com/order/o8pD2uRJ2uJBZu72TvBaqn $1.00 + $1.00 (Shared Shipping) + $0.21 Tax = Total of $2.21 | N56: =IFERROR(_xlfn.TEXTAFTER(L56,"https://www."),"")&CHAR(10)&_xlfn.CONCAT(TEXT(F56,"$0.00")," + ",TEXT(P56,"$0.00")," (Shared Shipping) + ",TEXT(R56,"$0.00")," Tax = Total of ",TEXT(S56,"$0.00")) -> whatnot.com/order/o8pD2uRJ2uJBZu72TvBaqn $1.00 + $1.00 (Shared Shipping) + $0.21 Tax = Total of $2.21 | O56: =SUM(F56:H56) -> 1.11 | P56: =SUMIFS(G:G,C:C,C56,D:D,D56)/COUNTIFS(C:C,C56,D:D,D56) -> 1 | Q56: =+F56+P56 -> 2 | R56: =IF(H56=0,0,Q56*0.1025) -> 0.205 | S56: =+Q56+R56 -> 2.205 | T56: =IFERROR(_xlfn.XLOOKUP(J56,Collection!A:A,Collection!D:D,0)/100/_xlfn.XLOOKUP(J56,Collection!A:A,Collection!J:J,0),_xlfn.XLOOKUP(J56,Sold!A:A,Sold!D:D,0)/100/_xlfn.XLOOKUP(J56,Sold!A:A,Sold!J:J,0)) -> 2 | U56: =IFERROR(T56-S56,0) -> -0.205 | V56: =COUNTIF(Collection!A:A,J56)+COUNTIF(Sold!A:A,J56) -> 1 | W56: =IFERROR(_xlfn.TEXTAFTER(_xlfn.XLOOKUP(J56,Collection!A:A,Collection!C:C,),"Cards "),_xlfn.TEXTAFTER(_xlfn.XLOOKUP(J56,Sold!A:A,Sold!C:C,),"Cards ")) -> 2019 Panini Chronicles | X56: =IFERROR(_xlfn.XLOOKUP(J56,Collection!A:A,Collection!B:B,),_xlfn.XLOOKUP(J56,Sold!A:A,Sold!B:B,)) -> JA Morant #168 | Y56: .
B57: R | C57: cardboardbeast | D57: 46150 | E57: 24 | F57: 2 | G57: 0 | H57: 0.21 | I57: Cunningham | J57: 11474841 | K57: 235 | L57: https://www.whatnot.com/order/V5Gh7hYUvoJshqsMYA2fjj | M57: whatnot.com/order/V5Gh7hYUvoJshqsMYA2fjj $2.00 + $1.00 (Shared Shipping) + $0.31 Tax = Total of $3.31 | N57: =IFERROR(_xlfn.TEXTAFTER(L57,"https://www."),"")&CHAR(10)&_xlfn.CONCAT(TEXT(F57,"$0.00")," + ",TEXT(P57,"$0.00")," (Shared Shipping) + ",TEXT(R57,"$0.00")," Tax = Total of ",TEXT(S57,"$0.00")) -> whatnot.com/order/V5Gh7hYUvoJshqsMYA2fjj $2.00 + $1.00 (Shared Shipping) + $0.31 Tax = Total of $3.31 | O57: =SUM(F57:H57) -> 2.21 | P57: =SUMIFS(G:G,C:C,C57,D:D,D57)/COUNTIFS(C:C,C57,D:D,D57) -> 1 | Q57: =+F57+P57 -> 3 | R57: =IF(H57=0,0,Q57*0.1025) -> 0.3075 | S57: =+Q57+R57 -> 3.3075 | T57: =IFERROR(_xlfn.XLOOKUP(J57,Collection!A:A,Collection!D:D,0)/100/_xlfn.XLOOKUP(J57,Collection!A:A,Collection!J:J,0),_xlfn.XLOOKUP(J57,Sold!A:A,Sold!D:D,0)/100/_xlfn.XLOOKUP(J57,Sold!A:A,Sold!J:J,0)) -> 2.01 | U57: =IFERROR(T57-S57,0) -> -1.2975 | V57: =COUNTIF(Collection!A:A,J57)+COUNTIF(Sold!A:A,J57) -> 1 | W57: =IFERROR(_xlfn.TEXTAFTER(_xlfn.XLOOKUP(J57,Collection!A:A,Collection!C:C,),"Cards "),_xlfn.TEXTAFTER(_xlfn.XLOOKUP(J57,Sold!A:A,Sold!C:C,),"Cards ")) -> 2025 Topps Chrome | X57: =IFERROR(_xlfn.XLOOKUP(J57,Collection!A:A,Collection!B:B,),_xlfn.XLOOKUP(J57,Sold!A:A,Sold!B:B,)) -> Cade Cunningham [Refractor] #88 | Y57: .
B58: R | C58: plymouthsportscards | D58: 46149 | E58: Givvy 3 | F58: 0 | G58: 0 | H58: 0 | I58: Kobe | J58: 145531 | K58: 66 | L58: https://www.whatnot.com/order/PPztzz2oNPCFrGQKEtGeKP | M58: whatnot.com/order/PPztzz2oNPCFrGQKEtGeKP $0.00 + $0.00 (Shared Shipping) + $0.00 Tax = Total of $0.00 | N58: =IFERROR(_xlfn.TEXTAFTER(L58,"https://www."),"")&CHAR(10)&_xlfn.CONCAT(TEXT(F58,"$0.00")," + ",TEXT(P58,"$0.00")," (Shared Shipping) + ",TEXT(R58,"$0.00")," Tax = Total of ",TEXT(S58,"$0.00")) -> whatnot.com/order/PPztzz2oNPCFrGQKEtGeKP $0.00 + $0.00 (Shared Shipping) + $0.00 Tax = Total of $0.00 | O58: =SUM(F58:H58) -> 0 | P58: =SUMIFS(G:G,C:C,C58,D:D,D58)/COUNTIFS(C:C,C58,D:D,D58) -> 0 | Q58: =+F58+P58 -> 0 | R58: =IF(H58=0,0,Q58*0.1025) -> 0 | S58: =+Q58+R58 -> 0 | T58: =IFERROR(_xlfn.XLOOKUP(J58,Collection!A:A,Collection!D:D,0)/100/_xlfn.XLOOKUP(J58,Collection!A:A,Collection!J:J,0),_xlfn.XLOOKUP(J58,Sold!A:A,Sold!D:D,0)/100/_xlfn.XLOOKUP(J58,Sold!A:A,Sold!J:J,0)) -> 5.2 | U58: =IFERROR(T58-S58,0) -> 5.2 | V58: =COUNTIF(Collection!A:A,J58)+COUNTIF(Sold!A:A,J58) -> 1 | W58: =IFERROR(_xlfn.TEXTAFTER(_xlfn.XLOOKUP(J58,Collection!A:A,Collection!C:C,),"Cards "),_xlfn.TEXTAFTER(_xlfn.XLOOKUP(J58,Sold!A:A,Sold!C:C,),"Cards ")) -> 2003 SP Authentic | X58: =IFERROR(_xlfn.XLOOKUP(J58,Collection!A:A,Collection!B:B,),_xlfn.XLOOKUP(J58,Sold!A:A,Sold!B:B,)) -> Kobe Bryant #35 | Y58: .
B59: R | C59: grizzkid | D59: 46149 | E59: 1 | F59: 1 | G59: 1.39 | H59: 0.25 | I59: Reaves | J59: 8395765 | K59: 420 | L59: https://www.whatnot.com/order/CyF3nZr4GRuqeEQwgYCVcq | M59: whatnot.com/order/CyF3nZr4GRuqeEQwgYCVcq $1.00 + $1.39 (Shared Shipping) + $0.24 Tax = Total of $2.63 | N59: =IFERROR(_xlfn.TEXTAFTER(L59,"https://www."),"")&CHAR(10)&_xlfn.CONCAT(TEXT(F59,"$0.00")," + ",TEXT(P59,"$0.00")," (Shared Shipping) + ",TEXT(R59,"$0.00")," Tax = Total of ",TEXT(S59,"$0.00")) -> whatnot.com/order/CyF3nZr4GRuqeEQwgYCVcq $1.00 + $1.39 (Shared Shipping) + $0.24 Tax = Total of $2.63 | O59: =SUM(F59:H59) -> 2.64 | P59: =SUMIFS(G:G,C:C,C59,D:D,D59)/COUNTIFS(C:C,C59,D:D,D59) -> 1.39 | Q59: =+F59+P59 -> 2.39 | R59: =IF(H59=0,0,Q59*0.1025) -> 0.244975 | S59: =+Q59+R59 -> 2.634975 | T59: =IFERROR(_xlfn.XLOOKUP(J59,Collection!A:A,Collection!D:D,0)/100/_xlfn.XLOOKUP(J59,Collection!A:A,Collection!J:J,0),_xlfn.XLOOKUP(J59,Sold!A:A,Sold!D:D,0)/100/_xlfn.XLOOKUP(J59,Sold!A:A,Sold!J:J,0)) -> 1.5 | U59: =IFERROR(T59-S59,0) -> -1.134975 | V59: =COUNTIF(Collection!A:A,J59)+COUNTIF(Sold!A:A,J59) -> 1 | W59: =IFERROR(_xlfn.TEXTAFTER(_xlfn.XLOOKUP(J59,Collection!A:A,Collection!C:C,),"Cards "),_xlfn.TEXTAFTER(_xlfn.XLOOKUP(J59,Sold!A:A,Sold!C:C,),"Cards ")) -> 2024 Panini NBA Hoops | X59: =IFERROR(_xlfn.XLOOKUP(J59,Collection!A:A,Collection!B:B,),_xlfn.XLOOKUP(J59,Sold!A:A,Sold!B:B,)) -> Austin Reaves [Winter] #138 | Y59: Premium?
B60: R | C60: gogreen_sportscards | D60: 46150 | E60: Givvy 3 | F60: 0 | G60: 0 | H60: 0 | I60: Parrish | J60: 8151713 | K60: 310 | L60: https://www.whatnot.com/order/mjPJ8grwnTa5xjehNNp2Qq | M60: whatnot.com/order/mjPJ8grwnTa5xjehNNp2Qq $0.00 + $1.72 (Shared Shipping) + $0.18 Tax = Total of $1.90 | N60: =IFERROR(_xlfn.TEXTAFTER(L60,"https://www."),"")&CHAR(10)&_xlfn.CONCAT(TEXT(F60,"$0.00")," + ",TEXT(P60,"$0.00")," (Shared Shipping) + ",TEXT(R60,"$0.00")," Tax = Total of ",TEXT(S60,"$0.00")) -> whatnot.com/order/mjPJ8grwnTa5xjehNNp2Qq $0.00 + $1.72 (Shared Shipping) + $0.00 Tax = Total of $1.72 | O60: =SUM(F60:H60) -> 0 | P60: =SUMIFS(G:G,C:C,C60,D:D,D60)/COUNTIFS(C:C,C60,D:D,D60) -> 1.72 | Q60: =+F60+P60 -> 1.72 | R60: =IF(H60=0,0,Q60*0.1025) -> 0 | S60: =+Q60+R60 -> 1.72 | T60: =IFERROR(_xlfn.XLOOKUP(J60,Collection!A:A,Collection!D:D,0)/100/_xlfn.XLOOKUP(J60,Collection!A:A,Collection!J:J,0),_xlfn.XLOOKUP(J60,Sold!A:A,Sold!D:D,0)/100/_xlfn.XLOOKUP(J60,Sold!A:A,Sold!J:J,0)) -> 1.89 | U60: =IFERROR(T60-S60,0) -> 0.17 | V60: =COUNTIF(Collection!A:A,J60)+COUNTIF(Sold!A:A,J60) -> 1 | W60: =IFERROR(_xlfn.TEXTAFTER(_xlfn.XLOOKUP(J60,Collection!A:A,Collection!C:C,),"Cards "),_xlfn.TEXTAFTER(_xlfn.XLOOKUP(J60,Sold!A:A,Sold!C:C,),"Cards ")) -> 2023 Topps Cosmic Chrome | X60: =IFERROR(_xlfn.XLOOKUP(J60,Collection!A:A,Collection!B:B,),_xlfn.XLOOKUP(J60,Sold!A:A,Sold!B:B,)) -> Robert Parish #140 | Y60: .
B61: R | C61: gogreen_sportscards | D61: 46150 | E61: 10 | F61: 3 | G61: 3.77 | H61: 0.71 | I61: Culver | J61: 2102671 | K61: 178 | L61: https://www.whatnot.com/order/76LD29BivfBZrNXYeJq5xV | M61: whatnot.com/order/76LD29BivfBZrNXYeJq5xV $3.00 + $1.72 (Shared Shipping) + $0.48 Tax = Total of $5.20 | N61: =IFERROR(_xlfn.TEXTAFTER(L61,"https://www."),"")&CHAR(10)&_xlfn.CONCAT(TEXT(F61,"$0.00")," + ",TEXT(P61,"$0.00")," (Shared Shipping) + ",TEXT(R61,"$0.00")," Tax = Total of ",TEXT(S61,"$0.00")) -> whatnot.com/order/76LD29BivfBZrNXYeJq5xV $3.00 + $1.72 (Shared Shipping) + $0.48 Tax = Total of $5.20 | O61: =SUM(F61:H61) -> 7.48 | P61: =SUMIFS(G:G,C:C,C61,D:D,D61)/COUNTIFS(C:C,C61,D:D,D61) -> 1.72 | Q61: =+F61+P61 -> 4.72 | R61: =IF(H61=0,0,Q61*0.1025) -> 0.4838 | S61: =+Q61+R61 -> 5.2038 | T61: =IFERROR(_xlfn.XLOOKUP(J61,Collection!A:A,Collection!D:D,0)/100/_xlfn.XLOOKUP(J61,Collection!A:A,Collection!J:J,0),_xlfn.XLOOKUP(J61,Sold!A:A,Sold!D:D,0)/100/_xlfn.XLOOKUP(J61,Sold!A:A,Sold!J:J,0)) -> 2.17 | U61: =IFERROR(T61-S61,0) -> -3.0338 | V61: =COUNTIF(Collection!A:A,J61)+COUNTIF(Sold!A:A,J61) -> 1 | W61: =IFERROR(_xlfn.TEXTAFTER(_xlfn.XLOOKUP(J61,Collection!A:A,Collection!C:C,),"Cards "),_xlfn.TEXTAFTER(_xlfn.XLOOKUP(J61,Sold!A:A,Sold!C:C,),"Cards ")) -> 2019 Panini Revolution Rookie Autographs | X61: =IFERROR(_xlfn.XLOOKUP(J61,Collection!A:A,Collection!B:B,),_xlfn.XLOOKUP(J61,Sold!A:A,Sold!B:B,)) -> Jarrett Culver #JCV | Y61: .
B62: R | C62: gogreen_sportscards | D62: 46150 | E62: 2 | F62: 3 | G62: 1.39 | H62: 0.45 | I62: Irving | J62: 4343792 | K62: 486 | L62: https://www.whatnot.com/order/4QyCs9xsuozDF4z5kAMs7r | M62: whatnot.com/order/4QyCs9xsuozDF4z5kAMs7r $3.00 + $1.72 (Shared Shipping) + $0.48 Tax = Total of $5.20 | N62: =IFERROR(_xlfn.TEXTAFTER(L62,"https://www."),"")&CHAR(10)&_xlfn.CONCAT(TEXT(F62,"$0.00")," + ",TEXT(P62,"$0.00")," (Shared Shipping) + ",TEXT(R62,"$0.00")," Tax = Total of ",TEXT(S62,"$0.00")) -> whatnot.com/order/4QyCs9xsuozDF4z5kAMs7r $3.00 + $1.72 (Shared Shipping) + $0.48 Tax = Total of $5.20 | O62: =SUM(F62:H62) -> 4.84 | P62: =SUMIFS(G:G,C:C,C62,D:D,D62)/COUNTIFS(C:C,C62,D:D,D62) -> 1.72 | Q62: =+F62+P62 -> 4.72 | R62: =IF(H62=0,0,Q62*0.1025) -> 0.4838 | S62: =+Q62+R62 -> 5.2038 | T62: =IFERROR(_xlfn.XLOOKUP(J62,Collection!A:A,Collection!D:D,0)/100/_xlfn.XLOOKUP(J62,Collection!A:A,Collection!J:J,0),_xlfn.XLOOKUP(J62,Sold!A:A,Sold!D:D,0)/100/_xlfn.XLOOKUP(J62,Sold!A:A,Sold!J:J,0)) -> 1.25 | U62: =IFERROR(T62-S62,0) -> -3.9538 | V62: =COUNTIF(Collection!A:A,J62)+COUNTIF(Sold!A:A,J62) -> 1 | W62: =IFERROR(_xlfn.TEXTAFTER(_xlfn.XLOOKUP(J62,Collection!A:A,Collection!C:C,),"Cards "),_xlfn.TEXTAFTER(_xlfn.XLOOKUP(J62,Sold!A:A,Sold!C:C,),"Cards ")) -> 2022 Panini Chronicles Draft Picks Revolution | X62: =IFERROR(_xlfn.XLOOKUP(J62,Collection!A:A,Collection!B:B,),_xlfn.XLOOKUP(J62,Sold!A:A,Sold!B:B,)) -> Kyrie Irving #63 | Y62: .
B63: R | C63: jaytheselller | D63: 46150 | E63: 1 | F63: 1.6666667 | G63: =9.21/9 -> 1.0233333 | H63: =2.48/9 -> 0.27555556 | I63: Wembanyama | J63: 12615262 | K63: 414 | L63: https://www.whatnot.com/order/7eozouSEnosHtokHHfAAYH | M63: whatnot.com/order/7eozouSEnosHtokHHfAAYH $1.67 + $1.02 (Shared Shipping) + $0.28 Tax = Total of $2.97 | N63: =IFERROR(_xlfn.TEXTAFTER(L63,"https://www."),"")&CHAR(10)&_xlfn.CONCAT(TEXT(F63,"$0.00")," + ",TEXT(P63,"$0.00")," (Shared Shipping) + ",TEXT(R63,"$0.00")," Tax = Total of ",TEXT(S63,"$0.00")) -> whatnot.com/order/7eozouSEnosHtokHHfAAYH $1.67 + $1.02 (Shared Shipping) + $0.28 Tax = Total of $2.97 | O63: =SUM(F63:H63) -> 2.9655556 | P63: =SUMIFS(G:G,C:C,C63,D:D,D63)/COUNTIFS(C:C,C63,D:D,D63) -> 1.0233333 | Q63: =+F63+P63 -> 2.69 | R63: =IF(H63=0,0,Q63*0.1025) -> 0.275725 | S63: =+Q63+R63 -> 2.965725 | T63: =IFERROR(_xlfn.XLOOKUP(J63,Collection!A:A,Collection!D:D,0)/100/_xlfn.XLOOKUP(J63,Collection!A:A,Collection!J:J,0),_xlfn.XLOOKUP(J63,Sold!A:A,Sold!D:D,0)/100/_xlfn.XLOOKUP(J63,Sold!A:A,Sold!J:J,0)) -> 1.35 | U63: =IFERROR(T63-S63,0) -> -1.615725 | V63: =COUNTIF(Collection!A:A,J63)+COUNTIF(Sold!A:A,J63) -> 2 | W63: =IFERROR(_xlfn.TEXTAFTER(_xlfn.XLOOKUP(J63,Collection!A:A,Collection!C:C,),"Cards "),_xlfn.TEXTAFTER(_xlfn.XLOOKUP(J63,Sold!A:A,Sold!C:C,),"Cards ")) -> 2025 Bowman | X63: =IFERROR(_xlfn.XLOOKUP(J63,Collection!A:A,Collection!B:B,),_xlfn.XLOOKUP(J63,Sold!A:A,Sold!B:B,)) -> Victor Wembanyama #143 | Y63: .
B64: R | C64: jaytheselller | D64: 46150 | E64: 1 | F64: 1.6666667 | G64: =9.21/9 -> 1.0233333 | H64: =2.48/9 -> 0.27555556 | I64: Jokic | J64: 12643617 | K64: 455 | L64: https://www.whatnot.com/order/7eozouSEnosHtokHHfAAYH | M64: whatnot.com/order/7eozouSEnosHtokHHfAAYH $1.67 + $1.02 (Shared Shipping) + $0.28 Tax = Total of $2.97 | N64: =IFERROR(_xlfn.TEXTAFTER(L64,"https://www."),"")&CHAR(10)&_xlfn.CONCAT(TEXT(F64,"$0.00")," + ",TEXT(P64,"$0.00")," (Shared Shipping) + ",TEXT(R64,"$0.00")," Tax = Total of ",TEXT(S64,"$0.00")) -> whatnot.com/order/7eozouSEnosHtokHHfAAYH $1.67 + $1.02 (Shared Shipping) + $0.28 Tax = Total of $2.97 | O64: =SUM(F64:H64) -> 2.9655556 | P64: =SUMIFS(G:G,C:C,C64,D:D,D64)/COUNTIFS(C:C,C64,D:D,D64) -> 1.0233333 | Q64: =+F64+P64 -> 2.69 | R64: =IF(H64=0,0,Q64*0.1025) -> 0.275725 | S64: =+Q64+R64 -> 2.965725 | T64: =IFERROR(_xlfn.XLOOKUP(J64,Collection!A:A,Collection!D:D,0)/100/_xlfn.XLOOKUP(J64,Collection!A:A,Collection!J:J,0),_xlfn.XLOOKUP(J64,Sold!A:A,Sold!D:D,0)/100/_xlfn.XLOOKUP(J64,Sold!A:A,Sold!J:J,0)) -> 1.25 | U64: =IFERROR(T64-S64,0) -> -1.715725 | V64: =COUNTIF(Collection!A:A,J64)+COUNTIF(Sold!A:A,J64) -> 1 | W64: =IFERROR(_xlfn.TEXTAFTER(_xlfn.XLOOKUP(J64,Collection!A:A,Collection!C:C,),"Cards "),_xlfn.TEXTAFTER(_xlfn.XLOOKUP(J64,Sold!A:A,Sold!C:C,),"Cards ")) -> 2025 Bowman Young Kings | X64: =IFERROR(_xlfn.XLOOKUP(J64,Collection!A:A,Collection!B:B,),_xlfn.XLOOKUP(J64,Sold!A:A,Sold!B:B,)) -> Nikola Jokic #YK-6 | Y64: .
B65: R | C65: jaytheselller | D65: 46150 | E65: 1 | F65: 1.6666667 | G65: =9.21/9 -> 1.0233333 | H65: =2.48/9 -> 0.27555556 | I65: Jokic | J65: 2892569 | K65: 177 | L65: https://www.whatnot.com/order/7eozouSEnosHtokHHfAAYH | M65: whatnot.com/order/7eozouSEnosHtokHHfAAYH $1.67 + $1.02 (Shared Shipping) + $0.28 Tax = Total of $2.97 | N65: =IFERROR(_xlfn.TEXTAFTER(L65,"https://www."),"")&CHAR(10)&_xlfn.CONCAT(TEXT(F65,"$0.00")," + ",TEXT(P65,"$0.00")," (Shared Shipping) + ",TEXT(R65,"$0.00")," Tax = Total of ",TEXT(S65,"$0.00")) -> whatnot.com/order/7eozouSEnosHtokHHfAAYH $1.67 + $1.02 (Shared Shipping) + $0.28 Tax = Total of $2.97 | O65: =SUM(F65:H65) -> 2.9655556 | P65: =SUMIFS(G:G,C:C,C65,D:D,D65)/COUNTIFS(C:C,C65,D:D,D65) -> 1.0233333 | Q65: =+F65+P65 -> 2.69 | R65: =IF(H65=0,0,Q65*0.1025) -> 0.275725 | S65: =+Q65+R65 -> 2.965725 | T65: =IFERROR(_xlfn.XLOOKUP(J65,Collection!A:A,Collection!D:D,0)/100/_xlfn.XLOOKUP(J65,Collection!A:A,Collection!J:J,0),_xlfn.XLOOKUP(J65,Sold!A:A,Sold!D:D,0)/100/_xlfn.XLOOKUP(J65,Sold!A:A,Sold!J:J,0)) -> 3 | U65: =IFERROR(T65-S65,0) -> 0.034275 | V65: =COUNTIF(Collection!A:A,J65)+COUNTIF(Sold!A:A,J65) -> 1 | W65: =IFERROR(_xlfn.TEXTAFTER(_xlfn.XLOOKUP(J65,Collection!A:A,Collection!C:C,),"Cards "),_xlfn.TEXTAFTER(_xlfn.XLOOKUP(J65,Sold!A:A,Sold!C:C,),"Cards ")) -> 2019 Panini Hoops Lights Camera Action | X65: =IFERROR(_xlfn.XLOOKUP(J65,Collection!A:A,Collection!B:B,),_xlfn.XLOOKUP(J65,Sold!A:A,Sold!B:B,)) -> Nikola Jokic [Holo] #28 | Y65: Not sure which parallel it is or if premium or not
B66: R | C66: jaytheselller | D66: 46150 | E66: 1 | F66: 1.6666667 | G66: =9.21/9 -> 1.0233333 | H66: =2.48/9 -> 0.27555556 | I66: Wembanyama | J66: 9778816 | K66: 83 | L66: https://www.whatnot.com/order/7eozouSEnosHtokHHfAAYH | M66: whatnot.com/order/7eozouSEnosHtokHHfAAYH $1.67 + $1.02 (Shared Shipping) + $0.28 Tax = Total of $2.97 | N66: =IFERROR(_xlfn.TEXTAFTER(L66,"https://www."),"")&CHAR(10)&_xlfn.CONCAT(TEXT(F66,"$0.00")," + ",TEXT(P66,"$0.00")," (Shared Shipping) + ",TEXT(R66,"$0.00")," Tax = Total of ",TEXT(S66,"$0.00")) -> whatnot.com/order/7eozouSEnosHtokHHfAAYH $1.67 + $1.02 (Shared Shipping) + $0.28 Tax = Total of $2.97 | O66: =SUM(F66:H66) -> 2.9655556 | P66: =SUMIFS(G:G,C:C,C66,D:D,D66)/COUNTIFS(C:C,C66,D:D,D66) -> 1.0233333 | Q66: =+F66+P66 -> 2.69 | R66: =IF(H66=0,0,Q66*0.1025) -> 0.275725 | S66: =+Q66+R66 -> 2.965725 | T66: =IFERROR(_xlfn.XLOOKUP(J66,Collection!A:A,Collection!D:D,0)/100/_xlfn.XLOOKUP(J66,Collection!A:A,Collection!J:J,0),_xlfn.XLOOKUP(J66,Sold!A:A,Sold!D:D,0)/100/_xlfn.XLOOKUP(J66,Sold!A:A,Sold!J:J,0)) -> 42.54 | U66: =IFERROR(T66-S66,0) -> 39.574275 | V66: =COUNTIF(Collection!A:A,J66)+COUNTIF(Sold!A:A,J66) -> 1 | W66: =IFERROR(_xlfn.TEXTAFTER(_xlfn.XLOOKUP(J66,Collection!A:A,Collection!C:C,),"Cards "),_xlfn.TEXTAFTER(_xlfn.XLOOKUP(J66,Sold!A:A,Sold!C:C,),"Cards ")) -> 2024 Panini Select | X66: =IFERROR(_xlfn.XLOOKUP(J66,Collection!A:A,Collection!B:B,),_xlfn.XLOOKUP(J66,Sold!A:A,Sold!B:B,)) -> Victor Wembanyama [Orange Cracked Ice Prizm] #9 | Y66: .
B67: R | C67: jaytheselller | D67: 46150 | E67: 1 | F67: 1.6666667 | G67: =9.21/9 -> 1.0233333 | H67: =2.48/9 -> 0.27555556 | I67: Shai | J67: 2963876 | K67: 381 | L67: https://www.whatnot.com/order/7eozouSEnosHtokHHfAAYH | M67: whatnot.com/order/7eozouSEnosHtokHHfAAYH $1.67 + $1.02 (Shared Shipping) + $0.28 Tax = Total of $2.97 | N67: =IFERROR(_xlfn.TEXTAFTER(L67,"https://www."),"")&CHAR(10)&_xlfn.CONCAT(TEXT(F67,"$0.00")," + ",TEXT(P67,"$0.00")," (Shared Shipping) + ",TEXT(R67,"$0.00")," Tax = Total of ",TEXT(S67,"$0.00")) -> whatnot.com/order/7eozouSEnosHtokHHfAAYH $1.67 + $1.02 (Shared Shipping) + $0.28 Tax = Total of $2.97 | O67: =SUM(F67:H67) -> 2.9655556 | P67: =SUMIFS(G:G,C:C,C67,D:D,D67)/COUNTIFS(C:C,C67,D:D,D67) -> 1.0233333 | Q67: =+F67+P67 -> 2.69 | R67: =IF(H67=0,0,Q67*0.1025) -> 0.275725 | S67: =+Q67+R67 -> 2.965725 | T67: =IFERROR(_xlfn.XLOOKUP(J67,Collection!A:A,Collection!D:D,0)/100/_xlfn.XLOOKUP(J67,Collection!A:A,Collection!J:J,0),_xlfn.XLOOKUP(J67,Sold!A:A,Sold!D:D,0)/100/_xlfn.XLOOKUP(J67,Sold!A:A,Sold!J:J,0)) -> 1.79 | U67: =IFERROR(T67-S67,0) -> -1.175725 | V67: =COUNTIF(Collection!A:A,J67)+COUNTIF(Sold!A:A,J67) -> 1 | W67: =IFERROR(_xlfn.TEXTAFTER(_xlfn.XLOOKUP(J67,Collection!A:A,Collection!C:C,),"Cards "),_xlfn.TEXTAFTER(_xlfn.XLOOKUP(J67,Sold!A:A,Sold!C:C,),"Cards ")) -> 2020 Panini Illusions | X67: =IFERROR(_xlfn.XLOOKUP(J67,Collection!A:A,Collection!B:B,),_xlfn.XLOOKUP(J67,Sold!A:A,Sold!B:B,)) -> Shai Gilgeous-Alexander #35 | Y67: .
B68: R | C68: jaytheselller | D68: 46150 | E68: 1 | F68: 1.6666667 | G68: =9.21/9 -> 1.0233333 | H68: =2.48/9 -> 0.27555556 | I68: Shai | J68: 3727518 | K68: 363 | L68: https://www.whatnot.com/order/7eozouSEnosHtokHHfAAYH | M68: whatnot.com/order/7eozouSEnosHtokHHfAAYH $1.67 + $1.02 (Shared Shipping) + $0.28 Tax = Total of $2.97 | N68: =IFERROR(_xlfn.TEXTAFTER(L68,"https://www."),"")&CHAR(10)&_xlfn.CONCAT(TEXT(F68,"$0.00")," + ",TEXT(P68,"$0.00")," (Shared Shipping) + ",TEXT(R68,"$0.00")," Tax = Total of ",TEXT(S68,"$0.00")) -> whatnot.com/order/7eozouSEnosHtokHHfAAYH $1.67 + $1.02 (Shared Shipping) + $0.28 Tax = Total of $2.97 | O68: =SUM(F68:H68) -> 2.9655556 | P68: =SUMIFS(G:G,C:C,C68,D:D,D68)/COUNTIFS(C:C,C68,D:D,D68) -> 1.0233333 | Q68: =+F68+P68 -> 2.69 | R68: =IF(H68=0,0,Q68*0.1025) -> 0.275725 | S68: =+Q68+R68 -> 2.965725 | T68: =IFERROR(_xlfn.XLOOKUP(J68,Collection!A:A,Collection!D:D,0)/100/_xlfn.XLOOKUP(J68,Collection!A:A,Collection!J:J,0),_xlfn.XLOOKUP(J68,Sold!A:A,Sold!D:D,0)/100/_xlfn.XLOOKUP(J68,Sold!A:A,Sold!J:J,0)) -> 1.47 | U68: =IFERROR(T68-S68,0) -> -1.495725 | V68: =COUNTIF(Collection!A:A,J68)+COUNTIF(Sold!A:A,J68) -> 1 | W68: =IFERROR(_xlfn.TEXTAFTER(_xlfn.XLOOKUP(J68,Collection!A:A,Collection!C:C,),"Cards "),_xlfn.TEXTAFTER(_xlfn.XLOOKUP(J68,Sold!A:A,Sold!C:C,),"Cards ")) -> 2021 Panini Prizm | X68: =IFERROR(_xlfn.XLOOKUP(J68,Collection!A:A,Collection!B:B,),_xlfn.XLOOKUP(J68,Sold!A:A,Sold!B:B,)) -> Shai Gilgeous Alexander #238 | Y68: .
B69: R | C69: jaytheselller | D69: 46150 | E69: 1 | F69: 1.6666667 | G69: =9.21/9 -> 1.0233333 | H69: =2.48/9 -> 0.27555556 | I69: Luka | J69: 9960699 | K69: 156 | L69: https://www.whatnot.com/order/7eozouSEnosHtokHHfAAYH | M69: whatnot.com/order/7eozouSEnosHtokHHfAAYH $1.67 + $1.02 (Shared Shipping) + $0.28 Tax = Total of $2.97 | N69: =IFERROR(_xlfn.TEXTAFTER(L69,"https://www."),"")&CHAR(10)&_xlfn.CONCAT(TEXT(F69,"$0.00")," + ",TEXT(P69,"$0.00")," (Shared Shipping) + ",TEXT(R69,"$0.00")," Tax = Total of ",TEXT(S69,"$0.00")) -> whatnot.com/order/7eozouSEnosHtokHHfAAYH $1.67 + $1.02 (Shared Shipping) + $0.28 Tax = Total of $2.97 | O69: =SUM(F69:H69) -> 2.9655556 | P69: =SUMIFS(G:G,C:C,C69,D:D,D69)/COUNTIFS(C:C,C69,D:D,D69) -> 1.0233333 | Q69: =+F69+P69 -> 2.69 | R69: =IF(H69=0,0,Q69*0.1025) -> 0.275725 | S69: =+Q69+R69 -> 2.965725 | T69: =IFERROR(_xlfn.XLOOKUP(J69,Collection!A:A,Collection!D:D,0)/100/_xlfn.XLOOKUP(J69,Collection!A:A,Collection!J:J,0),_xlfn.XLOOKUP(J69,Sold!A:A,Sold!D:D,0)/100/_xlfn.XLOOKUP(J69,Sold!A:A,Sold!J:J,0)) -> 3.11 | U69: =IFERROR(T69-S69,0) -> 0.144275 | V69: =COUNTIF(Collection!A:A,J69)+COUNTIF(Sold!A:A,J69) -> 2 | W69: =IFERROR(_xlfn.TEXTAFTER(_xlfn.XLOOKUP(J69,Collection!A:A,Collection!C:C,),"Cards "),_xlfn.TEXTAFTER(_xlfn.XLOOKUP(J69,Sold!A:A,Sold!C:C,),"Cards ")) -> 2024 Panini Mosaic Epic Performers | X69: =IFERROR(_xlfn.XLOOKUP(J69,Collection!A:A,Collection!B:B,),_xlfn.XLOOKUP(J69,Sold!A:A,Sold!B:B,)) -> Luka Doncic [Green] #10 | Y69: .
B70: R | C70: jaytheselller | D70: 46150 | E70: 1 | F70: 1.6666667 | G70: =9.21/9 -> 1.0233333 | H70: =2.48/9 -> 0.27555556 | I70: James | J70: 2945720 | K70: 467 | L70: https://www.whatnot.com/order/7eozouSEnosHtokHHfAAYH | M70: whatnot.com/order/7eozouSEnosHtokHHfAAYH $1.67 + $1.02 (Shared Shipping) + $0.28 Tax = Total of $2.97 | N70: =IFERROR(_xlfn.TEXTAFTER(L70,"https://www."),"")&CHAR(10)&_xlfn.CONCAT(TEXT(F70,"$0.00")," + ",TEXT(P70,"$0.00")," (Shared Shipping) + ",TEXT(R70,"$0.00")," Tax = Total of ",TEXT(S70,"$0.00")) -> whatnot.com/order/7eozouSEnosHtokHHfAAYH $1.67 + $1.02 (Shared Shipping) + $0.28 Tax = Total of $2.97 | O70: =SUM(F70:H70) -> 2.9655556 | P70: =SUMIFS(G:G,C:C,C70,D:D,D70)/COUNTIFS(C:C,C70,D:D,D70) -> 1.0233333 | Q70: =+F70+P70 -> 2.69 | R70: =IF(H70=0,0,Q70*0.1025) -> 0.275725 | S70: =+Q70+R70 -> 2.965725 | T70: =IFERROR(_xlfn.XLOOKUP(J70,Collection!A:A,Collection!D:D,0)/100/_xlfn.XLOOKUP(J70,Collection!A:A,Collection!J:J,0),_xlfn.XLOOKUP(J70,Sold!A:A,Sold!D:D,0)/100/_xlfn.XLOOKUP(J70,Sold!A:A,Sold!J:J,0)) -> 1.06 | U70: =IFERROR(T70-S70,0) -> -1.905725 | V70: =COUNTIF(Collection!A:A,J70)+COUNTIF(Sold!A:A,J70) -> 1 | W70: =IFERROR(_xlfn.TEXTAFTER(_xlfn.XLOOKUP(J70,Collection!A:A,Collection!C:C,),"Cards "),_xlfn.TEXTAFTER(_xlfn.XLOOKUP(J70,Sold!A:A,Sold!C:C,),"Cards ")) -> 2020 Panini Chronicles | X70: =IFERROR(_xlfn.XLOOKUP(J70,Collection!A:A,Collection!B:B,),_xlfn.XLOOKUP(J70,Sold!A:A,Sold!B:B,)) -> LeBron James #118 | Y70: .
B71: R | C71: jaytheselller | D71: 46150 | E71: 1 | F71: 1.6666667 | G71: =9.21/9 -> 1.0233333 | H71: =2.48/9 -> 0.27555556 | I71: Curry | J71: 9943175 | K71: 322 | L71: https://www.whatnot.com/order/7eozouSEnosHtokHHfAAYH | M71: whatnot.com/order/7eozouSEnosHtokHHfAAYH $1.67 + $1.02 (Shared Shipping) + $0.28 Tax = Total of $2.97 | N71: =IFERROR(_xlfn.TEXTAFTER(L71,"https://www."),"")&CHAR(10)&_xlfn.CONCAT(TEXT(F71,"$0.00")," + ",TEXT(P71,"$0.00")," (Shared Shipping) + ",TEXT(R71,"$0.00")," Tax = Total of ",TEXT(S71,"$0.00")) -> whatnot.com/order/7eozouSEnosHtokHHfAAYH $1.67 + $1.02 (Shared Shipping) + $0.28 Tax = Total of $2.97 | O71: =SUM(F71:H71) -> 2.9655556 | P71: =SUMIFS(G:G,C:C,C71,D:D,D71)/COUNTIFS(C:C,C71,D:D,D71) -> 1.0233333 | Q71: =+F71+P71 -> 2.69 | R71: =IF(H71=0,0,Q71*0.1025) -> 0.275725 | S71: =+Q71+R71 -> 2.965725 | T71: =IFERROR(_xlfn.XLOOKUP(J71,Collection!A:A,Collection!D:D,0)/100/_xlfn.XLOOKUP(J71,Collection!A:A,Collection!J:J,0),_xlfn.XLOOKUP(J71,Sold!A:A,Sold!D:D,0)/100/_xlfn.XLOOKUP(J71,Sold!A:A,Sold!J:J,0)) -> 1.64 | U71: =IFERROR(T71-S71,0) -> -1.325725 | V71: =COUNTIF(Collection!A:A,J71)+COUNTIF(Sold!A:A,J71) -> 1 | W71: =IFERROR(_xlfn.TEXTAFTER(_xlfn.XLOOKUP(J71,Collection!A:A,Collection!C:C,),"Cards "),_xlfn.TEXTAFTER(_xlfn.XLOOKUP(J71,Sold!A:A,Sold!C:C,),"Cards ")) -> 2024 Panini Mosaic | X71: =IFERROR(_xlfn.XLOOKUP(J71,Collection!A:A,Collection!B:B,),_xlfn.XLOOKUP(J71,Sold!A:A,Sold!B:B,)) -> Stephen Curry #163 | Y71: .
B72: R | C72: hotmamajamacards | D72: 46150 | E72: Givvy 25 | F72: 0 | G72: 0 | H72: 0 | I72: Fox | J72: 7094582 | K72: 105 | L72: https://www.whatnot.com/order/m4fEeiDTAEFP5LnXvHdGVx | M72: whatnot.com/order/m4fEeiDTAEFP5LnXvHdGVx $0.00 + $0.00 (Shared Shipping) + $0.00 Tax = Total of $0.00 | N72: =IFERROR(_xlfn.TEXTAFTER(L72,"https://www."),"")&CHAR(10)&_xlfn.CONCAT(TEXT(F72,"$0.00")," + ",TEXT(P72,"$0.00")," (Shared Shipping) + ",TEXT(R72,"$0.00")," Tax = Total of ",TEXT(S72,"$0.00")) -> whatnot.com/order/m4fEeiDTAEFP5LnXvHdGVx $0.00 + $0.00 (Shared Shipping) + $0.00 Tax = Total of $0.00 | O72: =SUM(F72:H72) -> 0 | P72: =SUMIFS(G:G,C:C,C72,D:D,D72)/COUNTIFS(C:C,C72,D:D,D72) -> 0 | Q72: =+F72+P72 -> 0 | R72: =IF(H72=0,0,Q72*0.1025) -> 0 | S72: =+Q72+R72 -> 0 | T72: =IFERROR(_xlfn.XLOOKUP(J72,Collection!A:A,Collection!D:D,0)/100/_xlfn.XLOOKUP(J72,Collection!A:A,Collection!J:J,0),_xlfn.XLOOKUP(J72,Sold!A:A,Sold!D:D,0)/100/_xlfn.XLOOKUP(J72,Sold!A:A,Sold!J:J,0)) -> 1.88 | U72: =IFERROR(T72-S72,0) -> 1.88 | V72: =COUNTIF(Collection!A:A,J72)+COUNTIF(Sold!A:A,J72) -> 1 | W72: =IFERROR(_xlfn.TEXTAFTER(_xlfn.XLOOKUP(J72,Collection!A:A,Collection!C:C,),"Cards "),_xlfn.TEXTAFTER(_xlfn.XLOOKUP(J72,Sold!A:A,Sold!C:C,),"Cards ")) -> 2019 Panini Hoops Premium Stock Lights Camera Action | X72: =IFERROR(_xlfn.XLOOKUP(J72,Collection!A:A,Collection!B:B,),_xlfn.XLOOKUP(J72,Sold!A:A,Sold!B:B,)) -> De'Aaron Fox #3 | Y72: .
B73: R | C73: swansonscards | D73: 46152 | E73: 2 | F73: 4 | G73: 0.78 | H73: 0.49 | I73: Flagg | J73: 10819468 | K73: 129 | L73: https://www.whatnot.com/order/WKa7ntNswTBEf2VahSBtgB | M73: whatnot.com/order/WKa7ntNswTBEf2VahSBtgB $4.00 + $0.55 (Shared Shipping) + $0.47 Tax = Total of $5.01 | N73: =IFERROR(_xlfn.TEXTAFTER(L73,"https://www."),"")&CHAR(10)&_xlfn.CONCAT(TEXT(F73,"$0.00")," + ",TEXT(P73,"$0.00")," (Shared Shipping) + ",TEXT(R73,"$0.00")," Tax = Total of ",TEXT(S73,"$0.00")) -> whatnot.com/order/WKa7ntNswTBEf2VahSBtgB $4.00 + $0.55 (Shared Shipping) + $0.47 Tax = Total of $5.01 | O73: =SUM(F73:H73) -> 5.27 | P73: =SUMIFS(G:G,C:C,C73,D:D,D73)/COUNTIFS(C:C,C73,D:D,D73) -> 0.545 | Q73: =+F73+P73 -> 4.545 | R73: =IF(H73=0,0,Q73*0.1025) -> 0.4658625 | S73: =+Q73+R73 -> 5.0108625 | T73: =IFERROR(_xlfn.XLOOKUP(J73,Collection!A:A,Collection!D:D,0)/100/_xlfn.XLOOKUP(J73,Collection!A:A,Collection!J:J,0),_xlfn.XLOOKUP(J73,Sold!A:A,Sold!D:D,0)/100/_xlfn.XLOOKUP(J73,Sold!A:A,Sold!J:J,0)) -> 4.88 | U73: =IFERROR(T73-S73,0) -> -0.1308625 | V73: =COUNTIF(Collection!A:A,J73)+COUNTIF(Sold!A:A,J73) -> 1 | W73: =IFERROR(_xlfn.TEXTAFTER(_xlfn.XLOOKUP(J73,Collection!A:A,Collection!C:C,),"Cards "),_xlfn.TEXTAFTER(_xlfn.XLOOKUP(J73,Sold!A:A,Sold!C:C,),"Cards ")) -> 2025 Topps | X73: =IFERROR(_xlfn.XLOOKUP(J73,Collection!A:A,Collection!B:B,),_xlfn.XLOOKUP(J73,Sold!A:A,Sold!B:B,)) -> Cooper Flagg #201 | Y73: .
B74: R | C74: swansonscards | D74: 46152 | E74: 11 | F74: 1 | G74: 0.31 | H74: 0.15 | I74: Luka | J74: 9259985 | K74: 542 | L74: https://www.whatnot.com/order/RBy2pvRpcvEutM74HSJXng | M74: whatnot.com/order/RBy2pvRpcvEutM74HSJXng $1.00 + $0.55 (Shared Shipping) + $0.16 Tax = Total of $1.70 | N74: =IFERROR(_xlfn.TEXTAFTER(L74,"https://www."),"")&CHAR(10)&_xlfn.CONCAT(TEXT(F74,"$0.00")," + ",TEXT(P74,"$0.00")," (Shared Shipping) + ",TEXT(R74,"$0.00")," Tax = Total of ",TEXT(S74,"$0.00")) -> whatnot.com/order/RBy2pvRpcvEutM74HSJXng $1.00 + $0.55 (Shared Shipping) + $0.16 Tax = Total of $1.70 | O74: =SUM(F74:H74) -> 1.46 | P74: =SUMIFS(G:G,C:C,C74,D:D,D74)/COUNTIFS(C:C,C74,D:D,D74) -> 0.545 | Q74: =+F74+P74 -> 1.545 | R74: =IF(H74=0,0,Q74*0.1025) -> 0.1583625 | S74: =+Q74+R74 -> 1.7033625 | T74: =IFERROR(_xlfn.XLOOKUP(J74,Collection!A:A,Collection!D:D,0)/100/_xlfn.XLOOKUP(J74,Collection!A:A,Collection!J:J,0),_xlfn.XLOOKUP(J74,Sold!A:A,Sold!D:D,0)/100/_xlfn.XLOOKUP(J74,Sold!A:A,Sold!J:J,0)) -> 1 | U74: =IFERROR(T74-S74,0) -> -0.7033625 | V74: =COUNTIF(Collection!A:A,J74)+COUNTIF(Sold!A:A,J74) -> 1 | W74: =IFERROR(_xlfn.TEXTAFTER(_xlfn.XLOOKUP(J74,Collection!A:A,Collection!C:C,),"Cards "),_xlfn.TEXTAFTER(_xlfn.XLOOKUP(J74,Sold!A:A,Sold!C:C,),"Cards ")) -> 2024 Panini Revolution | X74: =IFERROR(_xlfn.XLOOKUP(J74,Collection!A:A,Collection!B:B,),_xlfn.XLOOKUP(J74,Sold!A:A,Sold!B:B,)) -> Luka Doncic #13 | Y74: .
B75: R | C75: demarco210 | D75: 46153 | E75: 27 | F75: 1 | G75: 0.78 | H75: 0.19 | I75: Luka | J75: 2884706 | K75: 228 | L75: https://www.whatnot.com/order/BgoaXMcouJPo8C7yxmzWdd | M75: whatnot.com/order/BgoaXMcouJPo8C7yxmzWdd $1.00 + $0.78 (Shared Shipping) + $0.18 Tax = Total of $1.96 | N75: =IFERROR(_xlfn.TEXTAFTER(L75,"https://www."),"")&CHAR(10)&_xlfn.CONCAT(TEXT(F75,"$0.00")," + ",TEXT(P75,"$0.00")," (Shared Shipping) + ",TEXT(R75,"$0.00")," Tax = Total of ",TEXT(S75,"$0.00")) -> whatnot.com/order/BgoaXMcouJPo8C7yxmzWdd $1.00 + $0.78 (Shared Shipping) + $0.18 Tax = Total of $1.96 | O75: =SUM(F75:H75) -> 1.97 | P75: =SUMIFS(G:G,C:C,C75,D:D,D75)/COUNTIFS(C:C,C75,D:D,D75) -> 0.78 | Q75: =+F75+P75 -> 1.78 | R75: =IF(H75=0,0,Q75*0.1025) -> 0.18245 | S75: =+Q75+R75 -> 1.96245 | T75: =IFERROR(_xlfn.XLOOKUP(J75,Collection!A:A,Collection!D:D,0)/100/_xlfn.XLOOKUP(J75,Collection!A:A,Collection!J:J,0),_xlfn.XLOOKUP(J75,Sold!A:A,Sold!D:D,0)/100/_xlfn.XLOOKUP(J75,Sold!A:A,Sold!J:J,0)) -> 2.25 | U75: =IFERROR(T75-S75,0) -> 0.28755 | V75: =COUNTIF(Collection!A:A,J75)+COUNTIF(Sold!A:A,J75) -> 1 | W75: =IFERROR(_xlfn.TEXTAFTER(_xlfn.XLOOKUP(J75,Collection!A:A,Collection!C:C,),"Cards "),_xlfn.TEXTAFTER(_xlfn.XLOOKUP(J75,Sold!A:A,Sold!C:C,),"Cards ")) -> 2019 Panini Donruss Franchise Features | X75: =IFERROR(_xlfn.XLOOKUP(J75,Collection!A:A,Collection!B:B,),_xlfn.XLOOKUP(J75,Sold!A:A,Sold!B:B,)) -> Luka Doncic #29 | Y75: .
B76: R | C76: card_fire | D76: 46153 | E76: Givvy | F76: 0 | G76: 0 | H76: 0 | I76: Raynaud | J76: 11486782 | K76: 532 | L76: https://www.whatnot.com/order/kPmzHw359b76wtiBHv2d7E | M76: whatnot.com/order/kPmzHw359b76wtiBHv2d7E $0.00 + $0.00 (Shared Shipping) + $0.00 Tax = Total of $0.00 | N76: =IFERROR(_xlfn.TEXTAFTER(L76,"https://www."),"")&CHAR(10)&_xlfn.CONCAT(TEXT(F76,"$0.00")," + ",TEXT(P76,"$0.00")," (Shared Shipping) + ",TEXT(R76,"$0.00")," Tax = Total of ",TEXT(S76,"$0.00")) -> whatnot.com/order/kPmzHw359b76wtiBHv2d7E $0.00 + $0.00 (Shared Shipping) + $0.00 Tax = Total of $0.00 | O76: =SUM(F76:H76) -> 0 | P76: =SUMIFS(G:G,C:C,C76,D:D,D76)/COUNTIFS(C:C,C76,D:D,D76) -> 0 | Q76: =+F76+P76 -> 0 | R76: =IF(H76=0,0,Q76*0.1025) -> 0 | S76: =+Q76+R76 -> 0 | T76: =IFERROR(_xlfn.XLOOKUP(J76,Collection!A:A,Collection!D:D,0)/100/_xlfn.XLOOKUP(J76,Collection!A:A,Collection!J:J,0),_xlfn.XLOOKUP(J76,Sold!A:A,Sold!D:D,0)/100/_xlfn.XLOOKUP(J76,Sold!A:A,Sold!J:J,0)) -> 1 | U76: =IFERROR(T76-S76,0) -> 1 | V76: =COUNTIF(Collection!A:A,J76)+COUNTIF(Sold!A:A,J76) -> 1 | W76: =IFERROR(_xlfn.TEXTAFTER(_xlfn.XLOOKUP(J76,Collection!A:A,Collection!C:C,),"Cards "),_xlfn.TEXTAFTER(_xlfn.XLOOKUP(J76,Sold!A:A,Sold!C:C,),"Cards ")) -> 2025 Topps Chrome | X76: =IFERROR(_xlfn.XLOOKUP(J76,Collection!A:A,Collection!B:B,),_xlfn.XLOOKUP(J76,Sold!A:A,Sold!B:B,)) -> Maxime Raynaud #293 | Y76: .
B77: R | C77: millenniumcards | D77: 46153 | E77: 427 | F77: 2 | G77: 4.29 | H77: 0.66 | I77: Williams | J77: 92496 | K77: 152 | L77: https://www.whatnot.com/order/RtJrQKBCiEPUi9krGFqsyU | M77: whatnot.com/order/RtJrQKBCiEPUi9krGFqsyU $2.00 + $4.29 (Shared Shipping) + $0.64 Tax = Total of $6.93 | N77: =IFERROR(_xlfn.TEXTAFTER(L77,"https://www."),"")&CHAR(10)&_xlfn.CONCAT(TEXT(F77,"$0.00")," + ",TEXT(P77,"$0.00")," (Shared Shipping) + ",TEXT(R77,"$0.00")," Tax = Total of ",TEXT(S77,"$0.00")) -> whatnot.com/order/RtJrQKBCiEPUi9krGFqsyU $2.00 + $4.29 (Shared Shipping) + $0.64 Tax = Total of $6.93 | O77: =SUM(F77:H77) -> 6.95 | P77: =SUMIFS(G:G,C:C,C77,D:D,D77)/COUNTIFS(C:C,C77,D:D,D77) -> 4.29 | Q77: =+F77+P77 -> 6.29 | R77: =IF(H77=0,0,Q77*0.1025) -> 0.644725 | S77: =+Q77+R77 -> 6.934725 | T77: =IFERROR(_xlfn.XLOOKUP(J77,Collection!A:A,Collection!D:D,0)/100/_xlfn.XLOOKUP(J77,Collection!A:A,Collection!J:J,0),_xlfn.XLOOKUP(J77,Sold!A:A,Sold!D:D,0)/100/_xlfn.XLOOKUP(J77,Sold!A:A,Sold!J:J,0)) -> 3.28 | U77: =IFERROR(T77-S77,0) -> -3.654725 | V77: =COUNTIF(Collection!A:A,J77)+COUNTIF(Sold!A:A,J77) -> 1 | W77: =IFERROR(_xlfn.TEXTAFTER(_xlfn.XLOOKUP(J77,Collection!A:A,Collection!C:C,),"Cards "),_xlfn.TEXTAFTER(_xlfn.XLOOKUP(J77,Sold!A:A,Sold!C:C,),"Cards ")) -> 1998 Fleer Brilliants | X77: =IFERROR(_xlfn.XLOOKUP(J77,Collection!A:A,Collection!B:B,),_xlfn.XLOOKUP(J77,Sold!A:A,Sold!B:B,)) -> Jason Williams #107 | Y77: .
B78: R | C78: sbgcards | D78: 46154 | E78: 83 | F78: 1 | G78: 0.78 | H78: 0.19 | I78: Luka | J78: 95654 | K78: 320 | L78: https://www.whatnot.com/order/LzxCN3kkWJX8nCqy8qr5nU | M78: whatnot.com/order/LzxCN3kkWJX8nCqy8qr5nU $1.00 + $0.55 (Shared Shipping) + $0.16 Tax = Total of $1.70 | N78: =IFERROR(_xlfn.TEXTAFTER(L78,"https://www."),"")&CHAR(10)&_xlfn.CONCAT(TEXT(F78,"$0.00")," + ",TEXT(P78,"$0.00")," (Shared Shipping) + ",TEXT(R78,"$0.00")," Tax = Total of ",TEXT(S78,"$0.00")) -> whatnot.com/order/LzxCN3kkWJX8nCqy8qr5nU $1.00 + $0.55 (Shared Shipping) + $0.16 Tax = Total of $1.70 | O78: =SUM(F78:H78) -> 1.97 | P78: =SUMIFS(G:G,C:C,C78,D:D,D78)/COUNTIFS(C:C,C78,D:D,D78) -> 0.545 | Q78: =+F78+P78 -> 1.545 | R78: =IF(H78=0,0,Q78*0.1025) -> 0.1583625 | S78: =+Q78+R78 -> 1.7033625 | T78: =IFERROR(_xlfn.XLOOKUP(J78,Collection!A:A,Collection!D:D,0)/100/_xlfn.XLOOKUP(J78,Collection!A:A,Collection!J:J,0),_xlfn.XLOOKUP(J78,Sold!A:A,Sold!D:D,0)/100/_xlfn.XLOOKUP(J78,Sold!A:A,Sold!J:J,0)) -> 1.9 | U78: =IFERROR(T78-S78,0) -> 0.1966375 | V78: =COUNTIF(Collection!A:A,J78)+COUNTIF(Sold!A:A,J78) -> 1 | W78: =IFERROR(_xlfn.TEXTAFTER(_xlfn.XLOOKUP(J78,Collection!A:A,Collection!C:C,),"Cards "),_xlfn.TEXTAFTER(_xlfn.XLOOKUP(J78,Sold!A:A,Sold!C:C,),"Cards ")) -> 2019 Panini Prizm | X78: =IFERROR(_xlfn.XLOOKUP(J78,Collection!A:A,Collection!B:B,),_xlfn.XLOOKUP(J78,Sold!A:A,Sold!B:B,)) -> Luka Doncic #75 | Y78: .
B79: R | C79: sbgcards | D79: 46154 | E79: 84 | F79: 2 | G79: 0.31 | H79: 0.25 | I79: Luka | J79: 8846235 | K79: 215 | L79: https://www.whatnot.com/order/Qz7U5ppnESxTUaQq9NtVok | M79: whatnot.com/order/Qz7U5ppnESxTUaQq9NtVok $2.00 + $0.55 (Shared Shipping) + $0.26 Tax = Total of $2.81 | N79: =IFERROR(_xlfn.TEXTAFTER(L79,"https://www."),"")&CHAR(10)&_xlfn.CONCAT(TEXT(F79,"$0.00")," + ",TEXT(P79,"$0.00")," (Shared Shipping) + ",TEXT(R79,"$0.00")," Tax = Total of ",TEXT(S79,"$0.00")) -> whatnot.com/order/Qz7U5ppnESxTUaQq9NtVok $2.00 + $0.55 (Shared Shipping) + $0.26 Tax = Total of $2.81 | O79: =SUM(F79:H79) -> 2.56 | P79: =SUMIFS(G:G,C:C,C79,D:D,D79)/COUNTIFS(C:C,C79,D:D,D79) -> 0.545 | Q79: =+F79+P79 -> 2.545 | R79: =IF(H79=0,0,Q79*0.1025) -> 0.2608625 | S79: =+Q79+R79 -> 2.8058625 | T79: =IFERROR(_xlfn.XLOOKUP(J79,Collection!A:A,Collection!D:D,0)/100/_xlfn.XLOOKUP(J79,Collection!A:A,Collection!J:J,0),_xlfn.XLOOKUP(J79,Sold!A:A,Sold!D:D,0)/100/_xlfn.XLOOKUP(J79,Sold!A:A,Sold!J:J,0)) -> 3.02 | U79: =IFERROR(T79-S79,0) -> 0.2141375 | V79: =COUNTIF(Collection!A:A,J79)+COUNTIF(Sold!A:A,J79) -> 1 | W79: =IFERROR(_xlfn.TEXTAFTER(_xlfn.XLOOKUP(J79,Collection!A:A,Collection!C:C,),"Cards "),_xlfn.TEXTAFTER(_xlfn.XLOOKUP(J79,Sold!A:A,Sold!C:C,),"Cards ")) -> 2024 Panini Prizm | X79: =IFERROR(_xlfn.XLOOKUP(J79,Collection!A:A,Collection!B:B,),_xlfn.XLOOKUP(J79,Sold!A:A,Sold!B:B,)) -> Luka Doncic [Green] #89 | Y79: .
B80: R | C80: chubbayboy | D80: 46154 | E80: 163 | F80: 2 | G80: 0.78 | H80: 0.29 | I80: Luka | J80: 3114681 | K80: 304 | L80: https://www.whatnot.com/order/AFcBHwTXfggkzDpK3hRwdb | M80: whatnot.com/order/AFcBHwTXfggkzDpK3hRwdb $2.00 + $0.36 (Shared Shipping) + $0.24 Tax = Total of $2.61 | N80: =IFERROR(_xlfn.TEXTAFTER(L80,"https://www."),"")&CHAR(10)&_xlfn.CONCAT(TEXT(F80,"$0.00")," + ",TEXT(P80,"$0.00")," (Shared Shipping) + ",TEXT(R80,"$0.00")," Tax = Total of ",TEXT(S80,"$0.00")) -> whatnot.com/order/AFcBHwTXfggkzDpK3hRwdb $2.00 + $0.36 (Shared Shipping) + $0.24 Tax = Total of $2.61 | O80: =SUM(F80:H80) -> 3.07 | P80: =SUMIFS(G:G,C:C,C80,D:D,D80)/COUNTIFS(C:C,C80,D:D,D80) -> 0.36333333 | Q80: =+F80+P80 -> 2.3633333 | R80: =IF(H80=0,0,Q80*0.1025) -> 0.24224167 | S80: =+Q80+R80 -> 2.605575 | T80: =IFERROR(_xlfn.XLOOKUP(J80,Collection!A:A,Collection!D:D,0)/100/_xlfn.XLOOKUP(J80,Collection!A:A,Collection!J:J,0),_xlfn.XLOOKUP(J80,Sold!A:A,Sold!D:D,0)/100/_xlfn.XLOOKUP(J80,Sold!A:A,Sold!J:J,0)) -> 1.49 | U80: =IFERROR(T80-S80,0) -> -1.115575 | V80: =COUNTIF(Collection!A:A,J80)+COUNTIF(Sold!A:A,J80) -> 1 | W80: =IFERROR(_xlfn.TEXTAFTER(_xlfn.XLOOKUP(J80,Collection!A:A,Collection!C:C,),"Cards "),_xlfn.TEXTAFTER(_xlfn.XLOOKUP(J80,Sold!A:A,Sold!C:C,),"Cards ")) -> 2021 Panini Hoops | X80: =IFERROR(_xlfn.XLOOKUP(J80,Collection!A:A,Collection!B:B,),_xlfn.XLOOKUP(J80,Sold!A:A,Sold!B:B,)) -> Luka Doncic [Purple] #62 | Y80: .
B81: R | C81: chubbayboy | D81: 46154 | E81: 166 | F81: 2 | G81: 0.31 | H81: 0.25 | I81: Luka | J81: 2967050 | K81: 176 | L81: https://www.whatnot.com/order/QTaAU7BuEKWFVBSztLHVZt | M81: whatnot.com/order/QTaAU7BuEKWFVBSztLHVZt $2.00 + $0.36 (Shared Shipping) + $0.24 Tax = Total of $2.61 | N81: =IFERROR(_xlfn.TEXTAFTER(L81,"https://www."),"")&CHAR(10)&_xlfn.CONCAT(TEXT(F81,"$0.00")," + ",TEXT(P81,"$0.00")," (Shared Shipping) + ",TEXT(R81,"$0.00")," Tax = Total of ",TEXT(S81,"$0.00")) -> whatnot.com/order/QTaAU7BuEKWFVBSztLHVZt $2.00 + $0.36 (Shared Shipping) + $0.24 Tax = Total of $2.61 | O81: =SUM(F81:H81) -> 2.56 | P81: =SUMIFS(G:G,C:C,C81,D:D,D81)/COUNTIFS(C:C,C81,D:D,D81) -> 0.36333333 | Q81: =+F81+P81 -> 2.3633333 | R81: =IF(H81=0,0,Q81*0.1025) -> 0.24224167 | S81: =+Q81+R81 -> 2.605575 | T81: =IFERROR(_xlfn.XLOOKUP(J81,Collection!A:A,Collection!D:D,0)/100/_xlfn.XLOOKUP(J81,Collection!A:A,Collection!J:J,0),_xlfn.XLOOKUP(J81,Sold!A:A,Sold!D:D,0)/100/_xlfn.XLOOKUP(J81,Sold!A:A,Sold!J:J,0)) -> 3 | U81: =IFERROR(T81-S81,0) -> 0.394425 | V81: =COUNTIF(Collection!A:A,J81)+COUNTIF(Sold!A:A,J81) -> 1 | W81: =IFERROR(_xlfn.TEXTAFTER(_xlfn.XLOOKUP(J81,Collection!A:A,Collection!C:C,),"Cards "),_xlfn.TEXTAFTER(_xlfn.XLOOKUP(J81,Sold!A:A,Sold!C:C,),"Cards ")) -> 2020 Panini Illusions | X81: =IFERROR(_xlfn.XLOOKUP(J81,Collection!A:A,Collection!B:B,),_xlfn.XLOOKUP(J81,Sold!A:A,Sold!B:B,)) -> Luka Doncic [Sapphire] #43 | Y81: .
B82: R | C82: chubbayboy | D82: 46154 | E82: 167 | F82: 2 | G82: 0 | H82: 0.21 | I82: Morant | J82: 12104444 | K82: 489 | L82: https://www.whatnot.com/order/MwfykcrBkKSMi8nZ7VXmSm | M82: whatnot.com/order/MwfykcrBkKSMi8nZ7VXmSm $2.00 + $0.36 (Shared Shipping) + $0.24 Tax = Total of $2.61 | N82: =IFERROR(_xlfn.TEXTAFTER(L82,"https://www."),"")&CHAR(10)&_xlfn.CONCAT(TEXT(F82,"$0.00")," + ",TEXT(P82,"$0.00")," (Shared Shipping) + ",TEXT(R82,"$0.00")," Tax = Total of ",TEXT(S82,"$0.00")) -> whatnot.com/order/MwfykcrBkKSMi8nZ7VXmSm $2.00 + $0.36 (Shared Shipping) + $0.24 Tax = Total of $2.61 | O82: =SUM(F82:H82) -> 2.21 | P82: =SUMIFS(G:G,C:C,C82,D:D,D82)/COUNTIFS(C:C,C82,D:D,D82) -> 0.36333333 | Q82: =+F82+P82 -> 2.3633333 | R82: =IF(H82=0,0,Q82*0.1025) -> 0.24224167 | S82: =+Q82+R82 -> 2.605575 | T82: =IFERROR(_xlfn.XLOOKUP(J82,Collection!A:A,Collection!D:D,0)/100/_xlfn.XLOOKUP(J82,Collection!A:A,Collection!J:J,0),_xlfn.XLOOKUP(J82,Sold!A:A,Sold!D:D,0)/100/_xlfn.XLOOKUP(J82,Sold!A:A,Sold!J:J,0)) -> 1.53 | U82: =IFERROR(T82-S82,0) -> -1.075575 | V82: =COUNTIF(Collection!A:A,J82)+COUNTIF(Sold!A:A,J82) -> 1 | W82: =IFERROR(_xlfn.TEXTAFTER(_xlfn.XLOOKUP(J82,Collection!A:A,Collection!C:C,),"Cards "),_xlfn.TEXTAFTER(_xlfn.XLOOKUP(J82,Sold!A:A,Sold!C:C,),"Cards ")) -> 2025 Topps Finest | X82: =IFERROR(_xlfn.XLOOKUP(J82,Collection!A:A,Collection!B:B,),_xlfn.XLOOKUP(J82,Sold!A:A,Sold!B:B,)) -> Ja Morant [Oil Spill Refractor] #93 | Y82: Confirm if it is refractor
B83: R | C83: pullwax | D83: 46154 | E83: Givvy | F83: 0 | G83: 0 | H83: 0 | I83: N/A | J83: N/A | K83: N/A-5 | L83: https://www.whatnot.com/order/6ARC4WVoNn7Q6k5D2EzpXQ | M83: whatnot.com/order/6ARC4WVoNn7Q6k5D2EzpXQ $0.00 + $0.00 (Shared Shipping) + $0.00 Tax = Total of $0.00 | N83: =IFERROR(_xlfn.TEXTAFTER(L83,"https://www."),"")&CHAR(10)&_xlfn.CONCAT(TEXT(F83,"$0.00")," + ",TEXT(P83,"$0.00")," (Shared Shipping) + ",TEXT(R83,"$0.00")," Tax = Total of ",TEXT(S83,"$0.00")) -> whatnot.com/order/6ARC4WVoNn7Q6k5D2EzpXQ $0.00 + $0.00 (Shared Shipping) + $0.00 Tax = Total of $0.00 | O83: =SUM(F83:H83) -> 0 | P83: =SUMIFS(G:G,C:C,C83,D:D,D83)/COUNTIFS(C:C,C83,D:D,D83) -> 0 | Q83: =+F83+P83 -> 0 | R83: =IF(H83=0,0,Q83*0.1025) -> 0 | S83: =+Q83+R83 -> 0 | T83: =IFERROR(_xlfn.XLOOKUP(J83,Collection!A:A,Collection!D:D,0)/100/_xlfn.XLOOKUP(J83,Collection!A:A,Collection!J:J,0),_xlfn.XLOOKUP(J83,Sold!A:A,Sold!D:D,0)/100/_xlfn.XLOOKUP(J83,Sold!A:A,Sold!J:J,0)) -> #DIV/0! | U83: =IFERROR(T83-S83,0) -> 0 | V83: =COUNTIF(Collection!A:A,J83)+COUNTIF(Sold!A:A,J83) -> 0 | W83: =IFERROR(_xlfn.TEXTAFTER(_xlfn.XLOOKUP(J83,Collection!A:A,Collection!C:C,),"Cards "),_xlfn.TEXTAFTER(_xlfn.XLOOKUP(J83,Sold!A:A,Sold!C:C,),"Cards ")) -> #N/A | X83: =IFERROR(_xlfn.XLOOKUP(J83,Collection!A:A,Collection!B:B,),_xlfn.XLOOKUP(J83,Sold!A:A,Sold!B:B,)) -> #N/A | Y83: .
B84: R | C84: gerberlifebb | D84: 46154 | E84: 115 | F84: 2 | G84: 1.09 | H84: 0.32 | I84: Jokic | J84: 8388520 | K84: 50 | L84: https://www.whatnot.com/order/RykinryybXh9vCb6txwXKc | M84: whatnot.com/order/RykinryybXh9vCb6txwXKc $2.00 + $0.74 (Shared Shipping) + $0.28 Tax = Total of $3.02 | N84: =IFERROR(_xlfn.TEXTAFTER(L84,"https://www."),"")&CHAR(10)&_xlfn.CONCAT(TEXT(F84,"$0.00")," + ",TEXT(P84,"$0.00")," (Shared Shipping) + ",TEXT(R84,"$0.00")," Tax = Total of ",TEXT(S84,"$0.00")) -> whatnot.com/order/RykinryybXh9vCb6txwXKc $2.00 + $0.74 (Shared Shipping) + $0.28 Tax = Total of $3.02 | O84: =SUM(F84:H84) -> 3.41 | P84: =SUMIFS(G:G,C:C,C84,D:D,D84)/COUNTIFS(C:C,C84,D:D,D84) -> 0.73875 | Q84: =+F84+P84 -> 2.73875 | R84: =IF(H84=0,0,Q84*0.1025) -> 0.28072188 | S84: =+Q84+R84 -> 3.0194719 | T84: =IFERROR(_xlfn.XLOOKUP(J84,Collection!A:A,Collection!D:D,0)/100/_xlfn.XLOOKUP(J84,Collection!A:A,Collection!J:J,0),_xlfn.XLOOKUP(J84,Sold!A:A,Sold!D:D,0)/100/_xlfn.XLOOKUP(J84,Sold!A:A,Sold!J:J,0)) -> 5.8 | U84: =IFERROR(T84-S84,0) -> 2.7805281 | V84: =COUNTIF(Collection!A:A,J84)+COUNTIF(Sold!A:A,J84) -> 1 | W84: =IFERROR(_xlfn.TEXTAFTER(_xlfn.XLOOKUP(J84,Collection!A:A,Collection!C:C,),"Cards "),_xlfn.TEXTAFTER(_xlfn.XLOOKUP(J84,Sold!A:A,Sold!C:C,),"Cards ")) -> 2024 Panini NBA Hoops | X84: =IFERROR(_xlfn.XLOOKUP(J84,Collection!A:A,Collection!B:B,),_xlfn.XLOOKUP(J84,Sold!A:A,Sold!B:B,)) -> Nikola Jokic [Silver] #12 | Y84: Card added was numbered
B85: R | C85: gerberlifebb | D85: 46154 | E85: 121 | F85: 2 | G85: 0.3 | H85: 0.25 | I85: Luka | J85: 9259984 | K85: 241 | L85: https://www.whatnot.com/order/5scJ87fFG7iaQkajYWq4bV | M85: whatnot.com/order/5scJ87fFG7iaQkajYWq4bV $2.00 + $0.74 (Shared Shipping) + $0.28 Tax = Total of $3.02 | N85: =IFERROR(_xlfn.TEXTAFTER(L85,"https://www."),"")&CHAR(10)&_xlfn.CONCAT(TEXT(F85,"$0.00")," + ",TEXT(P85,"$0.00")," (Shared Shipping) + ",TEXT(R85,"$0.00")," Tax = Total of ",TEXT(S85,"$0.00")) -> whatnot.com/order/5scJ87fFG7iaQkajYWq4bV $2.00 + $0.74 (Shared Shipping) + $0.28 Tax = Total of $3.02 | O85: =SUM(F85:H85) -> 2.55 | P85: =SUMIFS(G:G,C:C,C85,D:D,D85)/COUNTIFS(C:C,C85,D:D,D85) -> 0.73875 | Q85: =+F85+P85 -> 2.73875 | R85: =IF(H85=0,0,Q85*0.1025) -> 0.28072188 | S85: =+Q85+R85 -> 3.0194719 | T85: =IFERROR(_xlfn.XLOOKUP(J85,Collection!A:A,Collection!D:D,0)/100/_xlfn.XLOOKUP(J85,Collection!A:A,Collection!J:J,0),_xlfn.XLOOKUP(J85,Sold!A:A,Sold!D:D,0)/100/_xlfn.XLOOKUP(J85,Sold!A:A,Sold!J:J,0)) -> 1.88 | U85: =IFERROR(T85-S85,0) -> -1.1394719 | V85: =COUNTIF(Collection!A:A,J85)+COUNTIF(Sold!A:A,J85) -> 1 | W85: =IFERROR(_xlfn.TEXTAFTER(_xlfn.XLOOKUP(J85,Collection!A:A,Collection!C:C,),"Cards "),_xlfn.TEXTAFTER(_xlfn.XLOOKUP(J85,Sold!A:A,Sold!C:C,),"Cards ")) -> 2024 Panini Revolution | X85: =IFERROR(_xlfn.XLOOKUP(J85,Collection!A:A,Collection!B:B,),_xlfn.XLOOKUP(J85,Sold!A:A,Sold!B:B,)) -> Luka Doncic [Astro] #13 | Y85: .
B86: R | C86: gerberlifebb | D86: 46154 | E86: 127 | F86: 2 | G86: 3.56 | H86: 0.57 | I86: Irving | J86: 6355545 | K86: 348 | L86: https://www.whatnot.com/order/U4wUV4wsrmJG4Ko5kpcCWo | M86: whatnot.com/order/U4wUV4wsrmJG4Ko5kpcCWo $2.00 + $0.74 (Shared Shipping) + $0.28 Tax = Total of $3.02 | N86: =IFERROR(_xlfn.TEXTAFTER(L86,"https://www."),"")&CHAR(10)&_xlfn.CONCAT(TEXT(F86,"$0.00")," + ",TEXT(P86,"$0.00")," (Shared Shipping) + ",TEXT(R86,"$0.00")," Tax = Total of ",TEXT(S86,"$0.00")) -> whatnot.com/order/U4wUV4wsrmJG4Ko5kpcCWo $2.00 + $0.74 (Shared Shipping) + $0.28 Tax = Total of $3.02 | O86: =SUM(F86:H86) -> 6.13 | P86: =SUMIFS(G:G,C:C,C86,D:D,D86)/COUNTIFS(C:C,C86,D:D,D86) -> 0.73875 | Q86: =+F86+P86 -> 2.73875 | R86: =IF(H86=0,0,Q86*0.1025) -> 0.28072188 | S86: =+Q86+R86 -> 3.0194719 | T86: =IFERROR(_xlfn.XLOOKUP(J86,Collection!A:A,Collection!D:D,0)/100/_xlfn.XLOOKUP(J86,Collection!A:A,Collection!J:J,0),_xlfn.XLOOKUP(J86,Sold!A:A,Sold!D:D,0)/100/_xlfn.XLOOKUP(J86,Sold!A:A,Sold!J:J,0)) -> 1.5 | U86: =IFERROR(T86-S86,0) -> -1.5194719 | V86: =COUNTIF(Collection!A:A,J86)+COUNTIF(Sold!A:A,J86) -> 1 | W86: =IFERROR(_xlfn.TEXTAFTER(_xlfn.XLOOKUP(J86,Collection!A:A,Collection!C:C,),"Cards "),_xlfn.TEXTAFTER(_xlfn.XLOOKUP(J86,Sold!A:A,Sold!C:C,),"Cards ")) -> 2023 Panini Prizm | X86: =IFERROR(_xlfn.XLOOKUP(J86,Collection!A:A,Collection!B:B,),_xlfn.XLOOKUP(J86,Sold!A:A,Sold!B:B,)) -> Kyrie Irving [Orange Ice] #22 | Y86: .
B87: R | C87: gerberlifebb | D87: 46154 | E87: 133 | F87: 2 | G87: 0 | H87: 0.21 | I87: Brunson | J87: 2965943 | K87: 382 | L87: https://www.whatnot.com/order/6AEw6dYtHHV2b8pbZH8HLX | M87: whatnot.com/order/6AEw6dYtHHV2b8pbZH8HLX $2.00 + $0.74 (Shared Shipping) + $0.28 Tax = Total of $3.02 | N87: =IFERROR(_xlfn.TEXTAFTER(L87,"https://www."),"")&CHAR(10)&_xlfn.CONCAT(TEXT(F87,"$0.00")," + ",TEXT(P87,"$0.00")," (Shared Shipping) + ",TEXT(R87,"$0.00")," Tax = Total of ",TEXT(S87,"$0.00")) -> whatnot.com/order/6AEw6dYtHHV2b8pbZH8HLX $2.00 + $0.74 (Shared Shipping) + $0.28 Tax = Total of $3.02 | O87: =SUM(F87:H87) -> 2.21 | P87: =SUMIFS(G:G,C:C,C87,D:D,D87)/COUNTIFS(C:C,C87,D:D,D87) -> 0.73875 | Q87: =+F87+P87 -> 2.73875 | R87: =IF(H87=0,0,Q87*0.1025) -> 0.28072188 | S87: =+Q87+R87 -> 3.0194719 | T87: =IFERROR(_xlfn.XLOOKUP(J87,Collection!A:A,Collection!D:D,0)/100/_xlfn.XLOOKUP(J87,Collection!A:A,Collection!J:J,0),_xlfn.XLOOKUP(J87,Sold!A:A,Sold!D:D,0)/100/_xlfn.XLOOKUP(J87,Sold!A:A,Sold!J:J,0)) -> 1.35 | U87: =IFERROR(T87-S87,0) -> -1.6694719 | V87: =COUNTIF(Collection!A:A,J87)+COUNTIF(Sold!A:A,J87) -> 1 | W87: =IFERROR(_xlfn.TEXTAFTER(_xlfn.XLOOKUP(J87,Collection!A:A,Collection!C:C,),"Cards "),_xlfn.TEXTAFTER(_xlfn.XLOOKUP(J87,Sold!A:A,Sold!C:C,),"Cards ")) -> 2020 Panini Illusions | X87: =IFERROR(_xlfn.XLOOKUP(J87,Collection!A:A,Collection!B:B,),_xlfn.XLOOKUP(J87,Sold!A:A,Sold!B:B,)) -> Jalen Brunson [Emerald] #125 | Y87: Streamer said it was Green, which is out of 5, I am guessing it is actually Emerald (Common) or a teal out of 75
B88: R | C88: gerberlifebb | D88: 46154 | E88: 134 | F88: 2 | G88: 0 | H88: 0.21 | I88: Irving | J88: 5468137 | K88: 534 | L88: https://www.whatnot.com/order/6aFhbaxuXeTPJA8aZNx5Bj | M88: whatnot.com/order/6aFhbaxuXeTPJA8aZNx5Bj $2.00 + $0.74 (Shared Shipping) + $0.28 Tax = Total of $3.02 | N88: =IFERROR(_xlfn.TEXTAFTER(L88,"https://www."),"")&CHAR(10)&_xlfn.CONCAT(TEXT(F88,"$0.00")," + ",TEXT(P88,"$0.00")," (Shared Shipping) + ",TEXT(R88,"$0.00")," Tax = Total of ",TEXT(S88,"$0.00")) -> whatnot.com/order/6aFhbaxuXeTPJA8aZNx5Bj $2.00 + $0.74 (Shared Shipping) + $0.28 Tax = Total of $3.02 | O88: =SUM(F88:H88) -> 2.21 | P88: =SUMIFS(G:G,C:C,C88,D:D,D88)/COUNTIFS(C:C,C88,D:D,D88) -> 0.73875 | Q88: =+F88+P88 -> 2.73875 | R88: =IF(H88=0,0,Q88*0.1025) -> 0.28072188 | S88: =+Q88+R88 -> 3.0194719 | T88: =IFERROR(_xlfn.XLOOKUP(J88,Collection!A:A,Collection!D:D,0)/100/_xlfn.XLOOKUP(J88,Collection!A:A,Collection!J:J,0),_xlfn.XLOOKUP(J88,Sold!A:A,Sold!D:D,0)/100/_xlfn.XLOOKUP(J88,Sold!A:A,Sold!J:J,0)) -> 1.04 | U88: =IFERROR(T88-S88,0) -> -1.9794719 | V88: =COUNTIF(Collection!A:A,J88)+COUNTIF(Sold!A:A,J88) -> 1 | W88: =IFERROR(_xlfn.TEXTAFTER(_xlfn.XLOOKUP(J88,Collection!A:A,Collection!C:C,),"Cards "),_xlfn.TEXTAFTER(_xlfn.XLOOKUP(J88,Sold!A:A,Sold!C:C,),"Cards ")) -> 2022 Panini Select | X88: =IFERROR(_xlfn.XLOOKUP(J88,Collection!A:A,Collection!B:B,),_xlfn.XLOOKUP(J88,Sold!A:A,Sold!B:B,)) -> Kyrie Irving [Blue Ice] #130 | Y88: .
B89: R | C89: gerberlifebb | D89: 46154 | E89: 148 | F89: 2 | G89: 0.96 | H89: 0.31 | I89: Maxey | J89: 10192986 | K89: 549 | L89: https://www.whatnot.com/order/apudhfkcpm8mjfcciD2gPJ | M89: whatnot.com/order/apudhfkcpm8mjfcciD2gPJ $2.00 + $0.74 (Shared Shipping) + $0.28 Tax = Total of $3.02 | N89: =IFERROR(_xlfn.TEXTAFTER(L89,"https://www."),"")&CHAR(10)&_xlfn.CONCAT(TEXT(F89,"$0.00")," + ",TEXT(P89,"$0.00")," (Shared Shipping) + ",TEXT(R89,"$0.00")," Tax = Total of ",TEXT(S89,"$0.00")) -> whatnot.com/order/apudhfkcpm8mjfcciD2gPJ $2.00 + $0.74 (Shared Shipping) + $0.28 Tax = Total of $3.02 | O89: =SUM(F89:H89) -> 3.27 | P89: =SUMIFS(G:G,C:C,C89,D:D,D89)/COUNTIFS(C:C,C89,D:D,D89) -> 0.73875 | Q89: =+F89+P89 -> 2.73875 | R89: =IF(H89=0,0,Q89*0.1025) -> 0.28072188 | S89: =+Q89+R89 -> 3.0194719 | T89: =IFERROR(_xlfn.XLOOKUP(J89,Collection!A:A,Collection!D:D,0)/100/_xlfn.XLOOKUP(J89,Collection!A:A,Collection!J:J,0),_xlfn.XLOOKUP(J89,Sold!A:A,Sold!D:D,0)/100/_xlfn.XLOOKUP(J89,Sold!A:A,Sold!J:J,0)) -> 1 | U89: =IFERROR(T89-S89,0) -> -2.0194719 | V89: =COUNTIF(Collection!A:A,J89)+COUNTIF(Sold!A:A,J89) -> 1 | W89: =IFERROR(_xlfn.TEXTAFTER(_xlfn.XLOOKUP(J89,Collection!A:A,Collection!C:C,),"Cards "),_xlfn.TEXTAFTER(_xlfn.XLOOKUP(J89,Sold!A:A,Sold!C:C,),"Cards ")) -> 2024 Panini Donruss Optic | X89: =IFERROR(_xlfn.XLOOKUP(J89,Collection!A:A,Collection!B:B,),_xlfn.XLOOKUP(J89,Sold!A:A,Sold!B:B,)) -> Tyrese Maxey [Holo] #135 | Y89: Silver not listed so I chose Holo
B90: R | C90: gerberlifebb | D90: 46154 | E90: 153 | F90: 2 | G90: 0 | H90: 0.21 | I90: Nowitzki | J90: 11484094 | K90: 479 | L90: https://www.whatnot.com/order/3HUXgbQpXQ3HpVzdfDiwuW | M90: whatnot.com/order/3HUXgbQpXQ3HpVzdfDiwuW $2.00 + $0.74 (Shared Shipping) + $0.28 Tax = Total of $3.02 | N90: =IFERROR(_xlfn.TEXTAFTER(L90,"https://www."),"")&CHAR(10)&_xlfn.CONCAT(TEXT(F90,"$0.00")," + ",TEXT(P90,"$0.00")," (Shared Shipping) + ",TEXT(R90,"$0.00")," Tax = Total of ",TEXT(S90,"$0.00")) -> whatnot.com/order/3HUXgbQpXQ3HpVzdfDiwuW $2.00 + $0.74 (Shared Shipping) + $0.28 Tax = Total of $3.02 | O90: =SUM(F90:H90) -> 2.21 | P90: =SUMIFS(G:G,C:C,C90,D:D,D90)/COUNTIFS(C:C,C90,D:D,D90) -> 0.73875 | Q90: =+F90+P90 -> 2.73875 | R90: =IF(H90=0,0,Q90*0.1025) -> 0.28072188 | S90: =+Q90+R90 -> 3.0194719 | T90: =IFERROR(_xlfn.XLOOKUP(J90,Collection!A:A,Collection!D:D,0)/100/_xlfn.XLOOKUP(J90,Collection!A:A,Collection!J:J,0),_xlfn.XLOOKUP(J90,Sold!A:A,Sold!D:D,0)/100/_xlfn.XLOOKUP(J90,Sold!A:A,Sold!J:J,0)) -> 1.5 | U90: =IFERROR(T90-S90,0) -> -1.5194719 | V90: =COUNTIF(Collection!A:A,J90)+COUNTIF(Sold!A:A,J90) -> 2 | W90: =IFERROR(_xlfn.TEXTAFTER(_xlfn.XLOOKUP(J90,Collection!A:A,Collection!C:C,),"Cards "),_xlfn.TEXTAFTER(_xlfn.XLOOKUP(J90,Sold!A:A,Sold!C:C,),"Cards ")) -> 2025 Topps Chrome | X90: =IFERROR(_xlfn.XLOOKUP(J90,Collection!A:A,Collection!B:B,),_xlfn.XLOOKUP(J90,Sold!A:A,Sold!B:B,)) -> Dirk Nowitzki [Refractor] #246 | Y90: .
B91: R | C91: gerberlifebb | D91: 46154 | E91: 165 | F91: 3 | G91: 0 | H91: 0.31 | I91: Shai | J91: 10193263 | K91: 316 | L91: https://www.whatnot.com/order/YSnqxDb4AmM3M6XH7veFMz | M91: whatnot.com/order/YSnqxDb4AmM3M6XH7veFMz $3.00 + $0.74 (Shared Shipping) + $0.38 Tax = Total of $4.12 | N91: =IFERROR(_xlfn.TEXTAFTER(L91,"https://www."),"")&CHAR(10)&_xlfn.CONCAT(TEXT(F91,"$0.00")," + ",TEXT(P91,"$0.00")," (Shared Shipping) + ",TEXT(R91,"$0.00")," Tax = Total of ",TEXT(S91,"$0.00")) -> whatnot.com/order/YSnqxDb4AmM3M6XH7veFMz $3.00 + $0.74 (Shared Shipping) + $0.38 Tax = Total of $4.12 | O91: =SUM(F91:H91) -> 3.31 | P91: =SUMIFS(G:G,C:C,C91,D:D,D91)/COUNTIFS(C:C,C91,D:D,D91) -> 0.73875 | Q91: =+F91+P91 -> 3.73875 | R91: =IF(H91=0,0,Q91*0.1025) -> 0.38322187 | S91: =+Q91+R91 -> 4.1219719 | T91: =IFERROR(_xlfn.XLOOKUP(J91,Collection!A:A,Collection!D:D,0)/100/_xlfn.XLOOKUP(J91,Collection!A:A,Collection!J:J,0),_xlfn.XLOOKUP(J91,Sold!A:A,Sold!D:D,0)/100/_xlfn.XLOOKUP(J91,Sold!A:A,Sold!J:J,0)) -> 1.97 | U91: =IFERROR(T91-S91,0) -> -2.1519719 | V91: =COUNTIF(Collection!A:A,J91)+COUNTIF(Sold!A:A,J91) -> 1 | W91: =IFERROR(_xlfn.TEXTAFTER(_xlfn.XLOOKUP(J91,Collection!A:A,Collection!C:C,),"Cards "),_xlfn.TEXTAFTER(_xlfn.XLOOKUP(J91,Sold!A:A,Sold!C:C,),"Cards ")) -> 2024 Panini Donruss Optic | X91: =IFERROR(_xlfn.XLOOKUP(J91,Collection!A:A,Collection!B:B,),_xlfn.XLOOKUP(J91,Sold!A:A,Sold!B:B,)) -> Shai Gilgeous-Alexander [Hyper Pink] #127 | Y91: .
B92: R | C92: wesperiod | D92: 46154 | E92: 58 | F92: 2 | G92: 1.09 | H92: 0.32 | I92: McDaniels | J92: 8013967 | K92: 222 | L92: https://www.whatnot.com/order/6GpfoWGnD4i8UVt4E9YZb3 | M92: whatnot.com/order/6GpfoWGnD4i8UVt4E9YZb3 $2.00 + $1.09 (Shared Shipping) + $0.32 Tax = Total of $3.41 | N92: =IFERROR(_xlfn.TEXTAFTER(L92,"https://www."),"")&CHAR(10)&_xlfn.CONCAT(TEXT(F92,"$0.00")," + ",TEXT(P92,"$0.00")," (Shared Shipping) + ",TEXT(R92,"$0.00")," Tax = Total of ",TEXT(S92,"$0.00")) -> whatnot.com/order/6GpfoWGnD4i8UVt4E9YZb3 $2.00 + $1.09 (Shared Shipping) + $0.32 Tax = Total of $3.41 | O92: =SUM(F92:H92) -> 3.41 | P92: =SUMIFS(G:G,C:C,C92,D:D,D92)/COUNTIFS(C:C,C92,D:D,D92) -> 1.09 | Q92: =+F92+P92 -> 3.09 | R92: =IF(H92=0,0,Q92*0.1025) -> 0.316725 | S92: =+Q92+R92 -> 3.406725 | T92: =IFERROR(_xlfn.XLOOKUP(J92,Collection!A:A,Collection!D:D,0)/100/_xlfn.XLOOKUP(J92,Collection!A:A,Collection!J:J,0),_xlfn.XLOOKUP(J92,Sold!A:A,Sold!D:D,0)/100/_xlfn.XLOOKUP(J92,Sold!A:A,Sold!J:J,0)) -> 2.81 | U92: =IFERROR(T92-S92,0) -> -0.596725 | V92: =COUNTIF(Collection!A:A,J92)+COUNTIF(Sold!A:A,J92) -> 1 | W92: =IFERROR(_xlfn.TEXTAFTER(_xlfn.XLOOKUP(J92,Collection!A:A,Collection!C:C,),"Cards "),_xlfn.TEXTAFTER(_xlfn.XLOOKUP(J92,Sold!A:A,Sold!C:C,),"Cards ")) -> 2020 Panini Prizm Emergent | X92: =IFERROR(_xlfn.XLOOKUP(J92,Collection!A:A,Collection!B:B,),_xlfn.XLOOKUP(J92,Sold!A:A,Sold!B:B,)) -> Jaden McDaniels [Silver Prizm] #10 | Y92: .
B93: R | C93: jurcar | D93: 46155 | E93: 44 | F93: 2 | G93: 0.78 | H93: 0.29 | I93: Morant | J93: 156855 | K93: 233 | L93: https://www.whatnot.com/order/dxXz2Jyt4MAZh5PgRPhA2e | M93: whatnot.com/order/dxXz2Jyt4MAZh5PgRPhA2e $2.00 + $0.63 (Shared Shipping) + $0.27 Tax = Total of $2.90 | N93: =IFERROR(_xlfn.TEXTAFTER(L93,"https://www."),"")&CHAR(10)&_xlfn.CONCAT(TEXT(F93,"$0.00")," + ",TEXT(P93,"$0.00")," (Shared Shipping) + ",TEXT(R93,"$0.00")," Tax = Total of ",TEXT(S93,"$0.00")) -> whatnot.com/order/dxXz2Jyt4MAZh5PgRPhA2e $2.00 + $0.63 (Shared Shipping) + $0.27 Tax = Total of $2.90 | O93: =SUM(F93:H93) -> 3.07 | P93: =SUMIFS(G:G,C:C,C93,D:D,D93)/COUNTIFS(C:C,C93,D:D,D93) -> 0.62727273 | Q93: =+F93+P93 -> 2.6272727 | R93: =IF(H93=0,0,Q93*0.1025) -> 0.26929545 | S93: =+Q93+R93 -> 2.8965682 | T93: =IFERROR(_xlfn.XLOOKUP(J93,Collection!A:A,Collection!D:D,0)/100/_xlfn.XLOOKUP(J93,Collection!A:A,Collection!J:J,0),_xlfn.XLOOKUP(J93,Sold!A:A,Sold!D:D,0)/100/_xlfn.XLOOKUP(J93,Sold!A:A,Sold!J:J,0)) -> 2.22 | U93: =IFERROR(T93-S93,0) -> -0.67656818 | V93: =COUNTIF(Collection!A:A,J93)+COUNTIF(Sold!A:A,J93) -> 1 | W93: =IFERROR(_xlfn.TEXTAFTER(_xlfn.XLOOKUP(J93,Collection!A:A,Collection!C:C,),"Cards "),_xlfn.TEXTAFTER(_xlfn.XLOOKUP(J93,Sold!A:A,Sold!C:C,),"Cards ")) -> 2019 Panini Chronicles | X93: =IFERROR(_xlfn.XLOOKUP(J93,Collection!A:A,Collection!B:B,),_xlfn.XLOOKUP(J93,Sold!A:A,Sold!B:B,)) -> JA Morant [Silver] #580 | Y93: .
B94: R | C94: jurcar | D94: 46155 | E94: 46 | F94: 2 | G94: 0.31 | H94: 0.25 | I94: Luka | J94: 9960699 | K94: 155 | L94: https://www.whatnot.com/order/3YdoTRkTxViD7gGBZ6h9iY | M94: whatnot.com/order/3YdoTRkTxViD7gGBZ6h9iY $2.00 + $0.63 (Shared Shipping) + $0.27 Tax = Total of $2.90 | N94: =IFERROR(_xlfn.TEXTAFTER(L94,"https://www."),"")&CHAR(10)&_xlfn.CONCAT(TEXT(F94,"$0.00")," + ",TEXT(P94,"$0.00")," (Shared Shipping) + ",TEXT(R94,"$0.00")," Tax = Total of ",TEXT(S94,"$0.00")) -> whatnot.com/order/3YdoTRkTxViD7gGBZ6h9iY $2.00 + $0.63 (Shared Shipping) + $0.27 Tax = Total of $2.90 | O94: =SUM(F94:H94) -> 2.56 | P94: =SUMIFS(G:G,C:C,C94,D:D,D94)/COUNTIFS(C:C,C94,D:D,D94) -> 0.62727273 | Q94: =+F94+P94 -> 2.6272727 | R94: =IF(H94=0,0,Q94*0.1025) -> 0.26929545 | S94: =+Q94+R94 -> 2.8965682 | T94: =IFERROR(_xlfn.XLOOKUP(J94,Collection!A:A,Collection!D:D,0)/100/_xlfn.XLOOKUP(J94,Collection!A:A,Collection!J:J,0),_xlfn.XLOOKUP(J94,Sold!A:A,Sold!D:D,0)/100/_xlfn.XLOOKUP(J94,Sold!A:A,Sold!J:J,0)) -> 3.11 | U94: =IFERROR(T94-S94,0) -> 0.21343182 | V94: =COUNTIF(Collection!A:A,J94)+COUNTIF(Sold!A:A,J94) -> 2 | W94: =IFERROR(_xlfn.TEXTAFTER(_xlfn.XLOOKUP(J94,Collection!A:A,Collection!C:C,),"Cards "),_xlfn.TEXTAFTER(_xlfn.XLOOKUP(J94,Sold!A:A,Sold!C:C,),"Cards ")) -> 2024 Panini Mosaic Epic Performers | X94: =IFERROR(_xlfn.XLOOKUP(J94,Collection!A:A,Collection!B:B,),_xlfn.XLOOKUP(J94,Sold!A:A,Sold!B:B,)) -> Luka Doncic [Green] #10 | Y94: .
B95: R | C95: jurcar | D95: 46155 | E95: 26 | F95: 5 | G95: 4.39 | H95: 0.98 | I95: Wembanyama | J95: 6059234 | K95: 107 | L95: https://www.whatnot.com/order/5kGXwUf5RaGgQF2EFmu4H9 | M95: whatnot.com/order/5kGXwUf5RaGgQF2EFmu4H9 $5.00 + $0.63 (Shared Shipping) + $0.58 Tax = Total of $6.20 | N95: =IFERROR(_xlfn.TEXTAFTER(L95,"https://www."),"")&CHAR(10)&_xlfn.CONCAT(TEXT(F95,"$0.00")," + ",TEXT(P95,"$0.00")," (Shared Shipping) + ",TEXT(R95,"$0.00")," Tax = Total of ",TEXT(S95,"$0.00")) -> whatnot.com/order/5kGXwUf5RaGgQF2EFmu4H9 $5.00 + $0.63 (Shared Shipping) + $0.58 Tax = Total of $6.20 | O95: =SUM(F95:H95) -> 10.37 | P95: =SUMIFS(G:G,C:C,C95,D:D,D95)/COUNTIFS(C:C,C95,D:D,D95) -> 0.62727273 | Q95: =+F95+P95 -> 5.6272727 | R95: =IF(H95=0,0,Q95*0.1025) -> 0.57679545 | S95: =+Q95+R95 -> 6.2040682 | T95: =IFERROR(_xlfn.XLOOKUP(J95,Collection!A:A,Collection!D:D,0)/100/_xlfn.XLOOKUP(J95,Collection!A:A,Collection!J:J,0),_xlfn.XLOOKUP(J95,Sold!A:A,Sold!D:D,0)/100/_xlfn.XLOOKUP(J95,Sold!A:A,Sold!J:J,0)) -> 6.96 | U95: =IFERROR(T95-S95,0) -> 0.75593182 | V95: =COUNTIF(Collection!A:A,J95)+COUNTIF(Sold!A:A,J95) -> 1 | W95: =IFERROR(_xlfn.TEXTAFTER(_xlfn.XLOOKUP(J95,Collection!A:A,Collection!C:C,),"Cards "),_xlfn.TEXTAFTER(_xlfn.XLOOKUP(J95,Sold!A:A,Sold!C:C,),"Cards ")) -> 2023 Panini Hoops | X95: =IFERROR(_xlfn.XLOOKUP(J95,Collection!A:A,Collection!B:B,),_xlfn.XLOOKUP(J95,Sold!A:A,Sold!B:B,)) -> Victor Wembanyama #277 | Y95: .
... B99: R | C99: jurcar | D99: 46155 | E99: 68 | F99: 2 | G99: 0 | H99: 0.21 | I99: Shai | J99: 6822796 | K99: 370 | L99: https://www.whatnot.com/order/dXNnRDYZ4XQd5syXTuJfHb | M99: whatnot.com/order/dXNnRDYZ4XQd5syXTuJfHb $2.00 + $0.63 (Shared Shipping) + $0.27 Tax = Total of $2.90 | N99: =IFERROR(_xlfn.TEXTAFTER(L99,"https://www."),"")&CHAR(10)&_xlfn.CONCAT(TEXT(F99,"$0.00")," + ",TEXT(P99,"$0.00")," (Shared Shipping) + ",TEXT(R99,"$0.00")," Tax = Total of ",TEXT(S99,"$0.00")) -> whatnot.com/order/dXNnRDYZ4XQd5syXTuJfHb $2.00 + $0.63 (Shared Shipping) + $0.27 Tax = Total of $2.90 | O99: =SUM(F99:H99) -> 2.21 | P99: =SUMIFS(G:G,C:C,C99,D:D,D99)/COUNTIFS(C:C,C99,D:D,D99) -> 0.62727273 | Q99: =+F99+P99 -> 2.6272727 | R99: =IF(H99=0,0,Q99*0.1025) -> 0.26929545 | S99: =+Q99+R99 -> 2.8965682 | T99: =IFERROR(_xlfn.XLOOKUP(J99,Collection!A:A,Collection!D:D,0)/100/_xlfn.XLOOKUP(J99,Collection!A:A,Collection!J:J,0),_xlfn.XLOOKUP(J99,Sold!A:A,Sold!D:D,0)/100/_xlfn.XLOOKUP(J99,Sold!A:A,Sold!J:J,0)) -> 1.54 | U99: =IFERROR(T99-S99,0) -> -1.3565682 | V99: =COUNTIF(Collection!A:A,J99)+COUNTIF(Sold!A:A,J99) -> 1 | W99: =IFERROR(_xlfn.TEXTAFTER(_xlfn.XLOOKUP(J99,Collection!A:A,Collection!C:C,),"Cards "),_xlfn.TEXTAFTER(_xlfn.XLOOKUP(J99,Sold!A:A,Sold!C:C,),"Cards ")) -> 2023 Panini Donruss Optic | X99: =IFERROR(_xlfn.XLOOKUP(J99,Collection!A:A,Collection!B:B,),_xlfn.XLOOKUP(J99,Sold!A:A,Sold!B:B,)) -> Shai Gilgeous-Alexander [Hyper Pink] #104 | Y99: .
B100: R | C100: jurcar | D100: 46155 | E100: Givvy 19 | F100: 0 | G100: 0 | H100: 0 | I100: Lively | J100: 9779919 | K100: 556 | L100: https://www.whatnot.com/order/4LCZQZfaVVhJG2pKsSRhXY | M100: whatnot.com/order/4LCZQZfaVVhJG2pKsSRhXY $0.00 + $0.63 (Shared Shipping) + $0.06 Tax = Total of $0.69 | N100: =IFERROR(_xlfn.TEXTAFTER(L100,"https://www."),"")&CHAR(10)&_xlfn.CONCAT(TEXT(F100,"$0.00")," + ",TEXT(P100,"$0.00")," (Shared Shipping) + ",TEXT(R100,"$0.00")," Tax = Total of ",TEXT(S100,"$0.00")) -> whatnot.com/order/4LCZQZfaVVhJG2pKsSRhXY $0.00 + $0.63 (Shared Shipping) + $0.00 Tax = Total of $0.63 | O100: =SUM(F100:H100) -> 0 | P100: =SUMIFS(G:G,C:C,C100,D:D,D100)/COUNTIFS(C:C,C100,D:D,D100) -> 0.62727273 | Q100: =+F100+P100 -> 0.62727273 | R100: =IF(H100=0,0,Q100*0.1025) -> 0 | S100: =+Q100+R100 -> 0.62727273 | T100: =IFERROR(_xlfn.XLOOKUP(J100,Collection!A:A,Collection!D:D,0)/100/_xlfn.XLOOKUP(J100,Collection!A:A,Collection!J:J,0),_xlfn.XLOOKUP(J100,Sold!A:A,Sold!D:D,0)/100/_xlfn.XLOOKUP(J100,Sold!A:A,Sold!J:J,0)) -> 0.99 | U100: =IFERROR(T100-S100,0) -> 0.36272727 | V100: =COUNTIF(Collection!A:A,J100)+COUNTIF(Sold!A:A,J100) -> 1 | W100: =IFERROR(_xlfn.TEXTAFTER(_xlfn.XLOOKUP(J100,Collection!A:A,Collection!C:C,),"Cards "),_xlfn.TEXTAFTER(_xlfn.XLOOKUP(J100,Sold!A:A,Sold!C:C,),"Cards ")) -> 2024 Panini Select | X100: =IFERROR(_xlfn.XLOOKUP(J100,Collection!A:A,Collection!B:B,),_xlfn.XLOOKUP(J100,Sold!A:A,Sold!B:B,)) -> Dereck Lively II [Green White Purple Prizm] #26 | Y100: .
B101: R | C101: jurcar | D101: 46155 | E101: Givvy 20 | F101: 0 | G101: 0 | H101: 0 | I101: Bridges | J101: 9936923 | K101: 230 | L101: https://www.whatnot.com/order/MyYjybCzWUdYQZ5Nmcqzid | M101: whatnot.com/order/MyYjybCzWUdYQZ5Nmcqzid $0.00 + $0.63 (Shared Shipping) + $0.06 Tax = Total of $0.69 | N101: =IFERROR(_xlfn.TEXTAFTER(L101,"https://www."),"")&CHAR(10)&_xlfn.CONCAT(TEXT(F101,"$0.00")," + ",TEXT(P101,"$0.00")," (Shared Shipping) + ",TEXT(R101,"$0.00")," Tax = Total of ",TEXT(S101,"$0.00")) -> whatnot.com/order/MyYjybCzWUdYQZ5Nmcqzid $0.00 + $0.63 (Shared Shipping) + $0.00 Tax = Total of $0.63 | O101: =SUM(F101:H101) -> 0 | P101: =SUMIFS(G:G,C:C,C101,D:D,D101)/COUNTIFS(C:C,C101,D:D,D101) -> 0.62727273 | Q101: =+F101+P101 -> 0.62727273 | R101: =IF(H101=0,0,Q101*0.1025) -> 0 | S101: =+Q101+R101 -> 0.62727273 | T101: =IFERROR(_xlfn.XLOOKUP(J101,Collection!A:A,Collection!D:D,0)/100/_xlfn.XLOOKUP(J101,Collection!A:A,Collection!J:J,0),_xlfn.XLOOKUP(J101,Sold!A:A,Sold!D:D,0)/100/_xlfn.XLOOKUP(J101,Sold!A:A,Sold!J:J,0)) -> 2.23 | U101: =IFERROR(T101-S101,0) -> 1.6027273 | V101: =COUNTIF(Collection!A:A,J101)+COUNTIF(Sold!A:A,J101) -> 1 | W101: =IFERROR(_xlfn.TEXTAFTER(_xlfn.XLOOKUP(J101,Collection!A:A,Collection!C:C,),"Cards "),_xlfn.TEXTAFTER(_xlfn.XLOOKUP(J101,Sold!A:A,Sold!C:C,),"Cards ")) -> 2024 Panini Mosaic | X101: =IFERROR(_xlfn.XLOOKUP(J101,Collection!A:A,Collection!B:B,),_xlfn.XLOOKUP(J101,Sold!A:A,Sold!B:B,)) -> Miles Bridges [Reactive Blue] #67 | Y101: .
B102: R | C102: jurcar | D102: 46155 | E102: 74 | F102: 2 | G102: 0 | H102: 0.21 | I102: Luka | J102: 10024204 | K102: 240 | L102: https://www.whatnot.com/order/X5K6umEJWi23LicF99oSTD | M102: whatnot.com/order/X5K6umEJWi23LicF99oSTD $2.00 + $0.63 (Shared Shipping) + $0.27 Tax = Total of $2.90 | N102: =IFERROR(_xlfn.TEXTAFTER(L102,"https://www."),"")&CHAR(10)&_xlfn.CONCAT(TEXT(F102,"$0.00")," + ",TEXT(P102,"$0.00")," (Shared Shipping) + ",TEXT(R102,"$0.00")," Tax = Total of ",TEXT(S102,"$0.00")) -> whatnot.com/order/X5K6umEJWi23LicF99oSTD $2.00 + $0.63 (Shared Shipping) + $0.27 Tax = Total of $2.90 | O102: =SUM(F102:H102) -> 2.21 | P102: =SUMIFS(G:G,C:C,C102,D:D,D102)/COUNTIFS(C:C,C102,D:D,D102) -> 0.62727273 | Q102: =+F102+P102 -> 2.6272727 | R102: =IF(H102=0,0,Q102*0.1025) -> 0.26929545 | S102: =+Q102+R102 -> 2.8965682 | T102: =IFERROR(_xlfn.XLOOKUP(J102,Collection!A:A,Collection!D:D,0)/100/_xlfn.XLOOKUP(J102,Collection!A:A,Collection!J:J,0),_xlfn.XLOOKUP(J102,Sold!A:A,Sold!D:D,0)/100/_xlfn.XLOOKUP(J102,Sold!A:A,Sold!J:J,0)) -> 2.08 | U102: =IFERROR(T102-S102,0) -> -0.81656818 | V102: =COUNTIF(Collection!A:A,J102)+COUNTIF(Sold!A:A,J102) -> 1 | W102: =IFERROR(_xlfn.TEXTAFTER(_xlfn.XLOOKUP(J102,Collection!A:A,Collection!C:C,),"Cards "),_xlfn.TEXTAFTER(_xlfn.XLOOKUP(J102,Sold!A:A,Sold!C:C,),"Cards ")) -> 2024 Panini Select | X102: =IFERROR(_xlfn.XLOOKUP(J102,Collection!A:A,Collection!B:B,),_xlfn.XLOOKUP(J102,Sold!A:A,Sold!B:B,)) -> Luka Doncic [Green White Purple Prizm] #141 | Y102: .
B103: R | C103: jurcar | D103: 46155 | E103: 78 | F103: 3 | G103: 1.42 | H103: 0.45 | I103: Mitchell | J103: 120495 | K103: 113 | L103: https://www.whatnot.com/order/iKMuPET2uvNEWaxZSPrWvT | M103: whatnot.com/order/iKMuPET2uvNEWaxZSPrWvT $3.00 + $0.63 (Shared Shipping) + $0.37 Tax = Total of $4.00 | N103: =IFERROR(_xlfn.TEXTAFTER(L103,"https://www."),"")&CHAR(10)&_xlfn.CONCAT(TEXT(F103,"$0.00")," + ",TEXT(P103,"$0.00")," (Shared Shipping) + ",TEXT(R103,"$0.00")," Tax = Total of ",TEXT(S103,"$0.00")) -> whatnot.com/order/iKMuPET2uvNEWaxZSPrWvT $3.00 + $0.63 (Shared Shipping) + $0.37 Tax = Total of $4.00 | O103: =SUM(F103:H103) -> 4.87 | P103: =SUMIFS(G:G,C:C,C103,D:D,D103)/COUNTIFS(C:C,C103,D:D,D103) -> 0.62727273 | Q103: =+F103+P103 -> 3.6272727 | R103: =IF(H103=0,0,Q103*0.1025) -> 0.37179545 | S103: =+Q103+R103 -> 3.9990682 | T103: =IFERROR(_xlfn.XLOOKUP(J103,Collection!A:A,Collection!D:D,0)/100/_xlfn.XLOOKUP(J103,Collection!A:A,Collection!J:J,0),_xlfn.XLOOKUP(J103,Sold!A:A,Sold!D:D,0)/100/_xlfn.XLOOKUP(J103,Sold!A:A,Sold!J:J,0)) -> 4.35 | U103: =IFERROR(T103-S103,0) -> 0.35093182 | V103: =COUNTIF(Collection!A:A,J103)+COUNTIF(Sold!A:A,J103) -> 1 | W103: =IFERROR(_xlfn.TEXTAFTER(_xlfn.XLOOKUP(J103,Collection!A:A,Collection!C:C,),"Cards "),_xlfn.TEXTAFTER(_xlfn.XLOOKUP(J103,Sold!A:A,Sold!C:C,),"Cards ")) -> 2017 Panini Donruss Optic | X103: =IFERROR(_xlfn.XLOOKUP(J103,Collection!A:A,Collection!B:B,),_xlfn.XLOOKUP(J103,Sold!A:A,Sold!B:B,)) -> Donovan Mitchell [Red and Yellow] #188 | Y103: .
B104: R | C104: fzmn77 | D104: 46156 | E104: 79 | F104: 2 | G104: 0.78 | H104: 0.29 | I104: Shai | J104: 10210719 | K104: 332 | L104: https://www.whatnot.com/order/eYoXvD5HkSQiYCAdyKw6ww | M104: whatnot.com/order/eYoXvD5HkSQiYCAdyKw6ww $2.00 + $0.23 (Shared Shipping) + $0.23 Tax = Total of $2.46 | N104: =IFERROR(_xlfn.TEXTAFTER(L104,"https://www."),"")&CHAR(10)&_xlfn.CONCAT(TEXT(F104,"$0.00")," + ",TEXT(P104,"$0.00")," (Shared Shipping) + ",TEXT(R104,"$0.00")," Tax = Total of ",TEXT(S104,"$0.00")) -> whatnot.com/order/eYoXvD5HkSQiYCAdyKw6ww $2.00 + $0.23 (Shared Shipping) + $0.23 Tax = Total of $2.46 | O104: =SUM(F104:H104) -> 3.07 | P104: =SUMIFS(G:G,C:C,C104,D:D,D104)/COUNTIFS(C:C,C104,D:D,D104) -> 0.23166667 | Q104: =+F104+P104 -> 2.2316667 | R104: =IF(H104=0,0,Q104*0.1025) -> 0.22874583 | S104: =+Q104+R104 -> 2.4604125 | T104: =IFERROR(_xlfn.XLOOKUP(J104,Collection!A:A,Collection!D:D,0)/100/_xlfn.XLOOKUP(J104,Collection!A:A,Collection!J:J,0),_xlfn.XLOOKUP(J104,Sold!A:A,Sold!D:D,0)/100/_xlfn.XLOOKUP(J104,Sold!A:A,Sold!J:J,0)) -> 1.63 | U104: =IFERROR(T104-S104,0) -> -0.8304125 | V104: =COUNTIF(Collection!A:A,J104)+COUNTIF(Sold!A:A,J104) -> 1 | W104: =IFERROR(_xlfn.TEXTAFTER(_xlfn.XLOOKUP(J104,Collection!A:A,Collection!C:C,),"Cards "),_xlfn.TEXTAFTER(_xlfn.XLOOKUP(J104,Sold!A:A,Sold!C:C,),"Cards ")) -> 2024 Panini Donruss Optic My House | X104: =IFERROR(_xlfn.XLOOKUP(J104,Collection!A:A,Collection!B:B,),_xlfn.XLOOKUP(J104,Sold!A:A,Sold!B:B,)) -> Shai Gilgeous-Alexander #6 | Y104: .
B105: R | C105: fzmn77 | D105: 46156 | E105: 97 | F105: 2 | G105: 0.31 | H105: 0.25 | I105: Jackson | J105: 11145114 | K105: 609 | L105: https://www.whatnot.com/order/moNYfWFRzgHft49zVDK7Ba | M105: whatnot.com/order/moNYfWFRzgHft49zVDK7Ba $2.00 + $0.23 (Shared Shipping) + $0.23 Tax = Total of $2.46 | N105: =IFERROR(_xlfn.TEXTAFTER(L105,"https://www."),"")&CHAR(10)&_xlfn.CONCAT(TEXT(F105,"$0.00")," + ",TEXT(P105,"$0.00")," (Shared Shipping) + ",TEXT(R105,"$0.00")," Tax = Total of ",TEXT(S105,"$0.00")) -> whatnot.com/order/moNYfWFRzgHft49zVDK7Ba $2.00 + $0.23 (Shared Shipping) + $0.23 Tax = Total of $2.46 | O105: =SUM(F105:H105) -> 2.56 | P105: =SUMIFS(G:G,C:C,C105,D:D,D105)/COUNTIFS(C:C,C105,D:D,D105) -> 0.23166667 | Q105: =+F105+P105 -> 2.2316667 | R105: =IF(H105=0,0,Q105*0.1025) -> 0.22874583 | S105: =+Q105+R105 -> 2.4604125 | T105: =IFERROR(_xlfn.XLOOKUP(J105,Collection!A:A,Collection!D:D,0)/100/_xlfn.XLOOKUP(J105,Collection!A:A,Collection!J:J,0),_xlfn.XLOOKUP(J105,Sold!A:A,Sold!D:D,0)/100/_xlfn.XLOOKUP(J105,Sold!A:A,Sold!J:J,0)) -> 0 | U105: =IFERROR(T105-S105,0) -> -2.4604125 | V105: =COUNTIF(Collection!A:A,J105)+COUNTIF(Sold!A:A,J105) -> 1 | W105: =IFERROR(_xlfn.TEXTAFTER(_xlfn.XLOOKUP(J105,Collection!A:A,Collection!C:C,),"Cards "),_xlfn.TEXTAFTER(_xlfn.XLOOKUP(J105,Sold!A:A,Sold!C:C,),"Cards ")) -> 2025 Panini Phoenix | X105: =IFERROR(_xlfn.XLOOKUP(J105,Collection!A:A,Collection!B:B,),_xlfn.XLOOKUP(J105,Sold!A:A,Sold!B:B,)) -> Lamar Jackson [Green Hyper] #144 | Y105: .
B106: R | C106: fzmn77 | D106: 46156 | E106: 101 | F106: 1 | G106: 0 | H106: 0.11 | I106: Burrow | J106: 12520986 | K106: 205 | L106: https://www.whatnot.com/order/3GyMAAaJhKT35PtSFFmp7M | M106: whatnot.com/order/3GyMAAaJhKT35PtSFFmp7M $1.00 + $0.23 (Shared Shipping) + $0.13 Tax = Total of $1.36 | N106: =IFERROR(_xlfn.TEXTAFTER(L106,"https://www."),"")&CHAR(10)&_xlfn.CONCAT(TEXT(F106,"$0.00")," + ",TEXT(P106,"$0.00")," (Shared Shipping) + ",TEXT(R106,"$0.00")," Tax = Total of ",TEXT(S106,"$0.00")) -> whatnot.com/order/3GyMAAaJhKT35PtSFFmp7M $1.00 + $0.23 (Shared Shipping) + $0.13 Tax = Total of $1.36 | O106: =SUM(F106:H106) -> 1.11 | P106: =SUMIFS(G:G,C:C,C106,D:D,D106)/COUNTIFS(C:C,C106,D:D,D106) -> 0.23166667 | Q106: =+F106+P106 -> 1.2316667 | R106: =IF(H106=0,0,Q106*0.1025) -> 0.12624583 | S106: =+Q106+R106 -> 1.3579125 | T106: =IFERROR(_xlfn.XLOOKUP(J106,Collection!A:A,Collection!D:D,0)/100/_xlfn.XLOOKUP(J106,Collection!A:A,Collection!J:J,0),_xlfn.XLOOKUP(J106,Sold!A:A,Sold!D:D,0)/100/_xlfn.XLOOKUP(J106,Sold!A:A,Sold!J:J,0)) -> 2.38 | U106: =IFERROR(T106-S106,0) -> 1.0220875 | V106: =COUNTIF(Collection!A:A,J106)+COUNTIF(Sold!A:A,J106) -> 1 | W106: =IFERROR(_xlfn.TEXTAFTER(_xlfn.XLOOKUP(J106,Collection!A:A,Collection!C:C,),"Cards "),_xlfn.TEXTAFTER(_xlfn.XLOOKUP(J106,Sold!A:A,Sold!C:C,),"Cards ")) -> 2025 Topps Chrome | X106: =IFERROR(_xlfn.XLOOKUP(J106,Collection!A:A,Collection!B:B,),_xlfn.XLOOKUP(J106,Sold!A:A,Sold!B:B,)) -> Joe Burrow [Pulsar Refractor] #61 | Y106: .
B107: R | C107: fzmn77 | D107: 46156 | E107: 115 | F107: 1 | G107: 0.3 | H107: 0.15 | I107: Wembanyama | J107: 12615262 | K107: 419 | L107: https://www.whatnot.com/order/jrU4Q7xp5yH4tmGayj7YpY | M107: whatnot.com/order/jrU4Q7xp5yH4tmGayj7YpY $1.00 + $0.23 (Shared Shipping) + $0.13 Tax = Total of $1.36 | N107: =IFERROR(_xlfn.TEXTAFTER(L107,"https://www."),"")&CHAR(10)&_xlfn.CONCAT(TEXT(F107,"$0.00")," + ",TEXT(P107,"$0.00")," (Shared Shipping) + ",TEXT(R107,"$0.00")," Tax = Total of ",TEXT(S107,"$0.00")) -> whatnot.com/order/jrU4Q7xp5yH4tmGayj7YpY $1.00 + $0.23 (Shared Shipping) + $0.13 Tax = Total of $1.36 | O107: =SUM(F107:H107) -> 1.45 | P107: =SUMIFS(G:G,C:C,C107,D:D,D107)/COUNTIFS(C:C,C107,D:D,D107) -> 0.23166667 | Q107: =+F107+P107 -> 1.2316667 | R107: =IF(H107=0,0,Q107*0.1025) -> 0.12624583 | S107: =+Q107+R107 -> 1.3579125 | T107: =IFERROR(_xlfn.XLOOKUP(J107,Collection!A:A,Collection!D:D,0)/100/_xlfn.XLOOKUP(J107,Collection!A:A,Collection!J:J,0),_xlfn.XLOOKUP(J107,Sold!A:A,Sold!D:D,0)/100/_xlfn.XLOOKUP(J107,Sold!A:A,Sold!J:J,0)) -> 1.35 | U107: =IFERROR(T107-S107,0) -> -0.0079125 | V107: =COUNTIF(Collection!A:A,J107)+COUNTIF(Sold!A:A,J107) -> 2 | W107: =IFERROR(_xlfn.TEXTAFTER(_xlfn.XLOOKUP(J107,Collection!A:A,Collection!C:C,),"Cards "),_xlfn.TEXTAFTER(_xlfn.XLOOKUP(J107,Sold!A:A,Sold!C:C,),"Cards ")) -> 2025 Bowman | X107: =IFERROR(_xlfn.XLOOKUP(J107,Collection!A:A,Collection!B:B,),_xlfn.XLOOKUP(J107,Sold!A:A,Sold!B:B,)) -> Victor Wembanyama #143 | Y107: .
B108: R | C108: fzmn77 | D108: 46156 | E108: 117 | F108: 0.5 | G108: 0 | H108: 0.06 | I108: Luka | J108: 12622531 | K108: 269 | L108: https://www.whatnot.com/order/QmxKqJw97MkWL4F4CV22QD | M108: whatnot.com/order/QmxKqJw97MkWL4F4CV22QD $0.50 + $0.23 (Shared Shipping) + $0.07 Tax = Total of $0.81 | N108: =IFERROR(_xlfn.TEXTAFTER(L108,"https://www."),"")&CHAR(10)&_xlfn.CONCAT(TEXT(F108,"$0.00")," + ",TEXT(P108,"$0.00")," (Shared Shipping) + ",TEXT(R108,"$0.00")," Tax = Total of ",TEXT(S108,"$0.00")) -> whatnot.com/order/QmxKqJw97MkWL4F4CV22QD $0.50 + $0.23 (Shared Shipping) + $0.07 Tax = Total of $0.81 | O108: =SUM(F108:H108) -> 0.56 | P108: =SUMIFS(G:G,C:C,C108,D:D,D108)/COUNTIFS(C:C,C108,D:D,D108) -> 0.23166667 | Q108: =+F108+P108 -> 0.73166667 | R108: =IF(H108=0,0,Q108*0.1025) -> 0.074995833 | S108: =+Q108+R108 -> 0.8066625 | T108: =IFERROR(_xlfn.XLOOKUP(J108,Collection!A:A,Collection!D:D,0)/100/_xlfn.XLOOKUP(J108,Collection!A:A,Collection!J:J,0),_xlfn.XLOOKUP(J108,Sold!A:A,Sold!D:D,0)/100/_xlfn.XLOOKUP(J108,Sold!A:A,Sold!J:J,0)) -> 1.99 | U108: =IFERROR(T108-S108,0) -> 1.1833375 | V108: =COUNTIF(Collection!A:A,J108)+COUNTIF(Sold!A:A,J108) -> 2 | W108: =IFERROR(_xlfn.TEXTAFTER(_xlfn.XLOOKUP(J108,Collection!A:A,Collection!C:C,),"Cards "),_xlfn.TEXTAFTER(_xlfn.XLOOKUP(J108,Sold!A:A,Sold!C:C,),"Cards ")) -> 2025 Bowman Chrome | X108: =IFERROR(_xlfn.XLOOKUP(J108,Collection!A:A,Collection!B:B,),_xlfn.XLOOKUP(J108,Sold!A:A,Sold!B:B,)) -> Luka DoncÌŒic #BCV-123 | Y108: .
B109: R | C109: fzmn77 | D109: 46156 | E109: 117 | F109: 0.5 | G109: 0 | H109: 0.05 | I109: Luka | J109: 12622531 | K109: 277 | L109: https://www.whatnot.com/order/QmxKqJw97MkWL4F4CV22QD | M109: whatnot.com/order/QmxKqJw97MkWL4F4CV22QD $0.50 + $0.23 (Shared Shipping) + $0.07 Tax = Total of $0.81 | N109: =IFERROR(_xlfn.TEXTAFTER(L109,"https://www."),"")&CHAR(10)&_xlfn.CONCAT(TEXT(F109,"$0.00")," + ",TEXT(P109,"$0.00")," (Shared Shipping) + ",TEXT(R109,"$0.00")," Tax = Total of ",TEXT(S109,"$0.00")) -> whatnot.com/order/QmxKqJw97MkWL4F4CV22QD $0.50 + $0.23 (Shared Shipping) + $0.07 Tax = Total of $0.81 | O109: =SUM(F109:H109) -> 0.55 | P109: =SUMIFS(G:G,C:C,C109,D:D,D109)/COUNTIFS(C:C,C109,D:D,D109) -> 0.23166667 | Q109: =+F109+P109 -> 0.73166667 | R109: =IF(H109=0,0,Q109*0.1025) -> 0.074995833 | S109: =+Q109+R109 -> 0.8066625 | T109: =IFERROR(_xlfn.XLOOKUP(J109,Collection!A:A,Collection!D:D,0)/100/_xlfn.XLOOKUP(J109,Collection!A:A,Collection!J:J,0),_xlfn.XLOOKUP(J109,Sold!A:A,Sold!D:D,0)/100/_xlfn.XLOOKUP(J109,Sold!A:A,Sold!J:J,0)) -> 1.99 | U109: =IFERROR(T109-S109,0) -> 1.1833375 | V109: =COUNTIF(Collection!A:A,J109)+COUNTIF(Sold!A:A,J109) -> 2 | W109: =IFERROR(_xlfn.TEXTAFTER(_xlfn.XLOOKUP(J109,Collection!A:A,Collection!C:C,),"Cards "),_xlfn.TEXTAFTER(_xlfn.XLOOKUP(J109,Sold!A:A,Sold!C:C,),"Cards ")) -> 2025 Bowman Chrome | X109: =IFERROR(_xlfn.XLOOKUP(J109,Collection!A:A,Collection!B:B,),_xlfn.XLOOKUP(J109,Sold!A:A,Sold!B:B,)) -> Luka DoncÌŒic #BCV-123 | Y109: .
B110: R | C110: wadek2332 | D110: 46156 | E110: 9 | F110: 10 | G110: 4.35 | H110: 1.48 | I110: Maxey | J110: 10482574 | K110: 28 | L110: https://www.whatnot.com/order/RkyA6Bkpg2Bd9SGH2hZzTu | M110: whatnot.com/order/RkyA6Bkpg2Bd9SGH2hZzTu $10.00 + $4.35 (Shared Shipping) + $1.47 Tax = Total of $15.82 | N110: =IFERROR(_xlfn.TEXTAFTER(L110,"https://www."),"")&CHAR(10)&_xlfn.CONCAT(TEXT(F110,"$0.00")," + ",TEXT(P110,"$0.00")," (Shared Shipping) + ",TEXT(R110,"$0.00")," Tax = Total of ",TEXT(S110,"$0.00")) -> whatnot.com/order/RkyA6Bkpg2Bd9SGH2hZzTu $10.00 + $4.35 (Shared Shipping) + $1.47 Tax = Total of $15.82 | O110: =SUM(F110:H110) -> 15.83 | P110: =SUMIFS(G:G,C:C,C110,D:D,D110)/COUNTIFS(C:C,C110,D:D,D110) -> 4.35 | Q110: =+F110+P110 -> 14.35 | R110: =IF(H110=0,0,Q110*0.1025) -> 1.470875 | S110: =+Q110+R110 -> 15.820875 | T110: =IFERROR(_xlfn.XLOOKUP(J110,Collection!A:A,Collection!D:D,0)/100/_xlfn.XLOOKUP(J110,Collection!A:A,Collection!J:J,0),_xlfn.XLOOKUP(J110,Sold!A:A,Sold!D:D,0)/100/_xlfn.XLOOKUP(J110,Sold!A:A,Sold!J:J,0)) -> 11.4 | U110: =IFERROR(T110-S110,0) -> -4.420875 | V110: =COUNTIF(Collection!A:A,J110)+COUNTIF(Sold!A:A,J110) -> 1 | W110: =IFERROR(_xlfn.TEXTAFTER(_xlfn.XLOOKUP(J110,Collection!A:A,Collection!C:C,),"Cards "),_xlfn.TEXTAFTER(_xlfn.XLOOKUP(J110,Sold!A:A,Sold!C:C,),"Cards ")) -> 2024 Panini Obsidian Equinox | X110: =IFERROR(_xlfn.XLOOKUP(J110,Collection!A:A,Collection!B:B,),_xlfn.XLOOKUP(J110,Sold!A:A,Sold!B:B,)) -> Tyrese Maxey [Electric Etch Orange Flood] #20 | Y110: .
B111: R | C111: everydaysingles | D111: 46156 | E111: 2 | F111: 1 | G111: 0.31 | H111: 0.15 | I111: Luka | J111: 6292612 | K111: 498 | L111: https://www.whatnot.com/order/m7u6JPnkRPdg3KPtvFYypQ | M111: whatnot.com/order/m7u6JPnkRPdg3KPtvFYypQ $1.00 + $0.14 (Shared Shipping) + $0.12 Tax = Total of $1.25 | N111: =IFERROR(_xlfn.TEXTAFTER(L111,"https://www."),"")&CHAR(10)&_xlfn.CONCAT(TEXT(F111,"$0.00")," + ",TEXT(P111,"$0.00")," (Shared Shipping) + ",TEXT(R111,"$0.00")," Tax = Total of ",TEXT(S111,"$0.00")) -> whatnot.com/order/m7u6JPnkRPdg3KPtvFYypQ $1.00 + $0.14 (Shared Shipping) + $0.12 Tax = Total of $1.25 | O111: =SUM(F111:H111) -> 1.46 | P111: =SUMIFS(G:G,C:C,C111,D:D,D111)/COUNTIFS(C:C,C111,D:D,D111) -> 0.13625 | Q111: =+F111+P111 -> 1.13625 | R111: =IF(H111=0,0,Q111*0.1025) -> 0.11646562 | S111: =+Q111+R111 -> 1.2527156 | T111: =IFERROR(_xlfn.XLOOKUP(J111,Collection!A:A,Collection!D:D,0)/100/_xlfn.XLOOKUP(J111,Collection!A:A,Collection!J:J,0),_xlfn.XLOOKUP(J111,Sold!A:A,Sold!D:D,0)/100/_xlfn.XLOOKUP(J111,Sold!A:A,Sold!J:J,0)) -> 1.23 | U111: =IFERROR(T111-S111,0) -> -0.022715625 | V111: =COUNTIF(Collection!A:A,J111)+COUNTIF(Sold!A:A,J111) -> 1 | W111: =IFERROR(_xlfn.TEXTAFTER(_xlfn.XLOOKUP(J111,Collection!A:A,Collection!C:C,),"Cards "),_xlfn.TEXTAFTER(_xlfn.XLOOKUP(J111,Sold!A:A,Sold!C:C,),"Cards ")) -> 2023 Panini Donruss Bomb Squad | X111: =IFERROR(_xlfn.XLOOKUP(J111,Collection!A:A,Collection!B:B,),_xlfn.XLOOKUP(J111,Sold!A:A,Sold!B:B,)) -> Luka Doncic #3 | Y111: .
...

Sheet Collection
A1: id | B1: product-name | C1: console-name | D1: price-in-pennies | E1: include-string | F1: condition-string | G1: sku | H1: notes | I1: cost-basis-in-pennies | J1: quantity | K1: date-entered | L1: date-purchased | M1: grading-company | N1: grading-cert-id | O1: folder | P1: Player Label | Q1: Set Name | R1: Variant | S1: Number | T1: Value | U1: PSV Player Label | V1: Status | W1: Count | X1: Tier | Y1: Desired Price | Z1: Minimum Price | AB1: Conditions | AC1: =COUNTBLANK(N1:N558) -> 0 | AE1: Average of Top 3 cards | AL1: Typos | AM1: Corrected
A2: 11484449 | B2: Cooper Flagg #251 | C2: Basketball Cards 2025 Topps Chrome | D2: 2104 | E2: Ungraded | F2: Normal wear | H2: eBay | I2: 2944 | J2: 1 | K2: 46133 | L2: 46132 | N2: 13 | P2: =TRIM(LEFT(B2, MIN(IFERROR(FIND("[", B2), LEN(B2)+1), IFERROR(FIND("#", B2), LEN(B2)+1)) - 1)) -> Cooper Flagg | Q2: =IFERROR(_xlfn.TEXTAFTER(_xlfn.XLOOKUP(A2,Collection!A:A,Collection!C:C,),"Cards "),C2) -> 2025 Topps Chrome | R2: =IFERROR(_xlfn.TEXTBEFORE(_xlfn.TEXTAFTER(B2, "["), "]"), "-") -> - | S2: =IFERROR(_xlfn.TEXTAFTER(_xlfn.XLOOKUP(A2,Collection!A:A,Collection!B:B,),"#"),"") -> 251 | T2: =D2/100 -> 21.04 | U2: Cooper Flagg | V2: =IF(ISNUMBER(MATCH(N2,Catalog!$B$4:$B$16, 0)), "Keep", "For Sale") -> Keep | W2: =COUNTIFS(V:V,"For Sale",A:A,A2) -> 1 | X2: =_xlfn.LET( _xlpm.val,_xlfn.XLOOKUP(U2,AE:AE,AG:AG,)/100, _xlpm.tier,IF(_xlpm.val<1,5,IF(_xlpm.val<2,4,IF(_xlpm.val<5,3,IF(_xlpm.val<10,2,1)))), _xlpm.tier) -> 1 | Y2: =_xlfn.LET( _xlpm.price, (MAX(I2,D2,25)/100)*(1+$AC$3), _xlpm.rounder, IF(_xlpm.price < 1.5, FLOOR(_xlpm.price, 0.25), IF(_xlpm.price < 2.5, MROUND(_xlpm.price, 0.5), MROUND(_xlpm.price, 1))), MAX(0.25, _xlpm.rounder)) -> 35 | Z2: =_xlfn.LET( _xlpm.price, IF(I2=0, IF(W2>1,1-$AC$2,1)*(D2/100), MIN(IF(W2>1,1-$AC$2,1)*(D2/100), IF(W2>1,1-$AC$2,1)*(I2/100))), _xlpm.rounder, IF(_xlpm.price < 1.5, FLOOR(_xlpm.price, 0.25), IF(_xlpm.price < 2.5, MROUND(_xlpm.price, 0.5), MROUND(_xlpm.price, 1))), MAX(0.25, _xlpm.rounder)) -> 21 | AB2: Double Discount | AC2: 0.15 | AL2: Luka DoncÌŒic | AM2: Luka Doncic
A3: 11484449 | B3: Cooper Flagg #251 | C3: Basketball Cards 2025 Topps Chrome | D3: 2104 | E3: Ungraded | F3: Normal wear | H3: "whatnot.com/order/JCCEshFbNE7KuEUh3Kjd6B_x000D_ $15.00 + $1.05 (Shared Shipping) + $1.65 Tax = Total of $17.70" | I3: 1770 | J3: 1 | K3: 46183 | L3: 46182 | N3: 14 | P3: =TRIM(LEFT(B3, MIN(IFERROR(FIND("[", B3), LEN(B3)+1), IFERROR(FIND("#", B3), LEN(B3)+1)) - 1)) -> Cooper Flagg | Q3: =IFERROR(_xlfn.TEXTAFTER(_xlfn.XLOOKUP(A3,Collection!A:A,Collection!C:C,),"Cards "),C3) -> 2025 Topps Chrome | R3: =IFERROR(_xlfn.TEXTBEFORE(_xlfn.TEXTAFTER(B3, "["), "]"), "-") -> - | S3: =IFERROR(_xlfn.TEXTAFTER(_xlfn.XLOOKUP(A3,Collection!A:A,Collection!B:B,),"#"),"") -> 251 | T3: =D3/100 -> 21.04 | U3: Cooper Flagg | V3: =IF(ISNUMBER(MATCH(N3,Catalog!$B$4:$B$16, 0)), "Keep", "For Sale") -> For Sale | W3: =COUNTIFS(V:V,"For Sale",A:A,A3) -> 1 | X3: =_xlfn.LET( _xlpm.val,_xlfn.XLOOKUP(U3,AE:AE,AG:AG,)/100, _xlpm.tier,IF(_xlpm.val<1,5,IF(_xlpm.val<2,4,IF(_xlpm.val<5,3,IF(_xlpm.val<10,2,1)))), _xlpm.tier) -> 1 | Y3: =_xlfn.LET( _xlpm.price, (MAX(I3,D3,25)/100)*(1+$AC$3), _xlpm.rounder, IF(_xlpm.price < 1.5, FLOOR(_xlpm.price, 0.25), IF(_xlpm.price < 2.5, MROUND(_xlpm.price, 0.5), MROUND(_xlpm.price, 1))), MAX(0.25, _xlpm.rounder)) -> 25 | Z3: =_xlfn.LET( _xlpm.price, IF(I3=0, IF(W3>1,1-$AC$2,1)*(D3/100), MIN(IF(W3>1,1-$AC$2,1)*(D3/100), IF(W3>1,1-$AC$2,1)*(I3/100))), _xlpm.rounder, IF(_xlpm.price < 1.5, FLOOR(_xlpm.price, 0.25), IF(_xlpm.price < 2.5, MROUND(_xlpm.price, 0.5), MROUND(_xlpm.price, 1))), MAX(0.25, _xlpm.rounder)) -> 18 | AB3: Desired Profit | AC3: 0.2 | AE3: PSV Player Label | AF3: id | AG3: Average of price-in-pennies | AI3: Row Labels | AJ3: Sum of quantity | AL3: Gheorghe MureÈ™an | AM3: Gheorghe Muresan
A4: 11498132 | B4: Cooper Flagg #SY-11 | C4: Basketball Cards 2025 Topps Chrome Serenity | D4: 1311 | E4: Ungraded | F4: Normal wear | H4: "https://www.whatnot.com/order/P6hZiMYk2ffSa8sLEMVeWQ_x000D_ $0.00 + $0.91 (Shared Shipping) + $0.09 Tax = Total of $1.00" | I4: 100 | J4: 1 | K4: 46174 | L4: 46173 | N4: 26 | P4: =TRIM(LEFT(B4, MIN(IFERROR(FIND("[", B4), LEN(B4)+1), IFERROR(FIND("#", B4), LEN(B4)+1)) - 1)) -> Cooper Flagg | Q4: =IFERROR(_xlfn.TEXTAFTER(_xlfn.XLOOKUP(A4,Collection!A:A,Collection!C:C,),"Cards "),C4) -> 2025 Topps Chrome Serenity | R4: =IFERROR(_xlfn.TEXTBEFORE(_xlfn.TEXTAFTER(B4, "["), "]"), "-") -> - | S4: =IFERROR(_xlfn.TEXTAFTER(_xlfn.XLOOKUP(A4,Collection!A:A,Collection!B:B,),"#"),"") -> SY-11 | T4: =D4/100 -> 13.11 | U4: Cooper Flagg | V4: =IF(ISNUMBER(MATCH(N4,Catalog!$B$4:$B$16, 0)), "Keep", "For Sale") -> For Sale | W4: =COUNTIFS(V:V,"For Sale",A:A,A4) -> 1 | X4: =_xlfn.LET( _xlpm.val,_xlfn.XLOOKUP(U4,AE:AE,AG:AG,)/100, _xlpm.tier,IF(_xlpm.val<1,5,IF(_xlpm.val<2,4,IF(_xlpm.val<5,3,IF(_xlpm.val<10,2,1)))), _xlpm.tier) -> 1 | Y4: =_xlfn.LET( _xlpm.price, (MAX(I4,D4,25)/100)*(1+$AC$3), _xlpm.rounder, IF(_xlpm.price < 1.5, FLOOR(_xlpm.price, 0.25), IF(_xlpm.price < 2.5, MROUND(_xlpm.price, 0.5), MROUND(_xlpm.price, 1))), MAX(0.25, _xlpm.rounder)) -> 16 | Z4: =_xlfn.LET( _xlpm.price, IF(I4=0, IF(W4>1,1-$AC$2,1)*(D4/100), MIN(IF(W4>1,1-$AC$2,1)*(D4/100), IF(W4>1,1-$AC$2,1)*(I4/100))), _xlpm.rounder, IF(_xlpm.price < 1.5, FLOOR(_xlpm.price, 0.25), IF(_xlpm.price < 2.5, MROUND(_xlpm.price, 0.5), MROUND(_xlpm.price, 1))), MAX(0.25, _xlpm.rounder)) -> 1 | AE4: Luka Doncic | AG4: 11091.333 | AI4: Luka Doncic | AJ4: 73 | AL4: Jason Kidd Single | AM4: Jason Kidd
A5: 10819468 | B5: Cooper Flagg #201 | C5: Basketball Cards 2025 Topps | D5: 488 | E5: Ungraded | F5: Normal wear | H5: "https://www.whatnot.com/order/WKa7ntNswTBEf2VahSBtgB_x000D_ $4.00 + $0.55 (Shared Shipping) + $0.47 Tax = Total of $5.01" | I5: 501 | J5: 1 | K5: 46154 | L5: 46152 | N5: 129 | P5: =TRIM(LEFT(B5, MIN(IFERROR(FIND("[", B5), LEN(B5)+1), IFERROR(FIND("#", B5), LEN(B5)+1)) - 1)) -> Cooper Flagg | Q5: =IFERROR(_xlfn.TEXTAFTER(_xlfn.XLOOKUP(A5,Collection!A:A,Collection!C:C,),"Cards "),C5) -> 2025 Topps | R5: =IFERROR(_xlfn.TEXTBEFORE(_xlfn.TEXTAFTER(B5, "["), "]"), "-") -> - | S5: =IFERROR(_xlfn.TEXTAFTER(_xlfn.XLOOKUP(A5,Collection!A:A,Collection!B:B,),"#"),"") -> 201 | T5: =D5/100 -> 4.88 | U5: Cooper Flagg | V5: =IF(ISNUMBER(MATCH(N5,Catalog!$B$4:$B$16, 0)), "Keep", "For Sale") -> For Sale | W5: =COUNTIFS(V:V,"For Sale",A:A,A5) -> 1 | X5: =_xlfn.LET( _xlpm.val,_xlfn.XLOOKUP(U5,AE:AE,AG:AG,)/100, _xlpm.tier,IF(_xlpm.val<1,5,IF(_xlpm.val<2,4,IF(_xlpm.val<5,3,IF(_xlpm.val<10,2,1)))), _xlpm.tier) -> 1 | Y5: =_xlfn.LET( _xlpm.price, (MAX(I5,D5,25)/100)*(1+$AC$3), _xlpm.rounder, IF(_xlpm.price < 1.5, FLOOR(_xlpm.price, 0.25), IF(_xlpm.price < 2.5, MROUND(_xlpm.price, 0.5), MROUND(_xlpm.price, 1))), MAX(0.25, _xlpm.rounder)) -> 6 | Z5: =_xlfn.LET( _xlpm.price, IF(I5=0, IF(W5>1,1-$AC$2,1)*(D5/100), MIN(IF(W5>1,1-$AC$2,1)*(D5/100), IF(W5>1,1-$AC$2,1)*(I5/100))), _xlpm.rounder, IF(_xlpm.price < 1.5, FLOOR(_xlpm.price, 0.25), IF(_xlpm.price < 2.5, MROUND(_xlpm.price, 0.5), MROUND(_xlpm.price, 1))), MAX(0.25, _xlpm.rounder)) -> 5 | AE5: Michael Jordan | AG5: 10340 | AI5: Michael Jordan | AJ5: 35 | AL5: Shai Gilgeous Alexander | AM5: Shai Gilgeous-Alexander
A6: 12613839 | B6: Cooper Flagg #1 | C6: Basketball Cards 2025 Bowman | D6: 371 | E6: Ungraded | F6: Normal wear | H6: "https://www.whatnot.com/order/cVAH6c2Ha2VVKr4oHxHUDo_x000D_ $2.00 + $4.55 (Shared Shipping) + $0.67 Tax = Total of $7.22" | I6: 722 | J6: 1 | K6: 46161 | L6: 46161 | N6: 149 | P6: =TRIM(LEFT(B6, MIN(IFERROR(FIND("[", B6), LEN(B6)+1), IFERROR(FIND("#", B6), LEN(B6)+1)) - 1)) -> Cooper Flagg | Q6: =IFERROR(_xlfn.TEXTAFTER(_xlfn.XLOOKUP(A6,Collection!A:A,Collection!C:C,),"Cards "),C6) -> 2025 Bowman | R6: =IFERROR(_xlfn.TEXTBEFORE(_xlfn.TEXTAFTER(B6, "["), "]"), "-") -> - | S6: =IFERROR(_xlfn.TEXTAFTER(_xlfn.XLOOKUP(A6,Collection!A:A,Collection!B:B,),"#"),"") -> 1 | T6: =D6/100 -> 3.71 | U6: Cooper Flagg | V6: =IF(ISNUMBER(MATCH(N6,Catalog!$B$4:$B$16, 0)), "Keep", "For Sale") -> For Sale | W6: =COUNTIFS(V:V,"For Sale",A:A,A6) -> 1 | X6: =_xlfn.LET( _xlpm.val,_xlfn.XLOOKUP(U6,AE:AE,AG:AG,)/100, _xlpm.tier,IF(_xlpm.val<1,5,IF(_xlpm.val<2,4,IF(_xlpm.val<5,3,IF(_xlpm.val<10,2,1)))), _xlpm.tier) -> 1 | Y6: =_xlfn.LET( _xlpm.price, (MAX(I6,D6,25)/100)*(1+$AC$3), _xlpm.rounder, IF(_xlpm.price < 1.5, FLOOR(_xlpm.price, 0.25), IF(_xlpm.price < 2.5, MROUND(_xlpm.price, 0.5), MROUND(_xlpm.price, 1))), MAX(0.25, _xlpm.rounder)) -> 9 | Z6: =_xlfn.LET( _xlpm.price, IF(I6=0, IF(W6>1,1-$AC$2,1)*(D6/100), MIN(IF(W6>1,1-$AC$2,1)*(D6/100), IF(W6>1,1-$AC$2,1)*(I6/100))), _xlpm.rounder, IF(_xlpm.price < 1.5, FLOOR(_xlpm.price, 0.25), IF(_xlpm.price < 2.5, MROUND(_xlpm.price, 0.5), MROUND(_xlpm.price, 1))), MAX(0.25, _xlpm.rounder)) -> 4 | AE6: Kobe Bryant | AG6: 4574 | AI6: Shaquille O'Neal | AJ6: 33
A7: 12530822 | B7: Deommodore Lenoir #269 | C7: Football Cards 2025 Topps Chrome | D7: 1231 | E7: Ungraded | F7: Normal wear | I7: 0 | J7: 1 | K7: 46172 | N7: 526 | P7: =TRIM(LEFT(B7, MIN(IFERROR(FIND("[", B7), LEN(B7)+1), IFERROR(FIND("#", B7), LEN(B7)+1)) - 1)) -> Deommodore Lenoir | Q7: =IFERROR(_xlfn.TEXTAFTER(_xlfn.XLOOKUP(A7,Collection!A:A,Collection!C:C,),"Cards "),C7) -> 2025 Topps Chrome | R7: =IFERROR(_xlfn.TEXTBEFORE(_xlfn.TEXTAFTER(B7, "["), "]"), "-") -> - | S7: =IFERROR(_xlfn.TEXTAFTER(_xlfn.XLOOKUP(A7,Collection!A:A,Collection!B:B,),"#"),"") -> 269 | T7: =D7/100 -> 12.31 | U7: Deommodore Lenoir | V7: =IF(ISNUMBER(MATCH(N7,Catalog!$B$4:$B$16, 0)), "Keep", "For Sale") -> For Sale | W7: =COUNTIFS(V:V,"For Sale",A:A,A7) -> 1 | X7: =_xlfn.LET( _xlpm.val,_xlfn.XLOOKUP(U7,AE:AE,AG:AG,)/100, _xlpm.tier,IF(_xlpm.val<1,5,IF(_xlpm.val<2,4,IF(_xlpm.val<5,3,IF(_xlpm.val<10,2,1)))), _xlpm.tier) -> 1 | Y7: =_xlfn.LET( _xlpm.price, (MAX(I7,D7,25)/100)*(1+$AC$3), _xlpm.rounder, IF(_xlpm.price < 1.5, FLOOR(_xlpm.price, 0.25), IF(_xlpm.price < 2.5, MROUND(_xlpm.price, 0.5), MROUND(_xlpm.price, 1))), MAX(0.25, _xlpm.rounder)) -> 15 | Z7: =_xlfn.LET( _xlpm.price, IF(I7=0, IF(W7>1,1-$AC$2,1)*(D7/100), MIN(IF(W7>1,1-$AC$2,1)*(D7/100), IF(W7>1,1-$AC$2,1)*(I7/100))), _xlpm.rounder, IF(_xlpm.price < 1.5, FLOOR(_xlpm.price, 0.25), IF(_xlpm.price < 2.5, MROUND(_xlpm.price, 0.5), MROUND(_xlpm.price, 1))), MAX(0.25, _xlpm.rounder)) -> 12 | AE7: Victor Wembanyama | AG7: 2032.6667 | AI7: Jason Williams | AJ7: 28
A8: 87362 | B8: Kobe Bryant #R10 | C8: Basketball Cards 1996 Upper Deck Rookie Exclusives | D8: 5550 | E8: Ungraded | F8: Normal wear | I8: 0 | J8: 1 | K8: 46127 | N8: 2 | P8: =TRIM(LEFT(B8, MIN(IFERROR(FIND("[", B8), LEN(B8)+1), IFERROR(FIND("#", B8), LEN(B8)+1)) - 1)) -> Kobe Bryant | Q8: =IFERROR(_xlfn.TEXTAFTER(_xlfn.XLOOKUP(A8,Collection!A:A,Collection!C:C,),"Cards "),C8) -> 1996 Upper Deck Rookie Exclusives | R8: =IFERROR(_xlfn.TEXTBEFORE(_xlfn.TEXTAFTER(B8, "["), "]"), "-") -> - | S8: =IFERROR(_xlfn.TEXTAFTER(_xlfn.XLOOKUP(A8,Collection!A:A,Collection!B:B,),"#"),"") -> R10 | T8: =D8/100 -> 55.5 | U8: Kobe Bryant | V8: =IF(ISNUMBER(MATCH(N8,Catalog!$B$4:$B$16, 0)), "Keep", "For Sale") -> Keep | W8: =COUNTIFS(V:V,"For Sale",A:A,A8) -> 0 | X8: =_xlfn.LET( _xlpm.val,_xlfn.XLOOKUP(U8,AE:AE,AG:AG,)/100, _xlpm.tier,IF(_xlpm.val<1,5,IF(_xlpm.val<2,4,IF(_xlpm.val<5,3,IF(_xlpm.val<10,2,1)))), _xlpm.tier) -> 1 | Y8: =_xlfn.LET( _xlpm.price, (MAX(I8,D8,25)/100)*(1+$AC$3), _xlpm.rounder, IF(_xlpm.price < 1.5, FLOOR(_xlpm.price, 0.25), IF(_xlpm.price < 2.5, MROUND(_xlpm.price, 0.5), MROUND(_xlpm.price, 1))), MAX(0.25, _xlpm.rounder)) -> 67 | Z8: =_xlfn.LET( _xlpm.price, IF(I8=0, IF(W8>1,1-$AC$2,1)*(D8/100), MIN(IF(W8>1,1-$AC$2,1)*(D8/100), IF(W8>1,1-$AC$2,1)*(I8/100))), _xlpm.rounder, IF(_xlpm.price < 1.5, FLOOR(_xlpm.price, 0.25), IF(_xlpm.price < 2.5, MROUND(_xlpm.price, 0.5), MROUND(_xlpm.price, 1))), MAX(0.25, _xlpm.rounder)) -> 56 | AE8: Spider-Man | AG8: 1649 | AI8: Stephon Marbury | AJ8: 23
A9: 87296 | B9: Kobe Bryant #52 | C9: Basketball Cards 1996 Ultra | D9: 4475 | E9: Ungraded | F9: Normal wear | I9: 0 | J9: 1 | K9: 46127 | N9: 4 | P9: =TRIM(LEFT(B9, MIN(IFERROR(FIND("[", B9), LEN(B9)+1), IFERROR(FIND("#", B9), LEN(B9)+1)) - 1)) -> Kobe Bryant | Q9: =IFERROR(_xlfn.TEXTAFTER(_xlfn.XLOOKUP(A9,Collection!A:A,Collection!C:C,),"Cards "),C9) -> 1996 Ultra | R9: =IFERROR(_xlfn.TEXTBEFORE(_xlfn.TEXTAFTER(B9, "["), "]"), "-") -> - | S9: =IFERROR(_xlfn.TEXTAFTER(_xlfn.XLOOKUP(A9,Collection!A:A,Collection!B:B,),"#"),"") -> 52 | T9: =D9/100 -> 44.75 | U9: Kobe Bryant | V9: =IF(ISNUMBER(MATCH(N9,Catalog!$B$4:$B$16, 0)), "Keep", "For Sale") -> For Sale | W9: =COUNTIFS(V:V,"For Sale",A:A,A9) -> 1 | X9: =_xlfn.LET( _xlpm.val,_xlfn.XLOOKUP(U9,AE:AE,AG:AG,)/100, _xlpm.tier,IF(_xlpm.val<1,5,IF(_xlpm.val<2,4,IF(_xlpm.val<5,3,IF(_xlpm.val<10,2,1)))), _xlpm.tier) -> 1 | Y9: =_xlfn.LET( _xlpm.price, (MAX(I9,D9,25)/100)*(1+$AC$3), _xlpm.rounder, IF(_xlpm.price < 1.5, FLOOR(_xlpm.price, 0.25), IF(_xlpm.price < 2.5, MROUND(_xlpm.price, 0.5), MROUND(_xlpm.price, 1))), MAX(0.25, _xlpm.rounder)) -> 54 | Z9: =_xlfn.LET( _xlpm.price, IF(I9=0, IF(W9>1,1-$AC$2,1)*(D9/100), MIN(IF(W9>1,1-$AC$2,1)*(D9/100), IF(W9>1,1-$AC$2,1)*(I9/100))), _xlpm.rounder, IF(_xlpm.price < 1.5, FLOOR(_xlpm.price, 0.25), IF(_xlpm.price < 2.5, MROUND(_xlpm.price, 0.5), MROUND(_xlpm.price, 1))), MAX(0.25, _xlpm.rounder)) -> 45 | AE9: Cooper Flagg | AG9: 1501.75 | AI9: Chris Webber | AJ9: 19
A10: 85652 | B10: Kobe Bryant #55 | C10: Basketball Cards 1996 Skybox Premium | D10: 3697 | E10: Ungraded | F10: Normal wear | I10: 0 | J10: 1 | K10: 46127 | N10: 5 | P10: =TRIM(LEFT(B10, MIN(IFERROR(FIND("[", B10), LEN(B10)+1), IFERROR(FIND("#", B10), LEN(B10)+1)) - 1)) -> Kobe Bryant | Q10: =IFERROR(_xlfn.TEXTAFTER(_xlfn.XLOOKUP(A10,Collection!A:A,Collection!C:C,),"Cards "),C10) -> 1996 Skybox Premium | R10: =IFERROR(_xlfn.TEXTBEFORE(_xlfn.TEXTAFTER(B10, "["), "]"), "-") -> - | S10: =IFERROR(_xlfn.TEXTAFTER(_xlfn.XLOOKUP(A10,Collection!A:A,Collection!B:B,),"#"),"") -> 55 | T10: =D10/100 -> 36.97 | U10: Kobe Bryant | V10: =IF(ISNUMBER(MATCH(N10,Catalog!$B$4:$B$16, 0)), "Keep", "For Sale") -> For Sale | W10: =COUNTIFS(V:V,"For Sale",A:A,A10) -> 1 | X10: =_xlfn.LET( _xlpm.val,_xlfn.XLOOKUP(U10,AE:AE,AG:AG,)/100, _xlpm.tier,IF(_xlpm.val<1,5,IF(_xlpm.val<2,4,IF(_xlpm.val<5,3,IF(_xlpm.val<10,2,1)))), _xlpm.tier) -> 1 | Y10: =_xlfn.LET( _xlpm.price, (MAX(I10,D10,25)/100)*(1+$AC$3), _xlpm.rounder, IF(_xlpm.price < 1.5, FLOOR(_xlpm.price, 0.25), IF(_xlpm.price < 2.5, MROUND(_xlpm.price, 0.5), MROUND(_xlpm.price, 1))), MAX(0.25, _xlpm.rounder)) -> 44 | Z10: =_xlfn.LET( _xlpm.price, IF(I10=0, IF(W10>1,1-$AC$2,1)*(D10/100), MIN(IF(W10>1,1-$AC$2,1)*(D10/100), IF(W10>1,1-$AC$2,1)*(I10/100))), _xlpm.rounder, IF(_xlpm.price < 1.5, FLOOR(_xlpm.price, 0.25), IF(_xlpm.price < 2.5, MROUND(_xlpm.price, 0.5), MROUND(_xlpm.price, 1))), MAX(0.25, _xlpm.rounder)) -> 37 | AE10: Deommodore Lenoir | AG10: 1231 | AI10: Shai Gilgeous-Alexander | AJ10: 15
A11: 3225482 | B11: Kobe Bryant #31 | C11: Basketball Cards 1997 Fleer Million Dollar Moments | D11: 299 | E11: Ungraded | F11: Normal wear | I11: 0 | J11: 1 | K11: 46186 | N11: 192 | P11: =TRIM(LEFT(B11, MIN(IFERROR(FIND("[", B11), LEN(B11)+1), IFERROR(FIND("#", B11), LEN(B11)+1)) - 1)) -> Kobe Bryant | Q11: =IFERROR(_xlfn.TEXTAFTER(_xlfn.XLOOKUP(A11,Collection!A:A,Collection!C:C,),"Cards "),C11) -> 1997 Fleer Million Dollar Moments | R11: =IFERROR(_xlfn.TEXTBEFORE(_xlfn.TEXTAFTER(B11, "["), "]"), "-") -> - | S11: =IFERROR(_xlfn.TEXTAFTER(_xlfn.XLOOKUP(A11,Collection!A:A,Collection!B:B,),"#"),"") -> 31 | T11: =D11/100 -> 2.99 | U11: Kobe Bryant | V11: =IF(ISNUMBER(MATCH(N11,Catalog!$B$4:$B$16, 0)), "Keep", "For Sale") -> For Sale | W11: =COUNTIFS(V:V,"For Sale",A:A,A11) -> 1 | X11: =_xlfn.LET( _xlpm.val,_xlfn.XLOOKUP(U11,AE:AE,AG:AG,)/100, _xlpm.tier,IF(_xlpm.val<1,5,IF(_xlpm.val<2,4,IF(_xlpm.val<5,3,IF(_xlpm.val<10,2,1)))), _xlpm.tier) -> 1 | Y11: =_xlfn.LET( _xlpm.price, (MAX(I11,D11,25)/100)*(1+$AC$3), _xlpm.rounder, IF(_xlpm.price < 1.5, FLOOR(_xlpm.price, 0.25), IF(_xlpm.price < 2.5, MROUND(_xlpm.price, 0.5), MROUND(_xlpm.price, 1))), MAX(0.25, _xlpm.rounder)) -> 4 | Z11: =_xlfn.LET( _xlpm.price, IF(I11=0, IF(W11>1,1-$AC$2,1)*(D11/100), MIN(IF(W11>1,1-$AC$2,1)*(D11/100), IF(W11>1,1-$AC$2,1)*(I11/100))), _xlpm.rounder, IF(_xlpm.price < 1.5, FLOOR(_xlpm.price, 0.25), IF(_xlpm.price < 2.5, MROUND(_xlpm.price, 0.5), MROUND(_xlpm.price, 1))), MAX(0.25, _xlpm.rounder)) -> 3 | AE11: Mac McClung | AG11: 1106 | AI11: Victor Wembanyama | AJ11: 12
A12: 114784 | B12: Luka Doncic #280 | C12: Basketball Cards 2018 Panini Prizm | D12: 19425 | E12: PSA 10 | F12: Normal wear | H12: "https://order.ebay.com/ord/show?orderId=04-14670-36767&purchaseOrderId=04-1467-036766#/_x000D_ $190.00 + $6.00 (Shared Shipping) + $20.09 Tax = Total of $216.09" | I12: 21609 | J12: 1 | K12: 46162 | L12: 46161 | M12: PSA | N12: 44578691 | P12: =TRIM(LEFT(B12, MIN(IFERROR(FIND("[", B12), LEN(B12)+1), IFERROR(FIND("#", B12), LEN(B12)+1)) - 1)) -> Luka Doncic | Q12: =IFERROR(_xlfn.TEXTAFTER(_xlfn.XLOOKUP(A12,Collection!A:A,Collection!C:C,),"Cards "),C12) -> 2018 Panini Prizm | R12: =IFERROR(_xlfn.TEXTBEFORE(_xlfn.TEXTAFTER(B12, "["), "]"), "-") -> - | S12: =IFERROR(_xlfn.TEXTAFTER(_xlfn.XLOOKUP(A12,Collection!A:A,Collection!B:B,),"#"),"") -> 280 | T12: =D12/100 -> 194.25 | U12: Luka Doncic | V12: =IF(ISNUMBER(MATCH(N12,Catalog!$B$4:$B$16, 0)), "Keep", "For Sale") -> Keep | W12: =COUNTIFS(V:V,"For Sale",A:A,A12) -> 0 | X12: =_xlfn.LET( _xlpm.val,_xlfn.XLOOKUP(U12,AE:AE,AG:AG,)/100, _xlpm.tier,IF(_xlpm.val<1,5,IF(_xlpm.val<2,4,IF(_xlpm.val<5,3,IF(_xlpm.val<10,2,1)))), _xlpm.tier) -> 1 | Y12: =_xlfn.LET( _xlpm.price, (MAX(I12,D12,25)/100)*(1+$AC$3), _xlpm.rounder, IF(_xlpm.price < 1.5, FLOOR(_xlpm.price, 0.25), IF(_xlpm.price < 2.5, MROUND(_xlpm.price, 0.5), MROUND(_xlpm.price, 1))), MAX(0.25, _xlpm.rounder)) -> 259 | Z12: =_xlfn.LET( _xlpm.price, IF(I12=0, IF(W12>1,1-$AC$2,1)*(D12/100), MIN(IF(W12>1,1-$AC$2,1)*(D12/100), IF(W12>1,1-$AC$2,1)*(I12/100))), _xlpm.rounder, IF(_xlpm.price < 1.5, FLOOR(_xlpm.price, 0.25), IF(_xlpm.price < 2.5, MROUND(_xlpm.price, 0.5), MROUND(_xlpm.price, 1))), MAX(0.25, _xlpm.rounder)) -> 194 | AE12: Nikola Jokic | AG12: 977 | AI12: Scottie Pippen | AJ12: 11
A13: 116892 | B13: Luka Doncic #122 | C13: Basketball Cards 2018 Panini Status | D13: 12000 | E13: PSA 10 | F13: Normal wear | H13: $85.00 + Shipping $5.75 + Tax $9.30 = $100.05 | I13: 10005 | J13: 1 | K13: 46192 | L13: 46186 | M13: PSA | N13: 78077713 | P13: =TRIM(LEFT(B13, MIN(IFERROR(FIND("[", B13), LEN(B13)+1), IFERROR(FIND("#", B13), LEN(B13)+1)) - 1)) -> Luka Doncic | Q13: =IFERROR(_xlfn.TEXTAFTER(_xlfn.XLOOKUP(A13,Collection!A:A,Collection!C:C,),"Cards "),C13) -> 2018 Panini Status | R13: =IFERROR(_xlfn.TEXTBEFORE(_xlfn.TEXTAFTER(B13, "["), "]"), "-") -> - | S13: =IFERROR(_xlfn.TEXTAFTER(_xlfn.XLOOKUP(A13,Collection!A:A,Collection!B:B,),"#"),"") -> 122 | T13: =D13/100 -> 120 | U13: Luka Doncic | V13: =IF(ISNUMBER(MATCH(N13,Catalog!$B$4:$B$16, 0)), "Keep", "For Sale") -> For Sale | W13: =COUNTIFS(V:V,"For Sale",A:A,A13) -> 1 | X13: =_xlfn.LET( _xlpm.val,_xlfn.XLOOKUP(U13,AE:AE,AG:AG,)/100, _xlpm.tier,IF(_xlpm.val<1,5,IF(_xlpm.val<2,4,IF(_xlpm.val<5,3,IF(_xlpm.val<10,2,1)))), _xlpm.tier) -> 1 | Y13: =_xlfn.LET( _xlpm.price, (MAX(I13,D13,25)/100)*(1+$AC$3), _xlpm.rounder, IF(_xlpm.price < 1.5, FLOOR(_xlpm.price, 0.25), IF(_xlpm.price < 2.5, MROUND(_xlpm.price, 0.5), MROUND(_xlpm.price, 1))), MAX(0.25, _xlpm.rounder)) -> 144 | Z13: =_xlfn.LET( _xlpm.price, IF(I13=0, IF(W13>1,1-$AC$2,1)*(D13/100), MIN(IF(W13>1,1-$AC$2,1)*(D13/100), IF(W13>1,1-$AC$2,1)*(I13/100))), _xlpm.rounder, IF(_xlpm.price < 1.5, FLOOR(_xlpm.price, 0.25), IF(_xlpm.price < 2.5, MROUND(_xlpm.price, 0.5), MROUND(_xlpm.price, 1))), MAX(0.25, _xlpm.rounder)) -> 100 | AE13: Shai Gilgeous-Alexander | AG13: 885 | AI13: Allen Iverson | AJ13: 11
A14: 158107 | B14: Luka Doncic #3 | C14: Basketball Cards 2018 Panini Hoops Class of 2018 | D14: 1849 | E14: Ungraded | F14: Normal wear | H14: Traded for Victor Wembanyama #HP-VW 2025 Topps Match Attax Hot Prospects valued at $7.34 | I14: 734 | J14: 1 | K14: 46189 | L14: 46186 | N14: 16 | P14: =TRIM(LEFT(B14, MIN(IFERROR(FIND("[", B14), LEN(B14)+1), IFERROR(FIND("#", B14), LEN(B14)+1)) - 1)) -> Luka Doncic | Q14: =IFERROR(_xlfn.TEXTAFTER(_xlfn.XLOOKUP(A14,Collection!A:A,Collection!C:C,),"Cards "),C14) -> 2018 Panini Hoops Class of 2018 | R14: =IFERROR(_xlfn.TEXTBEFORE(_xlfn.TEXTAFTER(B14, "["), "]"), "-") -> - | S14: =IFERROR(_xlfn.TEXTAFTER(_xlfn.XLOOKUP(A14,Collection!A:A,Collection!B:B,),"#"),"") -> 3 | T14: =D14/100 -> 18.49 | U14: Luka Doncic | V14: =IF(ISNUMBER(MATCH(N14,Catalog!$B$4:$B$16, 0)), "Keep", "For Sale") -> For Sale | W14: =COUNTIFS(V:V,"For Sale",A:A,A14) -> 1 | X14: =_xlfn.LET( _xlpm.val,_xlfn.XLOOKUP(U14,AE:AE,AG:AG,)/100, _xlpm.tier,IF(_xlpm.val<1,5,IF(_xlpm.val<2,4,IF(_xlpm.val<5,3,IF(_xlpm.val<10,2,1)))), _xlpm.tier) -> 1 | Y14: =_xlfn.LET( _xlpm.price, (MAX(I14,D14,25)/100)*(1+$AC$3), _xlpm.rounder, IF(_xlpm.price < 1.5, FLOOR(_xlpm.price, 0.25), IF(_xlpm.price < 2.5, MROUND(_xlpm.price, 0.5), MROUND(_xlpm.price, 1))), MAX(0.25, _xlpm.rounder)) -> 22 | Z14: =_xlfn.LET( _xlpm.price, IF(I14=0, IF(W14>1,1-$AC$2,1)*(D14/100), MIN(IF(W14>1,1-$AC$2,1)*(D14/100), IF(W14>1,1-$AC$2,1)*(I14/100))), _xlpm.rounder, IF(_xlpm.price < 1.5, FLOOR(_xlpm.price, 0.25), IF(_xlpm.price < 2.5, MROUND(_xlpm.price, 0.5), MROUND(_xlpm.price, 1))), MAX(0.25, _xlpm.rounder)) -> 7 | AE14: Tim Duncan | AG14: 865.5 | AI14: Nikola Jokic | AJ14: 10
A15: 9267400 | B15: Luka Doncic [Blue Astro] #9 | C15: Basketball Cards 2024 Panini Revolution Star Gazing | D15: 1400 | E15: Ungraded | F15: Normal wear | H15: "whatnot.com/order/n8cE95JzPotDagv8zS8364_x000D_ $11.00 + $1.05 (Shared Shipping) + $1.24 Tax = Total of $13.29" | I15: 1329 | J15: 1 | K15: 46183 | L15: 46182 | N15: 23 | P15: =TRIM(LEFT(B15, MIN(IFERROR(FIND("[", B15), LEN(B15)+1), IFERROR(FIND("#", B15), LEN(B15)+1)) - 1)) -> Luka Doncic | Q15: =IFERROR(_xlfn.TEXTAFTER(_xlfn.XLOOKUP(A15,Collection!A:A,Collection!C:C,),"Cards "),C15) -> 2024 Panini Revolution Star Gazing | R15: =IFERROR(_xlfn.TEXTBEFORE(_xlfn.TEXTAFTER(B15, "["), "]"), "-") -> Blue Astro | S15: =IFERROR(_xlfn.TEXTAFTER(_xlfn.XLOOKUP(A15,Collection!A:A,Collection!B:B,),"#"),"") -> 9 | T15: =D15/100 -> 14 | U15: Luka Doncic | V15: =IF(ISNUMBER(MATCH(N15,Catalog!$B$4:$B$16, 0)), "Keep", "For Sale") -> For Sale | W15: =COUNTIFS(V:V,"For Sale",A:A,A15) -> 1 | X15: =_xlfn.LET( _xlpm.val,_xlfn.XLOOKUP(U15,AE:AE,AG:AG,)/100, _xlpm.tier,IF(_xlpm.val<1,5,IF(_xlpm.val<2,4,IF(_xlpm.val<5,3,IF(_xlpm.val<10,2,1)))), _xlpm.tier) -> 1 | Y15: =_xlfn.LET( _xlpm.price, (MAX(I15,D15,25)/100)*(1+$AC$3), _xlpm.rounder, IF(_xlpm.price < 1.5, FLOOR(_xlpm.price, 0.25), IF(_xlpm.price < 2.5, MROUND(_xlpm.price, 0.5), MROUND(_xlpm.price, 1))), MAX(0.25, _xlpm.rounder)) -> 17 | Z15: =_xlfn.LET( _xlpm.price, IF(I15=0, IF(W15>1,1-$AC$2,1)*(D15/100), MIN(IF(W15>1,1-$AC$2,1)*(D15/100), IF(W15>1,1-$AC$2,1)*(I15/100))), _xlpm.rounder, IF(_xlpm.price < 1.5, FLOOR(_xlpm.price, 0.25), IF(_xlpm.price < 2.5, MROUND(_xlpm.price, 0.5), MROUND(_xlpm.price, 1))), MAX(0.25, _xlpm.rounder)) -> 13 | AE15: Mark Jackson | AG15: 865 | AI15: Damon Stoudamire | AJ15: 10
A16: 3607580 | B16: Luka Doncic #5 | C16: Basketball Cards 2020 Panini Hoops SLAM | D16: 1151 | E16: Ungraded | F16: Normal wear | H16: "https://www.ebay.com/itm/318340938096_x000D_ $8.50 + $1.32 (Shared Shipping) + $1.01 Tax = Total of $10.83" | I16: 1083 | J16: 1 | K16: 46171 | L16: 46170 | N16: 29 | P16: =TRIM(LEFT(B16, MIN(IFERROR(FIND("[", B16), LEN(B16)+1), IFERROR(FIND("#", B16), LEN(B16)+1)) - 1)) -> Luka Doncic | Q16: =IFERROR(_xlfn.TEXTAFTER(_xlfn.XLOOKUP(A16,Collection!A:A,Collection!C:C,),"Cards "),C16) -> 2020 Panini Hoops SLAM | R16: =IFERROR(_xlfn.TEXTBEFORE(_xlfn.TEXTAFTER(B16, "["), "]"), "-") -> - | S16: =IFERROR(_xlfn.TEXTAFTER(_xlfn.XLOOKUP(A16,Collection!A:A,Collection!B:B,),"#"),"") -> 5 | T16: =D16/100 -> 11.51 | U16: Luka Doncic | V16: =IF(ISNUMBER(MATCH(N16,Catalog!$B$4:$B$16, 0)), "Keep", "For Sale") -> Keep | W16: =COUNTIFS(V:V,"For Sale",A:A,A16) -> 0 | X16: =_xlfn.LET( _xlpm.val,_xlfn.XLOOKUP(U16,AE:AE,AG:AG,)/100, _xlpm.tier,IF(_xlpm.val<1,5,IF(_xlpm.val<2,4,IF(_xlpm.val<5,3,IF(_xlpm.val<10,2,1)))), _xlpm.tier) -> 1 | Y16: =_xlfn.LET( _xlpm.price, (MAX(I16,D16,25)/100)*(1+$AC$3), _xlpm.rounder, IF(_xlpm.price < 1.5, FLOOR(_xlpm.price, 0.25), IF(_xlpm.price < 2.5, MROUND(_xlpm.price, 0.5), MROUND(_xlpm.price, 1))), MAX(0.25, _xlpm.rounder)) -> 14 | Z16: =_xlfn.LET( _xlpm.price, IF(I16=0, IF(W16>1,1-$AC$2,1)*(D16/100), MIN(IF(W16>1,1-$AC$2,1)*(D16/100), IF(W16>1,1-$AC$2,1)*(I16/100))), _xlpm.rounder, IF(_xlpm.price < 1.5, FLOOR(_xlpm.price, 0.25), IF(_xlpm.price < 2.5, MROUND(_xlpm.price, 0.5), MROUND(_xlpm.price, 1))), MAX(0.25, _xlpm.rounder)) -> 11 | AE16: Jason Williams | AG16: 802 | AI16: Kevin Garnett | AJ16: 8
A17: 2857292 | B17: Luka Doncic [Teal] #15 | C17: Basketball Cards 2019 Panini Chronicles | D17: 587 | E17: Ungraded | F17: Normal wear | H17: "https://www.whatnot.com/order/THjJHwGpnJ2cNFaSnvcckW_x000D_ $1.00 + $1.00 (Shared Shipping) + $0.21 Tax = Total of $2.21" | I17: 221 | J17: 1 | K17: 46154 | L17: 46150 | N17: 110 | P17: =TRIM(LEFT(B17, MIN(IFERROR(FIND("[", B17), LEN(B17)+1), IFERROR(FIND("#", B17), LEN(B17)+1)) - 1)) -> Luka Doncic | Q17: =IFERROR(_xlfn.TEXTAFTER(_xlfn.XLOOKUP(A17,Collection!A:A,Collection!C:C,),"Cards "),C17) -> 2019 Panini Chronicles | R17: =IFERROR(_xlfn.TEXTBEFORE(_xlfn.TEXTAFTER(B17, "["), "]"), "-") -> Teal | S17: =IFERROR(_xlfn.TEXTAFTER(_xlfn.XLOOKUP(A17,Collection!A:A,Collection!B:B,),"#"),"") -> 15 | T17: =D17/100 -> 5.87 | U17: Luka Doncic | V17: =IF(ISNUMBER(MATCH(N17,Catalog!$B$4:$B$16, 0)), "Keep", "For Sale") -> For Sale | W17: =COUNTIFS(V:V,"For Sale",A:A,A17) -> 1 | X17: =_xlfn.LET( _xlpm.val,_xlfn.XLOOKUP(U17,AE:AE,AG:AG,)/100, _xlpm.tier,IF(_xlpm.val<1,5,IF(_xlpm.val<2,4,IF(_xlpm.val<5,3,IF(_xlpm.val<10,2,1)))), _xlpm.tier) -> 1 | Y17: =_xlfn.LET( _xlpm.price, (MAX(I17,D17,25)/100)*(1+$AC$3), _xlpm.rounder, IF(_xlpm.price < 1.5, FLOOR(_xlpm.price, 0.25), IF(_xlpm.price < 2.5, MROUND(_xlpm.price, 0.5), MROUND(_xlpm.price, 1))), MAX(0.25, _xlpm.rounder)) -> 7 | Z17: =_xlfn.LET( _xlpm.price, IF(I17=0, IF(W17>1,1-$AC$2,1)*(D17/100), MIN(IF(W17>1,1-$AC$2,1)*(D17/100), IF(W17>1,1-$AC$2,1)*(I17/100))), _xlpm.rounder, IF(_xlpm.price < 1.5, FLOOR(_xlpm.price, 0.25), IF(_xlpm.price < 2.5, MROUND(_xlpm.price, 0.5), MROUND(_xlpm.price, 1))), MAX(0.25, _xlpm.rounder)) -> 2 | AE17: Austin Reaves | AG17: 788.66667 | AI17: Stephen Curry | AJ17: 6
A18: 4536815 | B18: Luka Doncic [Holo] #15 | C18: Basketball Cards 2020 Panini Donruss Optic Splash | D18: 418 | E18: Ungraded | F18: Normal wear | H18: "https://www.whatnot.com/order/F9dPhgureZfuamzmCSWsoz_x000D_ $2.00 + $1.39 (Shared Shipping) + $0.35 Tax = Total of $3.74" | I18: 374 | J18: 1 | K18: 46174 | L18: 46173 | N18: 132 | P18: =TRIM(LEFT(B18, MIN(IFERROR(FIND("[", B18), LEN(B18)+1), IFERROR(FIND("#", B18), LEN(B18)+1)) - 1)) -> Luka Doncic | Q18: =IFERROR(_xlfn.TEXTAFTER(_xlfn.XLOOKUP(A18,Collection!A:A,Collection!C:C,),"Cards "),C18) -> 2020 Panini Donruss Optic Splash | R18: =IFERROR(_xlfn.TEXTBEFORE(_xlfn.TEXTAFTER(B18, "["), "]"), "-") -> Holo | S18: =IFERROR(_xlfn.TEXTAFTER(_xlfn.XLOOKUP(A18,Collection!A:A,Collection!B:B,),"#"),"") -> 15 | T18: =D18/100 -> 4.18 | U18: Luka Doncic | V18: =IF(ISNUMBER(MATCH(N18,Catalog!$B$4:$B$16, 0)), "Keep", "For Sale") -> For Sale | W18: =COUNTIFS(V:V,"For Sale",A:A,A18) -> 1 | X18: =_xlfn.LET( _xlpm.val,_xlfn.XLOOKUP(U18,AE:AE,AG:AG,)/100, _xlpm.tier,IF(_xlpm.val<1,5,IF(_xlpm.val<2,4,IF(_xlpm.val<5,3,IF(_xlpm.val<10,2,1)))), _xlpm.tier) -> 1 | Y18: =_xlfn.LET( _xlpm.price, (MAX(I18,D18,25)/100)*(1+$AC$3), _xlpm.rounder, IF(_xlpm.price < 1.5, FLOOR(_xlpm.price, 0.25), IF(_xlpm.price < 2.5, MROUND(_xlpm.price, 0.5), MROUND(_xlpm.price, 1))), MAX(0.25, _xlpm.rounder)) -> 5 | Z18: =_xlfn.LET( _xlpm.price, IF(I18=0, IF(W18>1,1-$AC$2,1)*(D18/100), MIN(IF(W18>1,1-$AC$2,1)*(D18/100), IF(W18>1,1-$AC$2,1)*(I18/100))), _xlpm.rounder, IF(_xlpm.price < 1.5, FLOOR(_xlpm.price, 0.25), IF(_xlpm.price < 2.5, MROUND(_xlpm.price, 0.5), MROUND(_xlpm.price, 1))), MAX(0.25, _xlpm.rounder)) -> 4 | AE18: Dirk Nowitzki | AG18: 680.75 | AI18: Shareef Abdur-Rahim | AJ18: 6
A19: 9960699 | B19: Luka Doncic [Green] #10 | C19: Basketball Cards 2024 Panini Mosaic Epic Performers | D19: 311 | E19: Ungraded | F19: Normal wear | H19: "whatnot.com/order/3YdoTRkTxViD7gGBZ6h9iY_x000D_ $2.00 + $0.63 (Shared Shipping) + $0.27 Tax = Total of $2.90" | I19: 290 | J19: 1 | K19: 46154 | L19: 46155 | N19: 155 | P19: =TRIM(LEFT(B19, MIN(IFERROR(FIND("[", B19), LEN(B19)+1), IFERROR(FIND("#", B19), LEN(B19)+1)) - 1)) -> Luka Doncic | Q19: =IFERROR(_xlfn.TEXTAFTER(_xlfn.XLOOKUP(A19,Collection!A:A,Collection!C:C,),"Cards "),C19) -> 2024 Panini Mosaic Epic Performers | R19: =IFERROR(_xlfn.TEXTBEFORE(_xlfn.TEXTAFTER(B19, "["), "]"), "-") -> Green | S19: =IFERROR(_xlfn.TEXTAFTER(_xlfn.XLOOKUP(A19,Collection!A:A,Collection!B:B,),"#"),"") -> 10 | T19: =D19/100 -> 3.11 | U19: Luka Doncic | V19: =IF(ISNUMBER(MATCH(N19,Catalog!$B$4:$B$16, 0)), "Keep", "For Sale") -> For Sale | W19: =COUNTIFS(V:V,"For Sale",A:A,A19) -> 2 | X19: =_xlfn.LET( _xlpm.val,_xlfn.XLOOKUP(U19,AE:AE,AG:AG,)/100, _xlpm.tier,IF(_xlpm.val<1,5,IF(_xlpm.val<2,4,IF(_xlpm.val<5,3,IF(_xlpm.val<10,2,1)))), _xlpm.tier) -> 1 | Y19: =_xlfn.LET( _xlpm.price, (MAX(I19,D19,25)/100)*(1+$AC$3), _xlpm.rounder, IF(_xlpm.price < 1.5, FLOOR(_xlpm.price, 0.25), IF(_xlpm.price < 2.5, MROUND(_xlpm.price, 0.5), MROUND(_xlpm.price, 1))), MAX(0.25, _xlpm.rounder)) -> 4 | Z19: =_xlfn.LET( _xlpm.price, IF(I19=0, IF(W19>1,1-$AC$2,1)*(D19/100), MIN(IF(W19>1,1-$AC$2,1)*(D19/100), IF(W19>1,1-$AC$2,1)*(I19/100))), _xlpm.rounder, IF(_xlpm.price < 1.5, FLOOR(_xlpm.price, 0.25), IF(_xlpm.price < 2.5, MROUND(_xlpm.price, 0.5), MROUND(_xlpm.price, 1))), MAX(0.25, _xlpm.rounder)) -> 2.5 | AE19: Gary Payton | AG19: 644.66667 | AI19: LeBron James | AJ19: 6
A20: 9960699 | B20: Luka Doncic [Green] #10 | C20: Basketball Cards 2024 Panini Mosaic Epic Performers | D20: 311 | E20: Ungraded | F20: Normal wear | H20: "whatnot.com/order/7eozouSEnosHtokHHfAAYH_x000D_ $1.67 + $1.02 (Shared Shipping) + $0.28 Tax = Total of $2.97" | I20: 297 | J20: 1 | K20: 46183 | L20: 46150 | N20: 156 | P20: =TRIM(LEFT(B20, MIN(IFERROR(FIND("[", B20), LEN(B20)+1), IFERROR(FIND("#", B20), LEN(B20)+1)) - 1)) -> Luka Doncic | Q20: =IFERROR(_xlfn.TEXTAFTER(_xlfn.XLOOKUP(A20,Collection!A:A,Collection!C:C,),"Cards "),C20) -> 2024 Panini Mosaic Epic Performers | R20: =IFERROR(_xlfn.TEXTBEFORE(_xlfn.TEXTAFTER(B20, "["), "]"), "-") -> Green | S20: =IFERROR(_xlfn.TEXTAFTER(_xlfn.XLOOKUP(A20,Collection!A:A,Collection!B:B,),"#"),"") -> 10 | T20: =D20/100 -> 3.11 | U20: Luka Doncic | V20: =IF(ISNUMBER(MATCH(N20,Catalog!$B$4:$B$16, 0)), "Keep", "For Sale") -> For Sale | W20: =COUNTIFS(V:V,"For Sale",A:A,A20) -> 2 | X20: =_xlfn.LET( _xlpm.val,_xlfn.XLOOKUP(U20,AE:AE,AG:AG,)/100, _xlpm.tier,IF(_xlpm.val<1,5,IF(_xlpm.val<2,4,IF(_xlpm.val<5,3,IF(_xlpm.val<10,2,1)))), _xlpm.tier) -> 1 | Y20: =_xlfn.LET( _xlpm.price, (MAX(I20,D20,25)/100)*(1+$AC$3), _xlpm.rounder, IF(_xlpm.price < 1.5, FLOOR(_xlpm.price, 0.25), IF(_xlpm.price < 2.5, MROUND(_xlpm.price, 0.5), MROUND(_xlpm.price, 1))), MAX(0.25, _xlpm.rounder)) -> 4 | Z20: =_xlfn.LET( _xlpm.price, IF(I20=0, IF(W20>1,1-$AC$2,1)*(D20/100), MIN(IF(W20>1,1-$AC$2,1)*(D20/100), IF(W20>1,1-$AC$2,1)*(I20/100))), _xlpm.rounder, IF(_xlpm.price < 1.5, FLOOR(_xlpm.price, 0.25), IF(_xlpm.price < 2.5, MROUND(_xlpm.price, 0.5), MROUND(_xlpm.price, 1))), MAX(0.25, _xlpm.rounder)) -> 3 | AE20: Wolverine Crippled | AG20: 636 | AI20: Sam Vincent | AJ20: 6
A21: 8846235 | B21: Luka Doncic [Green] #89 | C21: Basketball Cards 2024 Panini Prizm | D21: 302 | E21: Ungraded | F21: Normal wear | H21: "https://www.whatnot.com/order/Qz7U5ppnESxTUaQq9NtVok_x000D_ $2.00 + $0.55 (Shared Shipping) + $0.26 Tax = Total of $2.81" | I21: 281 | J21: 1 | K21: 46154 | L21: 46154 | N21: 215 | P21: =TRIM(LEFT(B21, MIN(IFERROR(FIND("[", B21), LEN(B21)+1), IFERROR(FIND("#", B21), LEN(B21)+1)) - 1)) -> Luka Doncic | Q21: =IFERROR(_xlfn.TEXTAFTER(_xlfn.XLOOKUP(A21,Collection!A:A,Collection!C:C,),"Cards "),C21) -> 2024 Panini Prizm | R21: =IFERROR(_xlfn.TEXTBEFORE(_xlfn.TEXTAFTER(B21, "["), "]"), "-") -> Green | S21: =IFERROR(_xlfn.TEXTAFTER(_xlfn.XLOOKUP(A21,Collection!A:A,Collection!B:B,),"#"),"") -> 89 | T21: =D21/100 -> 3.02 | U21: Luka Doncic | V21: =IF(ISNUMBER(MATCH(N21,Catalog!$B$4:$B$16, 0)), "Keep", "For Sale") -> For Sale | W21: =COUNTIFS(V:V,"For Sale",A:A,A21) -> 1 | X21: =_xlfn.LET( _xlpm.val,_xlfn.XLOOKUP(U21,AE:AE,AG:AG,)/100, _xlpm.tier,IF(_xlpm.val<1,5,IF(_xlpm.val<2,4,IF(_xlpm.val<5,3,IF(_xlpm.val<10,2,1)))), _xlpm.tier) -> 1 | Y21: =_xlfn.LET( _xlpm.price, (MAX(I21,D21,25)/100)*(1+$AC$3), _xlpm.rounder, IF(_xlpm.price < 1.5, FLOOR(_xlpm.price, 0.25), IF(_xlpm.price < 2.5, MROUND(_xlpm.price, 0.5), MROUND(_xlpm.price, 1))), MAX(0.25, _xlpm.rounder)) -> 4 | Z21: =_xlfn.LET( _xlpm.price, IF(I21=0, IF(W21>1,1-$AC$2,1)*(D21/100), MIN(IF(W21>1,1-$AC$2,1)*(D21/100), IF(W21>1,1-$AC$2,1)*(I21/100))), _xlpm.rounder, IF(_xlpm.price < 1.5, FLOOR(_xlpm.price, 0.25), IF(_xlpm.price < 2.5, MROUND(_xlpm.price, 0.5), MROUND(_xlpm.price, 1))), MAX(0.25, _xlpm.rounder)) -> 3 | AE21: Tyrese Maxey | AG21: 620 | AI21: JA Morant | AJ21: 5
A22: 2967050 | B22: Luka Doncic [Sapphire] #43 | C22: Basketball Cards 2020 Panini Illusions | D22: 300 | E22: Ungraded | F22: Normal wear | H22: "https://www.whatnot.com/order/QTaAU7BuEKWFVBSztLHVZt_x000D_ $2.00 + $0.36 (Shared Shipping) + $0.24 Tax = Total of $2.61" | I22: 261 | J22: 1 | K22: 46189 | L22: 46154 | N22: 176 | P22: =TRIM(LEFT(B22, MIN(IFERROR(FIND("[", B22), LEN(B22)+1), IFERROR(FIND("#", B22), LEN(B22)+1)) - 1)) -> Luka Doncic | Q22: =IFERROR(_xlfn.TEXTAFTER(_xlfn.XLOOKUP(A22,Collection!A:A,Collection!C:C,),"Cards "),C22) -> 2020 Panini Illusions | R22: =IFERROR(_xlfn.TEXTBEFORE(_xlfn.TEXTAFTER(B22, "["), "]"), "-") -> Sapphire | S22: =IFERROR(_xlfn.TEXTAFTER(_xlfn.XLOOKUP(A22,Collection!A:A,Collection!B:B,),"#"),"") -> 43 | T22: =D22/100 -> 3 | U22: Luka Doncic | V22: =IF(ISNUMBER(MATCH(N22,Catalog!$B$4:$B$16, 0)), "Keep", "For Sale") -> For Sale | W22: =COUNTIFS(V:V,"For Sale",A:A,A22) -> 1 | X22: =_xlfn.LET( _xlpm.val,_xlfn.XLOOKUP(U22,AE:AE,AG:AG,)/100, _xlpm.tier,IF(_xlpm.val<1,5,IF(_xlpm.val<2,4,IF(_xlpm.val<5,3,IF(_xlpm.val<10,2,1)))), _xlpm.tier) -> 1 | Y22: =_xlfn.LET( _xlpm.price, (MAX(I22,D22,25)/100)*(1+$AC$3), _xlpm.rounder, IF(_xlpm.price < 1.5, FLOOR(_xlpm.price, 0.25), IF(_xlpm.price < 2.5, MROUND(_xlpm.price, 0.5), MROUND(_xlpm.price, 1))), MAX(0.25, _xlpm.rounder)) -> 4 | Z22: =_xlfn.LET( _xlpm.price, IF(I22=0, IF(W22>1,1-$AC$2,1)*(D22/100), MIN(IF(W22>1,1-$AC$2,1)*(D22/100), IF(W22>1,1-$AC$2,1)*(I22/100))), _xlpm.rounder, IF(_xlpm.price < 1.5, FLOOR(_xlpm.price, 0.25), IF(_xlpm.price < 2.5, MROUND(_xlpm.price, 0.5), MROUND(_xlpm.price, 1))), MAX(0.25, _xlpm.rounder)) -> 3 | AE22: Ken Griffey Jr. | AG22: 616 | AI22: Austin Reaves | AJ22: 5
A23: 8537652 | B23: Luka Doncic [Pink Ice] #89 | C23: Basketball Cards 2024 Panini Prizm | D23: 288 | E23: Ungraded | F23: Normal wear | H23: "https://www.whatnot.com/order/aE4kEgCLAeDJfnfFh8U4bA_x000D_ $4.00 + $0.78 (Shared Shipping) + $0.49 Tax = Total of $5.27" | I23: 527 | J23: 1 | K23: 46159 | L23: 46159 | N23: 202 | P23: =TRIM(LEFT(B23, MIN(IFERROR(FIND("[", B23), LEN(B23)+1), IFERROR(FIND("#", B23), LEN(B23)+1)) - 1)) -> Luka Doncic | Q23: =IFERROR(_xlfn.TEXTAFTER(_xlfn.XLOOKUP(A23,Collection!A:A,Collection!C:C,),"Cards "),C23) -> 2024 Panini Prizm | R23: =IFERROR(_xlfn.TEXTBEFORE(_xlfn.TEXTAFTER(B23, "["), "]"), "-") -> Pink Ice | S23: =IFERROR(_xlfn.TEXTAFTER(_xlfn.XLOOKUP(A23,Collection!A:A,Collection!B:B,),"#"),"") -> 89 | T23: =D23/100 -> 2.88 | U23: Luka Doncic | V23: =IF(ISNUMBER(MATCH(N23,Catalog!$B$4:$B$16, 0)), "Keep", "For Sale") -> For Sale | W23: =COUNTIFS(V:V,"For Sale",A:A,A23) -> 1 | X23: =_xlfn.LET( _xlpm.val,_xlfn.XLOOKUP(U23,AE:AE,AG:AG,)/100, _xlpm.tier,IF(_xlpm.val<1,5,IF(_xlpm.val<2,4,IF(_xlpm.val<5,3,IF(_xlpm.val<10,2,1)))), _xlpm.tier) -> 1 | Y23: =_xlfn.LET( _xlpm.price, (MAX(I23,D23,25)/100)*(1+$AC$3), _xlpm.rounder, IF(_xlpm.price < 1.5, FLOOR(_xlpm.price, 0.25), IF(_xlpm.price < 2.5, MROUND(_xlpm.price, 0.5), MROUND(_xlpm.price, 1))), MAX(0.25, _xlpm.rounder)) -> 6 | Z23: =_xlfn.LET( _xlpm.price, IF(I23=0, IF(W23>1,1-$AC$2,1)*(D23/100), MIN(IF(W23>1,1-$AC$2,1)*(D23/100), IF(W23>1,1-$AC$2,1)*(I23/100))), _xlpm.rounder, IF(_xlpm.price < 1.5, FLOOR(_xlpm.price, 0.25), IF(_xlpm.price < 2.5, MROUND(_xlpm.price, 0.5), MROUND(_xlpm.price, 1))), MAX(0.25, _xlpm.rounder)) -> 3 | AE23: Grant Hill | AG23: 573.5 | AI23: Charles Barkley | AJ23: 5
A24: 5507557 | B24: Luka Doncic [Pink] #257 | C24: Basketball Cards 2022 Panini Chronicles | D24: 244 | E24: Ungraded | F24: Normal wear | H24: "https://www.whatnot.com/order/PH2i3WhAY5rePqutCdgM8c_x000D_ $1.29 + $0.29 (Shared Shipping) + $0.16 Tax = Total of $1.74" | I24: 174 | J24: 1 | K24: 46166 | L24: 46164 | N24: 210 | P24: =TRIM(LEFT(B24, MIN(IFERROR(FIND("[", B24), LEN(B24)+1), IFERROR(FIND("#", B24), LEN(B24)+1)) - 1)) -> Luka Doncic | Q24: =IFERROR(_xlfn.TEXTAFTER(_xlfn.XLOOKUP(A24,Collection!A:A,Collection!C:C,),"Cards "),C24) -> 2022 Panini Chronicles | R24: =IFERROR(_xlfn.TEXTBEFORE(_xlfn.TEXTAFTER(B24, "["), "]"), "-") -> Pink | S24: =IFERROR(_xlfn.TEXTAFTER(_xlfn.XLOOKUP(A24,Collection!A:A,Collection!B:B,),"#"),"") -> 257 | T24: =D24/100 -> 2.44 | U24: Luka Doncic | V24: =IF(ISNUMBER(MATCH(N24,Catalog!$B$4:$B$16, 0)), "Keep", "For Sale") -> For Sale | W24: =COUNTIFS(V:V,"For Sale",A:A,A24) -> 1 | X24: =_xlfn.LET( _xlpm.val,_xlfn.XLOOKUP(U24,AE:AE,AG:AG,)/100, _xlpm.tier,IF(_xlpm.val<1,5,IF(_xlpm.val<2,4,IF(_xlpm.val<5,3,IF(_xlpm.val<10,2,1)))), _xlpm.tier) -> 1 | Y24: =_xlfn.LET( _xlpm.price, (MAX(I24,D24,25)/100)*(1+$AC$3), _xlpm.rounder, IF(_xlpm.price < 1.5, FLOOR(_xlpm.price, 0.25), IF(_xlpm.price < 2.5, MROUND(_xlpm.price, 0.5), MROUND(_xlpm.price, 1))), MAX(0.25, _xlpm.rounder)) -> 3 | Z24: =_xlfn.LET( _xlpm.price, IF(I24=0, IF(W24>1,1-$AC$2,1)*(D24/100), MIN(IF(W24>1,1-$AC$2,1)*(D24/100), IF(W24>1,1-$AC$2,1)*(I24/100))), _xlpm.rounder, IF(_xlpm.price < 1.5, FLOOR(_xlpm.price, 0.25), IF(_xlpm.price < 2.5, MROUND(_xlpm.price, 0.5), MROUND(_xlpm.price, 1))), MAX(0.25, _xlpm.rounder)) -> 1.5 | AE24: Return of Excellence | AG24: 492 | AI24: Cooper Flagg | AJ24: 5
A25: 920589 | B25: Luka Doncic #254 | C25: Basketball Cards 2019 Panini Chronicles | D25: 238 | E25: Ungraded | F25: Normal wear | H25: "https://www.whatnot.com/order/GhBCHwczCmrh6F7iQjEyTX_x000D_ $1.43 + $0.29 (Shared Shipping) + $0.18 Tax = Total of $1.90" | I25: 190 | J25: 1 | K25: 46166 | L25: 46164 | N25: 336 | P25: =TRIM(LEFT(B25, MIN(IFERROR(FIND("[", B25), LEN(B25)+1), IFERROR(FIND("#", B25), LEN(B25)+1)) - 1)) -> Luka Doncic | Q25: =IFERROR(_xlfn.TEXTAFTER(_xlfn.XLOOKUP(A25,Collection!A:A,Collection!C:C,),"Cards "),C25) -> 2019 Panini Chronicles | R25: =IFERROR(_xlfn.TEXTBEFORE(_xlfn.TEXTAFTER(B25, "["), "]"), "-") -> - | S25: =IFERROR(_xlfn.TEXTAFTER(_xlfn.XLOOKUP(A25,Collection!A:A,Collection!B:B,),"#"),"") -> 254 | T25: =D25/100 -> 2.38 | U25: Luka Doncic | V25: =IF(ISNUMBER(MATCH(N25,Catalog!$B$4:$B$16, 0)), "Keep", "For Sale") -> For Sale | W25: =COUNTIFS(V:V,"For Sale",A:A,A25) -> 1 | X25: =_xlfn.LET( _xlpm.val,_xlfn.XLOOKUP(U25,AE:AE,AG:AG,)/100, _xlpm.tier,IF(_xlpm.val<1,5,IF(_xlpm.val<2,4,IF(_xlpm.val<5,3,IF(_xlpm.val<10,2,1)))), _xlpm.tier) -> 1 | Y25: =_xlfn.LET( _xlpm.price, (MAX(I25,D25,25)/100)*(1+$AC$3), _xlpm.rounder, IF(_xlpm.price < 1.5, FLOOR(_xlpm.price, 0.25), IF(_xlpm.price < 2.5, MROUND(_xlpm.price, 0.5), MROUND(_xlpm.price, 1))), MAX(0.25, _xlpm.rounder)) -> 3 | Z25: =_xlfn.LET( _xlpm.price, IF(I25=0, IF(W25>1,1-$AC$2,1)*(D25/100), MIN(IF(W25>1,1-$AC$2,1)*(D25/100), IF(W25>1,1-$AC$2,1)*(I25/100))), _xlpm.rounder, IF(_xlpm.price < 1.5, FLOOR(_xlpm.price, 0.25), IF(_xlpm.price < 2.5, MROUND(_xlpm.price, 0.5), MROUND(_xlpm.price, 1))), MAX(0.25, _xlpm.rounder)) -> 2 | AE25: Charles Barkley | AG25: 470.66667 | AI25: Anfernee Hardaway | AJ25: 5
... A86: 3351202 | B86: Mac McClung #39 | C86: Basketball Cards 2021 Panini Prizm Draft Picks | D86: 149 | E86: Ungraded | F86: Normal wear | H86: "https://www.whatnot.com/order/4zv9Y8T8uHjVEzhSWdVnjf_x000D_ $4.00 + $0.00 (Shared Shipping) + $0.41 Tax = Total of $4.41" | I86: 441 | J86: 1 | K86: 46182 | L86: 46181 | N86: 429 | P86: =TRIM(LEFT(B86, MIN(IFERROR(FIND("[", B86), LEN(B86)+1), IFERROR(FIND("#", B86), LEN(B86)+1)) - 1)) -> Mac McClung | Q86: =IFERROR(_xlfn.TEXTAFTER(_xlfn.XLOOKUP(A86,Collection!A:A,Collection!C:C,),"Cards "),C86) -> 2021 Panini Prizm Draft Picks | R86: =IFERROR(_xlfn.TEXTBEFORE(_xlfn.TEXTAFTER(B86, "["), "]"), "-") -> - | S86: =IFERROR(_xlfn.TEXTAFTER(_xlfn.XLOOKUP(A86,Collection!A:A,Collection!B:B,),"#"),"") -> 39 | T86: =D86/100 -> 1.49 | U86: Mac McClung | V86: =IF(ISNUMBER(MATCH(N86,Catalog!$B$4:$B$16, 0)), "Keep", "For Sale") -> For Sale | W86: =COUNTIFS(V:V,"For Sale",A:A,A86) -> 1 | X86: =_xlfn.LET( _xlpm.val,_xlfn.XLOOKUP(U86,AE:AE,AG:AG,)/100, _xlpm.tier,IF(_xlpm.val<1,5,IF(_xlpm.val<2,4,IF(_xlpm.val<5,3,IF(_xlpm.val<10,2,1)))), _xlpm.tier) -> 1 | Y86: =_xlfn.LET( _xlpm.price, (MAX(I86,D86,25)/100)*(1+$AC$3), _xlpm.rounder, IF(_xlpm.price < 1.5, FLOOR(_xlpm.price, 0.25), IF(_xlpm.price < 2.5, MROUND(_xlpm.price, 0.5), MROUND(_xlpm.price, 1))), MAX(0.25, _xlpm.rounder)) -> 5 | Z86: =_xlfn.LET( _xlpm.price, IF(I86=0, IF(W86>1,1-$AC$2,1)*(D86/100), MIN(IF(W86>1,1-$AC$2,1)*(D86/100), IF(W86>1,1-$AC$2,1)*(I86/100))), _xlpm.rounder, IF(_xlpm.price < 1.5, FLOOR(_xlpm.price, 0.25), IF(_xlpm.price < 2.5, MROUND(_xlpm.price, 0.5), MROUND(_xlpm.price, 1))), MAX(0.25, _xlpm.rounder)) -> 1.25 | AE86: Jalen Brunson | AG86: 177 | AI86: David Platt | AJ86: 1
A87: 89006 | B87: Michael Jordan #23 | C87: Basketball Cards 1997 Metal Universe | D87: 28311 | E87: Ungraded | F87: Normal wear | I87: 500 | J87: 1 | K87: 46183 | N87: 1 | P87: =TRIM(LEFT(B87, MIN(IFERROR(FIND("[", B87), LEN(B87)+1), IFERROR(FIND("#", B87), LEN(B87)+1)) - 1)) -> Michael Jordan | Q87: =IFERROR(_xlfn.TEXTAFTER(_xlfn.XLOOKUP(A87,Collection!A:A,Collection!C:C,),"Cards "),C87) -> 1997 Metal Universe | R87: =IFERROR(_xlfn.TEXTBEFORE(_xlfn.TEXTAFTER(B87, "["), "]"), "-") -> - | S87: =IFERROR(_xlfn.TEXTAFTER(_xlfn.XLOOKUP(A87,Collection!A:A,Collection!B:B,),"#"),"") -> 23 | T87: =D87/100 -> 283.11 | U87: Michael Jordan | V87: =IF(ISNUMBER(MATCH(N87,Catalog!$B$4:$B$16, 0)), "Keep", "For Sale") -> Keep | W87: =COUNTIFS(V:V,"For Sale",A:A,A87) -> 0 | X87: =_xlfn.LET( _xlpm.val,_xlfn.XLOOKUP(U87,AE:AE,AG:AG,)/100, _xlpm.tier,IF(_xlpm.val<1,5,IF(_xlpm.val<2,4,IF(_xlpm.val<5,3,IF(_xlpm.val<10,2,1)))), _xlpm.tier) -> 1 | Y87: =_xlfn.LET( _xlpm.price, (MAX(I87,D87,25)/100)*(1+$AC$3), _xlpm.rounder, IF(_xlpm.price < 1.5, FLOOR(_xlpm.price, 0.25), IF(_xlpm.price < 2.5, MROUND(_xlpm.price, 0.5), MROUND(_xlpm.price, 1))), MAX(0.25, _xlpm.rounder)) -> 340 | Z87: =_xlfn.LET( _xlpm.price, IF(I87=0, IF(W87>1,1-$AC$2,1)*(D87/100), MIN(IF(W87>1,1-$AC$2,1)*(D87/100), IF(W87>1,1-$AC$2,1)*(I87/100))), _xlpm.rounder, IF(_xlpm.price < 1.5, FLOOR(_xlpm.price, 0.25), IF(_xlpm.price < 2.5, MROUND(_xlpm.price, 0.5), MROUND(_xlpm.price, 1))), MAX(0.25, _xlpm.rounder)) -> 5 | AE87: Bam Adebayo | AG87: 175 | AI87: Cotie McMahon | AJ87: 1
A88: 85372 | B88: Michael Jordan #11 | C88: Basketball Cards 1996 Fleer Metal | D88: 5000 | E88: Ungraded | F88: Normal wear | I88: 500 | J88: 1 | K88: 46197 | N88: 11 | P88: =TRIM(LEFT(B88, MIN(IFERROR(FIND("[", B88), LEN(B88)+1), IFERROR(FIND("#", B88), LEN(B88)+1)) - 1)) -> Michael Jordan | Q88: =IFERROR(_xlfn.TEXTAFTER(_xlfn.XLOOKUP(A88,Collection!A:A,Collection!C:C,),"Cards "),C88) -> 1996 Fleer Metal | R88: =IFERROR(_xlfn.TEXTBEFORE(_xlfn.TEXTAFTER(B88, "["), "]"), "-") -> - | S88: =IFERROR(_xlfn.TEXTAFTER(_xlfn.XLOOKUP(A88,Collection!A:A,Collection!B:B,),"#"),"") -> 11 | T88: =D88/100 -> 50 | U88: Michael Jordan | V88: =IF(ISNUMBER(MATCH(N88,Catalog!$B$4:$B$16, 0)), "Keep", "For Sale") -> Keep | W88: =COUNTIFS(V:V,"For Sale",A:A,A88) -> 1 | X88: =_xlfn.LET( _xlpm.val,_xlfn.XLOOKUP(U88,AE:AE,AG:AG,)/100, _xlpm.tier,IF(_xlpm.val<1,5,IF(_xlpm.val<2,4,IF(_xlpm.val<5,3,IF(_xlpm.val<10,2,1)))), _xlpm.tier) -> 1 | Y88: =_xlfn.LET( _xlpm.price, (MAX(I88,D88,25)/100)*(1+$AC$3), _xlpm.rounder, IF(_xlpm.price < 1.5, FLOOR(_xlpm.price, 0.25), IF(_xlpm.price < 2.5, MROUND(_xlpm.price, 0.5), MROUND(_xlpm.price, 1))), MAX(0.25, _xlpm.rounder)) -> 60 | Z88: =_xlfn.LET( _xlpm.price, IF(I88=0, IF(W88>1,1-$AC$2,1)*(D88/100), MIN(IF(W88>1,1-$AC$2,1)*(D88/100), IF(W88>1,1-$AC$2,1)*(I88/100))), _xlpm.rounder, IF(_xlpm.price < 1.5, FLOOR(_xlpm.price, 0.25), IF(_xlpm.price < 2.5, MROUND(_xlpm.price, 0.5), MROUND(_xlpm.price, 1))), MAX(0.25, _xlpm.rounder)) -> 5 | AE88: Terrence Shannon Jr. | AG88: 175 | AI88: Heathcliff Slocumb | AJ88: 1
A89: 85372 | B89: Michael Jordan #11 | C89: Basketball Cards 1996 Fleer Metal | D89: 5000 | E89: Ungraded | F89: Normal wear | I89: 500 | J89: 1 | K89: 46183 | N89: 3 | P89: =TRIM(LEFT(B89, MIN(IFERROR(FIND("[", B89), LEN(B89)+1), IFERROR(FIND("#", B89), LEN(B89)+1)) - 1)) -> Michael Jordan | Q89: =IFERROR(_xlfn.TEXTAFTER(_xlfn.XLOOKUP(A89,Collection!A:A,Collection!C:C,),"Cards "),C89) -> 1996 Fleer Metal | R89: =IFERROR(_xlfn.TEXTBEFORE(_xlfn.TEXTAFTER(B89, "["), "]"), "-") -> - | S89: =IFERROR(_xlfn.TEXTAFTER(_xlfn.XLOOKUP(A89,Collection!A:A,Collection!B:B,),"#"),"") -> 11 | T89: =D89/100 -> 50 | U89: Michael Jordan | V89: =IF(ISNUMBER(MATCH(N89,Catalog!$B$4:$B$16, 0)), "Keep", "For Sale") -> For Sale | W89: =COUNTIFS(V:V,"For Sale",A:A,A89) -> 1 | X89: =_xlfn.LET( _xlpm.val,_xlfn.XLOOKUP(U89,AE:AE,AG:AG,)/100, _xlpm.tier,IF(_xlpm.val<1,5,IF(_xlpm.val<2,4,IF(_xlpm.val<5,3,IF(_xlpm.val<10,2,1)))), _xlpm.tier) -> 1 | Y89: =_xlfn.LET( _xlpm.price, (MAX(I89,D89,25)/100)*(1+$AC$3), _xlpm.rounder, IF(_xlpm.price < 1.5, FLOOR(_xlpm.price, 0.25), IF(_xlpm.price < 2.5, MROUND(_xlpm.price, 0.5), MROUND(_xlpm.price, 1))), MAX(0.25, _xlpm.rounder)) -> 60 | Z89: =_xlfn.LET( _xlpm.price, IF(I89=0, IF(W89>1,1-$AC$2,1)*(D89/100), MIN(IF(W89>1,1-$AC$2,1)*(D89/100), IF(W89>1,1-$AC$2,1)*(I89/100))), _xlpm.rounder, IF(_xlpm.price < 1.5, FLOOR(_xlpm.price, 0.25), IF(_xlpm.price < 2.5, MROUND(_xlpm.price, 0.5), MROUND(_xlpm.price, 1))), MAX(0.25, _xlpm.rounder)) -> 5 | AE89: Marcus Camby | AG89: 174.33333 | AI89: Tim Teufel | AJ89: 1
A90: 85449 | B90: Michael Jordan #241 | C90: Basketball Cards 1996 Fleer Metal | D90: 3049 | E90: Ungraded | F90: Normal wear | I90: 250 | J90: 1 | K90: 46129 | N90: 7 | P90: =TRIM(LEFT(B90, MIN(IFERROR(FIND("[", B90), LEN(B90)+1), IFERROR(FIND("#", B90), LEN(B90)+1)) - 1)) -> Michael Jordan | Q90: =IFERROR(_xlfn.TEXTAFTER(_xlfn.XLOOKUP(A90,Collection!A:A,Collection!C:C,),"Cards "),C90) -> 1996 Fleer Metal | R90: =IFERROR(_xlfn.TEXTBEFORE(_xlfn.TEXTAFTER(B90, "["), "]"), "-") -> - | S90: =IFERROR(_xlfn.TEXTAFTER(_xlfn.XLOOKUP(A90,Collection!A:A,Collection!B:B,),"#"),"") -> 241 | T90: =D90/100 -> 30.49 | U90: Michael Jordan | V90: =IF(ISNUMBER(MATCH(N90,Catalog!$B$4:$B$16, 0)), "Keep", "For Sale") -> For Sale | W90: =COUNTIFS(V:V,"For Sale",A:A,A90) -> 1 | X90: =_xlfn.LET( _xlpm.val,_xlfn.XLOOKUP(U90,AE:AE,AG:AG,)/100, _xlpm.tier,IF(_xlpm.val<1,5,IF(_xlpm.val<2,4,IF(_xlpm.val<5,3,IF(_xlpm.val<10,2,1)))), _xlpm.tier) -> 1 | Y90: =_xlfn.LET( _xlpm.price, (MAX(I90,D90,25)/100)*(1+$AC$3), _xlpm.rounder, IF(_xlpm.price < 1.5, FLOOR(_xlpm.price, 0.25), IF(_xlpm.price < 2.5, MROUND(_xlpm.price, 0.5), MROUND(_xlpm.price, 1))), MAX(0.25, _xlpm.rounder)) -> 37 | Z90: =_xlfn.LET( _xlpm.price, IF(I90=0, IF(W90>1,1-$AC$2,1)*(D90/100), MIN(IF(W90>1,1-$AC$2,1)*(D90/100), IF(W90>1,1-$AC$2,1)*(I90/100))), _xlpm.rounder, IF(_xlpm.price < 1.5, FLOOR(_xlpm.price, 0.25), IF(_xlpm.price < 2.5, MROUND(_xlpm.price, 0.5), MROUND(_xlpm.price, 1))), MAX(0.25, _xlpm.rounder)) -> 3 | AE90: Cade Cunningham | AG90: 173.5 | AI90: Kevin Morton | AJ90: 1
A91: 3225488 | B91: Michael Jordan #100 | C91: Basketball Cards 1994 E Motion | D91: 2970 | E91: Ungraded | F91: Normal wear | H91: "ebay.com/itm/298423082887_x000D_ $20.00 + $5.48 (Shared Shipping) + $2.61 Tax = Total of $28.09" | I91: 2809 | J91: 1 | K91: 46195 | L91: 46194 | N91: 8 | P91: =TRIM(LEFT(B91, MIN(IFERROR(FIND("[", B91), LEN(B91)+1), IFERROR(FIND("#", B91), LEN(B91)+1)) - 1)) -> Michael Jordan | Q91: =IFERROR(_xlfn.TEXTAFTER(_xlfn.XLOOKUP(A91,Collection!A:A,Collection!C:C,),"Cards "),C91) -> 1994 E Motion | R91: =IFERROR(_xlfn.TEXTBEFORE(_xlfn.TEXTAFTER(B91, "["), "]"), "-") -> - | S91: =IFERROR(_xlfn.TEXTAFTER(_xlfn.XLOOKUP(A91,Collection!A:A,Collection!B:B,),"#"),"") -> 100 | T91: =D91/100 -> 29.7 | U91: Michael Jordan | V91: =IF(ISNUMBER(MATCH(N91,Catalog!$B$4:$B$16, 0)), "Keep", "For Sale") -> Keep | W91: =COUNTIFS(V:V,"For Sale",A:A,A91) -> 0 | X91: =_xlfn.LET( _xlpm.val,_xlfn.XLOOKUP(U91,AE:AE,AG:AG,)/100, _xlpm.tier,IF(_xlpm.val<1,5,IF(_xlpm.val<2,4,IF(_xlpm.val<5,3,IF(_xlpm.val<10,2,1)))), _xlpm.tier) -> 1 | Y91: =_xlfn.LET( _xlpm.price, (MAX(I91,D91,25)/100)*(1+$AC$3), _xlpm.rounder, IF(_xlpm.price < 1.5, FLOOR(_xlpm.price, 0.25), IF(_xlpm.price < 2.5, MROUND(_xlpm.price, 0.5), MROUND(_xlpm.price, 1))), MAX(0.25, _xlpm.rounder)) -> 36 | Z91: =_xlfn.LET( _xlpm.price, IF(I91=0, IF(W91>1,1-$AC$2,1)*(D91/100), MIN(IF(W91>1,1-$AC$2,1)*(D91/100), IF(W91>1,1-$AC$2,1)*(I91/100))), _xlpm.rounder, IF(_xlpm.price < 1.5, FLOOR(_xlpm.price, 0.25), IF(_xlpm.price < 2.5, MROUND(_xlpm.price, 0.5), MROUND(_xlpm.price, 1))), MAX(0.25, _xlpm.rounder)) -> 28 | AE91: Dyson Daniels | AG91: 170 | AI91: Wolverine Crippled | AJ91: 1
A92: 3279930 | B92: Michael Jordan #T59 | C92: Basketball Cards 1997 Upper Deck Teammates | D92: 2152 | E92: Ungraded | F92: Normal wear | I92: 0 | J92: 1 | K92: 46127 | N92: 10 | P92: =TRIM(LEFT(B92, MIN(IFERROR(FIND("[", B92), LEN(B92)+1), IFERROR(FIND("#", B92), LEN(B92)+1)) - 1)) -> Michael Jordan | Q92: =IFERROR(_xlfn.TEXTAFTER(_xlfn.XLOOKUP(A92,Collection!A:A,Collection!C:C,),"Cards "),C92) -> 1997 Upper Deck Teammates | R92: =IFERROR(_xlfn.TEXTBEFORE(_xlfn.TEXTAFTER(B92, "["), "]"), "-") -> - | S92: =IFERROR(_xlfn.TEXTAFTER(_xlfn.XLOOKUP(A92,Collection!A:A,Collection!B:B,),"#"),"") -> T59 | T92: =D92/100 -> 21.52 | U92: Michael Jordan | V92: =IF(ISNUMBER(MATCH(N92,Catalog!$B$4:$B$16, 0)), "Keep", "For Sale") -> For Sale | W92: =COUNTIFS(V:V,"For Sale",A:A,A92) -> 1 | X92: =_xlfn.LET( _xlpm.val,_xlfn.XLOOKUP(U92,AE:AE,AG:AG,)/100, _xlpm.tier,IF(_xlpm.val<1,5,IF(_xlpm.val<2,4,IF(_xlpm.val<5,3,IF(_xlpm.val<10,2,1)))), _xlpm.tier) -> 1 | Y92: =_xlfn.LET( _xlpm.price, (MAX(I92,D92,25)/100)*(1+$AC$3), _xlpm.rounder, IF(_xlpm.price < 1.5, FLOOR(_xlpm.price, 0.25), IF(_xlpm.price < 2.5, MROUND(_xlpm.price, 0.5), MROUND(_xlpm.price, 1))), MAX(0.25, _xlpm.rounder)) -> 26 | Z92: =_xlfn.LET( _xlpm.price, IF(I92=0, IF(W92>1,1-$AC$2,1)*(D92/100), MIN(IF(W92>1,1-$AC$2,1)*(D92/100), IF(W92>1,1-$AC$2,1)*(I92/100))), _xlpm.rounder, IF(_xlpm.price < 1.5, FLOOR(_xlpm.price, 0.25), IF(_xlpm.price < 2.5, MROUND(_xlpm.price, 0.5), MROUND(_xlpm.price, 1))), MAX(0.25, _xlpm.rounder)) -> 22 | AE92: Jerry Rice | AG92: 166 | AI92: Delanie Walker | AJ92: 1
A93: 1951621 | B93: Michael Jordan #SP1 | C93: Baseball Cards 1991 Upper Deck | D93: 2034 | E93: Ungraded | F93: Normal wear | I93: 0 | J93: 1 | K93: 46129 | N93: 9 | P93: =TRIM(LEFT(B93, MIN(IFERROR(FIND("[", B93), LEN(B93)+1), IFERROR(FIND("#", B93), LEN(B93)+1)) - 1)) -> Michael Jordan | Q93: =IFERROR(_xlfn.TEXTAFTER(_xlfn.XLOOKUP(A93,Collection!A:A,Collection!C:C,),"Cards "),C93) -> 1991 Upper Deck | R93: =IFERROR(_xlfn.TEXTBEFORE(_xlfn.TEXTAFTER(B93, "["), "]"), "-") -> - | S93: =IFERROR(_xlfn.TEXTAFTER(_xlfn.XLOOKUP(A93,Collection!A:A,Collection!B:B,),"#"),"") -> SP1 | T93: =D93/100 -> 20.34 | U93: Michael Jordan | V93: =IF(ISNUMBER(MATCH(N93,Catalog!$B$4:$B$16, 0)), "Keep", "For Sale") -> For Sale | W93: =COUNTIFS(V:V,"For Sale",A:A,A93) -> 1 | X93: =_xlfn.LET( _xlpm.val,_xlfn.XLOOKUP(U93,AE:AE,AG:AG,)/100, _xlpm.tier,IF(_xlpm.val<1,5,IF(_xlpm.val<2,4,IF(_xlpm.val<5,3,IF(_xlpm.val<10,2,1)))), _xlpm.tier) -> 1 | Y93: =_xlfn.LET( _xlpm.price, (MAX(I93,D93,25)/100)*(1+$AC$3), _xlpm.rounder, IF(_xlpm.price < 1.5, FLOOR(_xlpm.price, 0.25), IF(_xlpm.price < 2.5, MROUND(_xlpm.price, 0.5), MROUND(_xlpm.price, 1))), MAX(0.25, _xlpm.rounder)) -> 24 | Z93: =_xlfn.LET( _xlpm.price, IF(I93=0, IF(W93>1,1-$AC$2,1)*(D93/100), MIN(IF(W93>1,1-$AC$2,1)*(D93/100), IF(W93>1,1-$AC$2,1)*(I93/100))), _xlpm.rounder, IF(_xlpm.price < 1.5, FLOOR(_xlpm.price, 0.25), IF(_xlpm.price < 2.5, MROUND(_xlpm.price, 0.5), MROUND(_xlpm.price, 1))), MAX(0.25, _xlpm.rounder)) -> 20 | AE93: Anthony Edwards | AG93: 166 | AI93: Edmundo | AJ93: 1
A94: 85637 | B94: Michael Jordan #16 | C94: Basketball Cards 1996 Skybox Premium | D94: 1573 | E94: Ungraded | F94: Normal wear | I94: 0 | J94: 1 | K94: 46183 | N94: 17 | P94: =TRIM(LEFT(B94, MIN(IFERROR(FIND("[", B94), LEN(B94)+1), IFERROR(FIND("#", B94), LEN(B94)+1)) - 1)) -> Michael Jordan | Q94: =IFERROR(_xlfn.TEXTAFTER(_xlfn.XLOOKUP(A94,Collection!A:A,Collection!C:C,),"Cards "),C94) -> 1996 Skybox Premium | R94: =IFERROR(_xlfn.TEXTBEFORE(_xlfn.TEXTAFTER(B94, "["), "]"), "-") -> - | S94: =IFERROR(_xlfn.TEXTAFTER(_xlfn.XLOOKUP(A94,Collection!A:A,Collection!B:B,),"#"),"") -> 16 | T94: =D94/100 -> 15.73 | U94: Michael Jordan | V94: =IF(ISNUMBER(MATCH(N94,Catalog!$B$4:$B$16, 0)), "Keep", "For Sale") -> For Sale | W94: =COUNTIFS(V:V,"For Sale",A:A,A94) -> 2 | X94: =_xlfn.LET( _xlpm.val,_xlfn.XLOOKUP(U94,AE:AE,AG:AG,)/100, _xlpm.tier,IF(_xlpm.val<1,5,IF(_xlpm.val<2,4,IF(_xlpm.val<5,3,IF(_xlpm.val<10,2,1)))), _xlpm.tier) -> 1 | Y94: =_xlfn.LET( _xlpm.price, (MAX(I94,D94,25)/100)*(1+$AC$3), _xlpm.rounder, IF(_xlpm.price < 1.5, FLOOR(_xlpm.price, 0.25), IF(_xlpm.price < 2.5, MROUND(_xlpm.price, 0.5), MROUND(_xlpm.price, 1))), MAX(0.25, _xlpm.rounder)) -> 19 | Z94: =_xlfn.LET( _xlpm.price, IF(I94=0, IF(W94>1,1-$AC$2,1)*(D94/100), MIN(IF(W94>1,1-$AC$2,1)*(D94/100), IF(W94>1,1-$AC$2,1)*(I94/100))), _xlpm.rounder, IF(_xlpm.price < 1.5, FLOOR(_xlpm.price, 0.25), IF(_xlpm.price < 2.5, MROUND(_xlpm.price, 0.5), MROUND(_xlpm.price, 1))), MAX(0.25, _xlpm.rounder)) -> 13 | AE94: Larry Bird | AG94: 165.5 | AI94: Kyle Pitts | AJ94: 1
A95: 85637 | B95: Michael Jordan #16 | C95: Basketball Cards 1996 Skybox Premium | D95: 1573 | E95: Ungraded | F95: Normal wear | I95: 0 | J95: 1 | K95: 46128 | L95: 46128 | N95: 18 | P95: =TRIM(LEFT(B95, MIN(IFERROR(FIND("[", B95), LEN(B95)+1), IFERROR(FIND("#", B95), LEN(B95)+1)) - 1)) -> Michael Jordan | Q95: =IFERROR(_xlfn.TEXTAFTER(_xlfn.XLOOKUP(A95,Collection!A:A,Collection!C:C,),"Cards "),C95) -> 1996 Skybox Premium | R95: =IFERROR(_xlfn.TEXTBEFORE(_xlfn.TEXTAFTER(B95, "["), "]"), "-") -> - | S95: =IFERROR(_xlfn.TEXTAFTER(_xlfn.XLOOKUP(A95,Collection!A:A,Collection!B:B,),"#"),"") -> 16 | T95: =D95/100 -> 15.73 | U95: Michael Jordan | V95: =IF(ISNUMBER(MATCH(N95,Catalog!$B$4:$B$16, 0)), "Keep", "For Sale") -> For Sale | W95: =COUNTIFS(V:V,"For Sale",A:A,A95) -> 2 | X95: =_xlfn.LET( _xlpm.val,_xlfn.XLOOKUP(U95,AE:AE,AG:AG,)/100, _xlpm.tier,IF(_xlpm.val<1,5,IF(_xlpm.val<2,4,IF(_xlpm.val<5,3,IF(_xlpm.val<10,2,1)))), _xlpm.tier) -> 1 | Y95: =_xlfn.LET( _xlpm.price, (MAX(I95,D95,25)/100)*(1+$AC$3), _xlpm.rounder, IF(_xlpm.price < 1.5, FLOOR(_xlpm.price, 0.25), IF(_xlpm.price < 2.5, MROUND(_xlpm.price, 0.5), MROUND(_xlpm.price, 1))), MAX(0.25, _xlpm.rounder)) -> 19 | Z95: =_xlfn.LET( _xlpm.price, IF(I95=0, IF(W95>1,1-$AC$2,1)*(D95/100), MIN(IF(W95>1,1-$AC$2,1)*(D95/100), IF(W95>1,1-$AC$2,1)*(I95/100))), _xlpm.rounder, IF(_xlpm.price < 1.5, FLOOR(_xlpm.price, 0.25), IF(_xlpm.price < 2.5, MROUND(_xlpm.price, 0.5), MROUND(_xlpm.price, 1))), MAX(0.25, _xlpm.rounder)) -> 13 | AE95: Ray Allen | AG95: 158 | AI95: Ruud Gullit | AJ95: 1
